Workbook

Sheet Cover
B2: Variance-to-Action FP&A Model
B3: Fictional Indian D2C brand · FY27 budget, variance analysis and rolling forecast
B4: Prepared by | C4: Debayan Bandyopadhyay
B5: The company is FICTIONAL. Cost ratios are benchmarked to Honasa Consumer FY26 public disclosures; no real company financials are represented.
B7: Snapshot
B8: FY26 net revenue (₹ crore) | F8: ='Historical Data'!AB12/100 -> 399.99959
B9: FY26 EBITDA margin | F9: ='Historical Data'!AB40 -> 0.10024407
B10: FY27 budget net revenue (₹ crore) | F10: ='Assumptions & Budget'!O67/100 -> 453.4469
B11: FY27 budget EBITDA margin | F11: ='Assumptions & Budget'!O95 -> 0.11815857
B12: FY27 rolling forecast net revenue (₹ crore) | F12: ='Rolling Forecast'!O12/100 -> 455.37875
B13: FY27 rolling forecast EBITDA margin | F13: ='Rolling Forecast'!O40 -> 0.1125173
B14: Actuals loaded through | F14: ='Assumptions & Budget'!$C$6 -> 46266
B16: Workbook map
B17: Executive Dashboard | C17: One-page view: KPI tiles, two EBITDA bridges, variance by cause, monthly margin trend
B18: Historical Data | C18: 24 months of synthetic history across Sales, Operations, Marketing, HR, IT and Finance
B19: Assumptions & Budget | C19: All drivers in labelled cells; monthly FY27 budget built from them
B20: Actual vs Budget | C20: Actuals input, flexed budget, ₹ variances (favourable = +), revenue volume vs price split
B21: Variance-to-Action Log | C21: Materiality test, Timing / One-off / Structural classification, action and override
B22: Rolling Forecast | C22: Actuals to date + forecast re-based for structural variances, timing reversals and cuts
B23: Summary | C23: YTD result, FY27 outlook, log statistics, top adverse variances, integrity checks
B24: Model Notes | C24: Method, benchmark, assumptions, limitations
B25: Colour code
B26: Blue text | C26: Hard-coded input or assumption
B27: Black text | C27: Formula
B28: Green text | C28: Direct link from another sheet
B29: Yellow fill | C29: Key assumption to flex

Sheet Executive Dashboard
A1: Executive Dashboard – FY27 Budget, Performance and Outlook
A2: ="Decision view · ₹ lakh unless stated · Actuals loaded through "&TEXT('Assumptions & Budget'!$C$6,"mmm-yy") -> Decision view · ₹ lakh unless stated · Actuals loaded through Sep-26
A4: FY27 budget revenue (₹ crore) | B4: FY27 forecast revenue (₹ crore) | D4: YTD EBITDA vs budget (₹ lakh) | F4: FY27 budget EBITDA margin | H4: FY27 forecast EBITDA margin | J4: Material variances (no.)
A5: ='Assumptions & Budget'!O67/100 -> 453.4469 | B5: ='Rolling Forecast'!O12/100 -> 455.37875 | D5: ='Actual vs Budget'!O143 -> -413.17006 | F5: ='Assumptions & Budget'!O95 -> 0.11815857 | H5: ='Rolling Forecast'!O40 -> 0.1125173 | J5: ='Variance-to-Action Log'!C27 -> 8
A40: Reading the charts: green = favourable, red = unfavourable, navy = totals. Bridges tie to the model (check cells in the chart data below). The cause chart uses the trigger variance from the Variance-to-Action Log.
A48: Chart data (formulas only; feeds the charts above)
A50: Step | B50: Value | C50: Cumulative | D50: Base (hidden) | E50: Increase | F50: Decrease | G50: Total
A51: Budget | B51: ='Actual vs Budget'!O87 -> 2299.0598 | C51: =B51 -> 2299.0598 | D51: =0 -> 0 | E51: =0 -> 0 | F51: =0 -> 0 | G51: =B51 -> 2299.0598
A52: Revenue | B52: ='Actual vs Budget'!O119 -> 193.18544 | C52: =C51+B52 -> 2492.2452 | D52: =MIN(C51,C52) -> 2299.0598 | E52: =MAX(B52,0) -> 193.18544 | F52: =MAX(-B52,0) -> 0 | G52: =0 -> 0
A53: COGS | B53: ='Actual vs Budget'!O120 -> 115.68834 | C53: =C52+B53 -> 2607.9336 | D53: =MIN(C52,C53) -> 2492.2452 | E53: =MAX(B53,0) -> 115.68834 | F53: =MAX(-B53,0) -> 0 | G53: =0 -> 0
A54: Sales | B54: ='Actual vs Budget'!O124 -> -83.749698 | C54: =C53+B54 -> 2524.1839 | D54: =MIN(C53,C54) -> 2524.1839 | E54: =MAX(B54,0) -> 0 | F54: =MAX(-B54,0) -> 83.749698 | G54: =0 -> 0
A55: Operations | B55: ='Actual vs Budget'!O128 -> -193.17242 | C55: =C54+B55 -> 2331.0115 | D55: =MIN(C54,C55) -> 2331.0115 | E55: =MAX(B55,0) -> 0 | F55: =MAX(-B55,0) -> 193.17242 | G55: =0 -> 0
A56: Marketing | B56: ='Actual vs Budget'!O132 -> -366.01186 | C56: =C55+B56 -> 1964.9996 | D56: =MIN(C55,C56) -> 1964.9996 | E56: =MAX(B56,0) -> 0 | F56: =MAX(-B56,0) -> 366.01186 | G56: =0 -> 0
A57: IT | B57: ='Actual vs Budget'!O138 -> -82.827355 | C57: =C56+B57 -> 1882.1722 | D57: =MIN(C56,C57) -> 1882.1722 | E57: =MAX(B57,0) -> 0 | F57: =MAX(-B57,0) -> 82.827355 | G57: =0 -> 0
A58: HR + Finance | B58: ='Actual vs Budget'!O135+'Actual vs Budget'!O141 -> 3.7175 | C58: =C57+B58 -> 1885.8897 | D58: =MIN(C57,C58) -> 1882.1722 | E58: =MAX(B58,0) -> 3.7175 | F58: =MAX(-B58,0) -> 0 | G58: =0 -> 0
A59: Actual | B59: ='Actual vs Budget'!O40 -> 1885.8897 | C59: =B59 -> 1885.8897 | D59: =0 -> 0 | E59: =0 -> 0 | F59: =0 -> 0 | G59: =B59 -> 1885.8897
A60: Tie-out (should be 0) | B60: =ROUND(C58-B59,3) -> 0
A63: Cause | B63: Adverse (₹ lakh) | C63: Favourable (₹ lakh)
A64: Timing | B64: =SUMIFS('Variance-to-Action Log'!$X$8:$X$23,'Variance-to-Action Log'!$O$8:$O$23,A64,'Variance-to-Action Log'!$X$8:$X$23,"<0") -> -192.53862 | C64: =SUMIFS('Variance-to-Action Log'!$X$8:$X$23,'Variance-to-Action Log'!$O$8:$O$23,A64,'Variance-to-Action Log'!$X$8:$X$23,">0") -> 0
A65: One-off | B65: =SUMIFS('Variance-to-Action Log'!$X$8:$X$23,'Variance-to-Action Log'!$O$8:$O$23,A65,'Variance-to-Action Log'!$X$8:$X$23,"<0") -> -153.931 | C65: =SUMIFS('Variance-to-Action Log'!$X$8:$X$23,'Variance-to-Action Log'!$O$8:$O$23,A65,'Variance-to-Action Log'!$X$8:$X$23,">0") -> 0
A66: Structural | B66: =SUMIFS('Variance-to-Action Log'!$X$8:$X$23,'Variance-to-Action Log'!$O$8:$O$23,A66,'Variance-to-Action Log'!$X$8:$X$23,"<0") -> -370.62845 | C66: =SUMIFS('Variance-to-Action Log'!$X$8:$X$23,'Variance-to-Action Log'!$O$8:$O$23,A66,'Variance-to-Action Log'!$X$8:$X$23,">0") -> 204.08461
A70: Line (open months) | B70: Cause | C70: Final action | D70: Budget – open months | E70: Forecast – open months | F70: EBITDA effect
A71: ='Variance-to-Action Log'!A8 -> Net revenue | B71: =IF('Variance-to-Action Log'!O8="","",'Variance-to-Action Log'!O8) | C71: ='Variance-to-Action Log'!T8 -> No action | D71: =SUMIFS('Assumptions & Budget'!$C67:$N67,'Assumptions & Budget'!$C$61:$N$61,">"&'Assumptions & Budget'!$C$6) -> 24116.985 | E71: =SUMIFS('Rolling Forecast'!$C12:$N12,'Rolling Forecast'!$C$5:$N$5,">"&'Assumptions & Budget'!$C$6) -> 24116.985 | F71: =E71-D71 -> 0
A72: ='Variance-to-Action Log'!A9 -> Cost of goods sold | B72: =IF('Variance-to-Action Log'!O9="","",'Variance-to-Action Log'!O9) -> Structural | C72: ='Variance-to-Action Log'!T9 -> Reforecast | D72: =SUMIFS('Assumptions & Budget'!$C68:$N68,'Assumptions & Budget'!$C$61:$N$61,">"&'Assumptions & Budget'!$C$6) -> 7476.2655 | E72: =SUMIFS('Rolling Forecast'!$C13:$N13,'Rolling Forecast'!$C$5:$N$5,">"&'Assumptions & Budget'!$C$6) -> 7021.9021 | F72: =D72-E72 -> 454.36339
A73: ='Variance-to-Action Log'!A10 -> Sales – personnel | B73: =IF('Variance-to-Action Log'!O10="","",'Variance-to-Action Log'!O10) -> Structural | C73: ='Variance-to-Action Log'!T10 -> Reforecast | D73: =SUMIFS('Assumptions & Budget'!$C72:$N72,'Assumptions & Budget'!$C$61:$N$61,">"&'Assumptions & Budget'!$C$6) -> 445.04749 | E73: =SUMIFS('Rolling Forecast'!$C17:$N17,'Rolling Forecast'!$C$5:$N$5,">"&'Assumptions & Budget'!$C$6) -> 484.2033 | F73: =D73-E73 -> -39.155811
A74: ='Variance-to-Action Log'!A11 -> Sales – marketplace & payment fees | B74: =IF('Variance-to-Action Log'!O11="","",'Variance-to-Action Log'!O11) -> Structural | C74: ='Variance-to-Action Log'!T11 -> Reforecast | D74: =SUMIFS('Assumptions & Budget'!$C73:$N73,'Assumptions & Budget'!$C$61:$N$61,">"&'Assumptions & Budget'!$C$6) -> 723.50956 | E74: =SUMIFS('Rolling Forecast'!$C18:$N18,'Rolling Forecast'!$C$5:$N$5,">"&'Assumptions & Budget'!$C$6) -> 826.42044 | F74: =D74-E74 -> -102.91087
A75: ='Variance-to-Action Log'!A12 -> Operations – personnel | B75: =IF('Variance-to-Action Log'!O12="","",'Variance-to-Action Log'!O12) | C75: ='Variance-to-Action Log'!T12 -> No action | D75: =SUMIFS('Assumptions & Budget'!$C75:$N75,'Assumptions & Budget'!$C$61:$N$61,">"&'Assumptions & Budget'!$C$6) -> 616.36349 | E75: =SUMIFS('Rolling Forecast'!$C20:$N20,'Rolling Forecast'!$C$5:$N$5,">"&'Assumptions & Budget'!$C$6) -> 616.36349 | F75: =D75-E75 -> 0
A76: ='Variance-to-Action Log'!A13 -> Operations – fulfilment & logistics | B76: =IF('Variance-to-Action Log'!O13="","",'Variance-to-Action Log'!O13) -> Structural | C76: ='Variance-to-Action Log'!T13 -> Reforecast | D76: =SUMIFS('Assumptions & Budget'!$C76:$N76,'Assumptions & Budget'!$C$61:$N$61,">"&'Assumptions & Budget'!$C$6) -> 1761.7108 | E76: =SUMIFS('Rolling Forecast'!$C21:$N21,'Rolling Forecast'!$C$5:$N$5,">"&'Assumptions & Budget'!$C$6) -> 1912.0404 | F76: =D76-E76 -> -150.32967
A77: ='Variance-to-Action Log'!A14 -> Operations – warehouse, QC & other | B77: =IF('Variance-to-Action Log'!O14="","",'Variance-to-Action Log'!O14) -> One-off | C77: ='Variance-to-Action Log'!T14 -> Ignore | D77: =SUMIFS('Assumptions & Budget'!$C77:$N77,'Assumptions & Budget'!$C$61:$N$61,">"&'Assumptions & Budget'!$C$6) -> 205.905 | E77: =SUMIFS('Rolling Forecast'!$C22:$N22,'Rolling Forecast'!$C$5:$N$5,">"&'Assumptions & Budget'!$C$6) -> 205.905 | F77: =D77-E77 -> 0
A78: ='Variance-to-Action Log'!A15 -> Marketing – personnel | B78: =IF('Variance-to-Action Log'!O15="","",'Variance-to-Action Log'!O15) | C78: ='Variance-to-Action Log'!T15 -> No action | D78: =SUMIFS('Assumptions & Budget'!$C79:$N79,'Assumptions & Budget'!$C$61:$N$61,">"&'Assumptions & Budget'!$C$6) -> 563.06524 | E78: =SUMIFS('Rolling Forecast'!$C24:$N24,'Rolling Forecast'!$C$5:$N$5,">"&'Assumptions & Budget'!$C$6) -> 563.06524 | F78: =D78-E78 -> 0
A79: ='Variance-to-Action Log'!A16 -> Marketing – performance marketing | B79: =IF('Variance-to-Action Log'!O16="","",'Variance-to-Action Log'!O16) -> Timing | C79: ='Variance-to-Action Log'!T16 -> Ignore | D79: =SUMIFS('Assumptions & Budget'!$C80:$N80,'Assumptions & Budget'!$C$61:$N$61,">"&'Assumptions & Budget'!$C$6) -> 5185.1519 | E79: =SUMIFS('Rolling Forecast'!$C25:$N25,'Rolling Forecast'!$C$5:$N$5,">"&'Assumptions & Budget'!$C$6) -> 5013.7083 | F79: =D79-E79 -> 171.44357
A80: ='Variance-to-Action Log'!A17 -> Marketing – brand & influencer | B80: =IF('Variance-to-Action Log'!O17="","",'Variance-to-Action Log'!O17) -> Structural | C80: ='Variance-to-Action Log'!T17 -> Cut spend | D80: =SUMIFS('Assumptions & Budget'!$C81:$N81,'Assumptions & Budget'!$C$61:$N$61,">"&'Assumptions & Budget'!$C$6) -> 2411.6985 | E80: =SUMIFS('Rolling Forecast'!$C26:$N26,'Rolling Forecast'!$C$5:$N$5,">"&'Assumptions & Budget'!$C$6) -> 2566.0041 | F80: =D80-E80 -> -154.30557
A81: ='Variance-to-Action Log'!A18 -> HR – personnel | B81: =IF('Variance-to-Action Log'!O18="","",'Variance-to-Action Log'!O18) | C81: ='Variance-to-Action Log'!T18 -> No action | D81: =SUMIFS('Assumptions & Budget'!$C83:$N83,'Assumptions & Budget'!$C$61:$N$61,">"&'Assumptions & Budget'!$C$6) -> 90.072 | E81: =SUMIFS('Rolling Forecast'!$C28:$N28,'Rolling Forecast'!$C$5:$N$5,">"&'Assumptions & Budget'!$C$6) -> 90.072 | F81: =D81-E81 -> 0
A82: ='Variance-to-Action Log'!A19 -> HR – recruitment, training & other | B82: =IF('Variance-to-Action Log'!O19="","",'Variance-to-Action Log'!O19) | C82: ='Variance-to-Action Log'!T19 -> No action | D82: =SUMIFS('Assumptions & Budget'!$C84:$N84,'Assumptions & Budget'!$C$61:$N$61,">"&'Assumptions & Budget'!$C$6) -> 60.7425 | E82: =SUMIFS('Rolling Forecast'!$C29:$N29,'Rolling Forecast'!$C$5:$N$5,">"&'Assumptions & Budget'!$C$6) -> 60.7425 | F82: =D82-E82 -> 0
A83: ='Variance-to-Action Log'!A20 -> IT – personnel | B83: =IF('Variance-to-Action Log'!O20="","",'Variance-to-Action Log'!O20) | C83: ='Variance-to-Action Log'!T20 -> No action | D83: =SUMIFS('Assumptions & Budget'!$C86:$N86,'Assumptions & Budget'!$C$61:$N$61,">"&'Assumptions & Budget'!$C$6) -> 589.22013 | E83: =SUMIFS('Rolling Forecast'!$C31:$N31,'Rolling Forecast'!$C$5:$N$5,">"&'Assumptions & Budget'!$C$6) -> 589.22013 | F83: =D83-E83 -> 0
A84: ='Variance-to-Action Log'!A21 -> IT – software, cloud & other | B84: =IF('Variance-to-Action Log'!O21="","",'Variance-to-Action Log'!O21) -> One-off | C84: ='Variance-to-Action Log'!T21 -> Ignore | D84: =SUMIFS('Assumptions & Budget'!$C87:$N87,'Assumptions & Budget'!$C$61:$N$61,">"&'Assumptions & Budget'!$C$6) -> 313.264 | E84: =SUMIFS('Rolling Forecast'!$C32:$N32,'Rolling Forecast'!$C$5:$N$5,">"&'Assumptions & Budget'!$C$6) -> 313.264 | F84: =D84-E84 -> 0
A85: ='Variance-to-Action Log'!A22 -> Finance – personnel | B85: =IF('Variance-to-Action Log'!O22="","",'Variance-to-Action Log'!O22) | C85: ='Variance-to-Action Log'!T22 -> No action | D85: =SUMIFS('Assumptions & Budget'!$C89:$N89,'Assumptions & Budget'!$C$61:$N$61,">"&'Assumptions & Budget'!$C$6) -> 243.7344 | E85: =SUMIFS('Rolling Forecast'!$C34:$N34,'Rolling Forecast'!$C$5:$N$5,">"&'Assumptions & Budget'!$C$6) -> 243.7344 | F85: =D85-E85 -> 0
A86: ='Variance-to-Action Log'!A23 -> Finance – professional fees, rent & admin | B86: =IF('Variance-to-Action Log'!O23="","",'Variance-to-Action Log'!O23) | C86: ='Variance-to-Action Log'!T23 -> No action | D86: =SUMIFS('Assumptions & Budget'!$C90:$N90,'Assumptions & Budget'!$C$61:$N$61,">"&'Assumptions & Budget'!$C$6) -> 372.431 | E86: =SUMIFS('Rolling Forecast'!$C35:$N35,'Rolling Forecast'!$C$5:$N$5,">"&'Assumptions & Budget'!$C$6) -> 372.431 | F86: =D86-E86 -> 0
A89: Step | B89: Value | C89: Adverse | D89: Favourable | E89: Net vs budget
A90: YTD variance | B90: ='Actual vs Budget'!O143 -> -413.17006 | C90: =MIN(B90,0) -> -413.17006 | D90: =MAX(B90,0) -> 0 | E90: =0 -> 0
A91: Structural re-forecasts | B91: =SUMIF($C$71:$C$86,"Reforecast",$F$71:$F$86) -> 161.96703 | C91: =MIN(B91,0) -> 0 | D91: =MAX(B91,0) -> 161.96703 | E91: =0 -> 0
A92: Cut-spend recovery | B92: =SUMIF($C$71:$C$86,"Cut spend",$F$71:$F$86) -> -154.30557 | C92: =MIN(B92,0) -> -154.30557 | D92: =MAX(B92,0) -> 0 | E92: =0 -> 0
A93: Timing reversal | B93: =SUMIFS($F$71:$F$86,$B$71:$B$86,"Timing") -> 171.44357 | C93: =MIN(B93,0) -> 0 | D93: =MAX(B93,0) -> 171.44357 | E93: =0 -> 0
A94: Other / residual | B94: ='Rolling Forecast'!O39-'Assumptions & Budget'!O94-SUM(B90:B93) -> 6.2527761e-13 | C94: =MIN(B94,0) -> 0 | D94: =MAX(B94,0) -> 6.2527761e-13 | E94: =0 -> 0
A95: Net vs budget | B95: ='Rolling Forecast'!O39-'Assumptions & Budget'!O94 -> -234.06502 | C95: =0 -> 0 | D95: =0 -> 0 | E95: =B95 -> -234.06502
A96: Tie-out (should be 0) | B96: =ROUND(SUM(B90:B94)-B95,3) -> 0
A99: Month | B99: Budget EBITDA margin | C99: Actual / forecast EBITDA margin
A100: ='Assumptions & Budget'!C61 -> 46113 | B100: ='Assumptions & Budget'!C95 -> 0.10839286 | C100: ='Rolling Forecast'!C40 -> 0.10956685
A101: ='Assumptions & Budget'!D61 -> 46143 | B101: ='Assumptions & Budget'!D95 -> 0.10910056 | C101: ='Rolling Forecast'!D40 -> 0.10297093
A102: ='Assumptions & Budget'!E61 -> 46174 | B102: ='Assumptions & Budget'!E95 -> 0.10456466 | C102: ='Rolling Forecast'!E40 -> 0.066842345
A103: ='Assumptions & Budget'!F61 -> 46204 | B103: ='Assumptions & Budget'!F95 -> 0.099698276 | C103: ='Rolling Forecast'!F40 -> 0.079022564
A104: ='Assumptions & Budget'!G61 -> 46235 | B104: ='Assumptions & Budget'!G95 -> 0.10940871 | C104: ='Rolling Forecast'!G40 -> 0.090215959
A105: ='Assumptions & Budget'!H61 -> 46266 | B105: ='Assumptions & Budget'!H95 -> 0.11753894 | C105: ='Rolling Forecast'!H40 -> 0.079824884
A106: ='Assumptions & Budget'!I61 -> 46296 | B106: ='Assumptions & Budget'!I95 -> 0.14346606 | C106: ='Rolling Forecast'!I40 -> 0.16281984
A107: ='Assumptions & Budget'!J61 -> 46327 | B107: ='Assumptions & Budget'!J95 -> 0.13852176 | C107: ='Rolling Forecast'!J40 -> 0.15859883
A108: ='Assumptions & Budget'!K61 -> 46357 | B108: ='Assumptions & Budget'!K95 -> 0.12582466 | C108: ='Rolling Forecast'!K40 -> 0.12613904
A109: ='Assumptions & Budget'!L61 -> 46388 | B109: ='Assumptions & Budget'!L95 -> 0.11888882 | C109: ='Rolling Forecast'!L40 -> 0.1191186
A110: ='Assumptions & Budget'!M61 -> 46419 | B110: ='Assumptions & Budget'!M95 -> 0.11152602 | C110: ='Rolling Forecast'!M40 -> 0.11168913
A111: ='Assumptions & Budget'!N61 -> 46447 | B111: ='Assumptions & Budget'!N95 -> 0.11713153 | C111: ='Rolling Forecast'!N40 -> 0.1173738

Sheet Historical Data
A1: Historical Data – 24 months (Apr-24 to Mar-26)
A2: Fictional Indian D2C company. Amounts in ₹ lakh unless stated (100 lakh = ₹1 crore). Values are synthetic; ratios benchmarked to Honasa Consumer FY26.
A3: Blue = hard-coded input (synthetic history) · Black = formula · Green = link from another sheet
A5: Line item | B5: Unit | C5: 45383 | D5: 45413 | E5: 45444 | F5: 45474 | G5: 45505 | H5: 45536 | I5: 45566 | J5: 45597 | K5: 45627 | L5: 45658 | M5: 45689 | N5: 45717 | O5: 45748 | P5: 45778 | Q5: 45809 | R5: 45839 | S5: 45870 | T5: 45901 | U5: 45931 | V5: 45962 | W5: 45992 | X5: 46023 | Y5: 46054 | Z5: 46082 | AA5: FY25 | AB5: FY26 | AC5: YoY % / Δ pp
A6: Fiscal year (Apr–Mar) | C6: =IF(MONTH(C5)>=4,"FY"&TEXT(MOD(YEAR(C5)+1,100),"00"),"FY"&TEXT(MOD(YEAR(C5),100),"00")) -> FY25 | D6: =IF(MONTH(D5)>=4,"FY"&TEXT(MOD(YEAR(D5)+1,100),"00"),"FY"&TEXT(MOD(YEAR(D5),100),"00")) -> FY25 | E6: =IF(MONTH(E5)>=4,"FY"&TEXT(MOD(YEAR(E5)+1,100),"00"),"FY"&TEXT(MOD(YEAR(E5),100),"00")) -> FY25 | F6: =IF(MONTH(F5)>=4,"FY"&TEXT(MOD(YEAR(F5)+1,100),"00"),"FY"&TEXT(MOD(YEAR(F5),100),"00")) -> FY25 | G6: =IF(MONTH(G5)>=4,"FY"&TEXT(MOD(YEAR(G5)+1,100),"00"),"FY"&TEXT(MOD(YEAR(G5),100),"00")) -> FY25 | H6: =IF(MONTH(H5)>=4,"FY"&TEXT(MOD(YEAR(H5)+1,100),"00"),"FY"&TEXT(MOD(YEAR(H5),100),"00")) -> FY25 | I6: =IF(MONTH(I5)>=4,"FY"&TEXT(MOD(YEAR(I5)+1,100),"00"),"FY"&TEXT(MOD(YEAR(I5),100),"00")) -> FY25 | J6: =IF(MONTH(J5)>=4,"FY"&TEXT(MOD(YEAR(J5)+1,100),"00"),"FY"&TEXT(MOD(YEAR(J5),100),"00")) -> FY25 | ... Z6: =IF(MONTH(Z5)>=4,"FY"&TEXT(MOD(YEAR(Z5)+1,100),"00"),"FY"&TEXT(MOD(YEAR(Z5),100),"00")) -> FY26
A7: Revenue drivers
A8: Seasonality index | B8: index | C8: 0.95 | D8: 0.95 | E8: 0.92 | F8: 0.9 | G8: 0.95 | H8: 1 | I8: 1.2 | J8: 1.15 | K8: 1.05 | L8: 1 | M8: 0.95 | N8: 0.98 | O8: 0.95 | P8: 0.95 | Q8: 0.92 | R8: 0.9 | S8: 0.95 | T8: 1 | U8: 1.2 | V8: 1.15 | W8: 1.05 | X8: 1 | Y8: 0.95 | Z8: 0.98 | AA8: =SUMIF($C$6:$Z$6,AA$5,$C8:$Z8) -> 12 | AB8: =SUMIF($C$6:$Z$6,AB$5,$C8:$Z8) -> 12
A9: Orders (no.) | B9: no. | C9: 384145 | D9: 378011 | E9: 383658 | F9: 380891 | G9: 383424 | H9: 413579 | I9: 516519 | J9: 496039 | K9: 460674 | L9: 436168 | M9: 433711 | N9: 451452 | O9: 436271 | P9: 450446 | Q9: 435355 | R9: 419281 | S9: 458652 | T9: 475265 | U9: 598230 | V9: 569068 | W9: 523911 | X9: 499458 | Y9: 498249 | Z9: 505697 | AA9: =SUMIF($C$6:$Z$6,AA$5,$C9:$Z9) -> 5118271 | AB9: =SUMIF($C$6:$Z$6,AB$5,$C9:$Z9) -> 5869883 | AC9: =IF(AA9=0,"",AB9/AA9-1) -> 0.14684881
A10: Net AOV (₹ per order) | B10: ₹ | C10: 637.8 | D10: 640.4 | E10: 647.2 | F10: 648.6 | G10: 651.2 | H10: 653.5 | I10: 663.4 | J10: 653.7 | K10: 655.4 | L10: 656.1 | M10: 666 | N10: 671.1 | O10: 666.8 | P10: 665.2 | Q10: 667.7 | R10: 677.9 | S10: 680.8 | T10: 682.1 | U10: 677.9 | V10: 685.2 | W10: 687 | X10: 689.9 | Y10: 696 | Z10: 694.8 | AA10: =IF(AA9=0,0,AA12*100000/AA9) -> 654.36762 | AB10: =IF(AB9=0,0,AB12*100000/AB9) -> 681.44388
A11: Profit & loss (₹ lakh)
A12: Net revenue | B12: ₹ lakh | C12: =C9*C10/100000 -> 2450.0768 | D12: =D9*D10/100000 -> 2420.7824 | E12: =E9*E10/100000 -> 2483.0346 | F12: =F9*F10/100000 -> 2470.459 | G12: =G9*G10/100000 -> 2496.8571 | H12: =H9*H10/100000 -> 2702.7388 | I12: =I9*I10/100000 -> 3426.587 | J12: =J9*J10/100000 -> 3242.6069 | ... Z12: =Z9*Z10/100000 -> 3513.5828 | AA12: =SUMIF($C$6:$Z$6,AA$5,$C12:$Z12) -> 33492.308 | AB12: =SUMIF($C$6:$Z$6,AB$5,$C12:$Z12) -> 39999.959 | AC12: =IF(AA12=0,"",AB12/AA12-1) -> 0.19430284
A13: Cost of goods sold | B13: ₹ lakh | C13: 822.7 | D13: 816.3 | E13: 830.4 | F13: 817.8 | G13: 848.5 | H13: 898.6 | I13: 1136.1 | J13: 1072.4 | K13: 988 | L13: 906.4 | M13: 944.1 | N13: 957.4 | O13: 953 | P13: 956.5 | Q13: 915.8 | R13: 884.7 | S13: 964.8 | T13: 994.9 | U13: 1261 | V13: 1208.1 | W13: 1085.4 | X13: 1051.5 | Y13: 1071.2 | Z13: 1077 | AA13: =SUMIF($C$6:$Z$6,AA$5,$C13:$Z13) -> 11038.7 | AB13: =SUMIF($C$6:$Z$6,AB$5,$C13:$Z13) -> 12423.9 | AC13: =IF(AA13=0,"",AB13/AA13-1) -> 0.12548579
A14: Gross profit | B14: ₹ lakh | C14: =C12-C13 -> 1627.3768 | D14: =D12-D13 -> 1604.4824 | E14: =E12-E13 -> 1652.6346 | F14: =F12-F13 -> 1652.659 | G14: =G12-G13 -> 1648.3571 | H14: =H12-H13 -> 1804.1388 | I14: =I12-I13 -> 2290.487 | J14: =J12-J13 -> 2170.2069 | ... AB14: =AB12-AB13 -> 27576.059 | AC14: =IF(AA14=0,"",AB14/AA14-1) -> 0.22813486
A15: Gross margin % | B15: % | C15: =IF(C12=0,0,C14/C12) -> 0.66421461 | D15: =IF(D12=0,0,D14/D12) -> 0.66279498 | E15: =IF(E12=0,0,E14/E12) -> 0.6655705 | F15: =IF(F12=0,0,F14/F12) -> 0.6689684 | G15: =IF(G12=0,0,G14/G12) -> 0.66017278 | H15: =IF(H12=0,0,H14/H12) -> 0.66752244 | I15: =IF(I12=0,0,I14/I12) -> 0.6684456 | J15: =IF(J12=0,0,J14/J12) -> 0.66927845 | ... AB15: =IF(AB12=0,0,AB14/AB12) -> 0.68940218 | AC15: =AB15-AA15 -> 0.01899129
A16: Operating costs by cost centre (₹ lakh)
A17: Sales – personnel | B17: ₹ lakh | C17: 50.5 | D17: 50.6 | E17: 51.5 | F17: 51.8 | G17: 53.6 | H17: 51.1 | I17: 53.5 | J17: 53.8 | K17: 53.9 | L17: 54.5 | M17: 53.6 | N17: 55.9 | O17: 60.9 | P17: 59.6 | Q17: 61.3 | R17: 61.6 | S17: 61.8 | T17: 61 | U17: 62.6 | V17: 63.9 | W17: 64.4 | X17: 65.3 | Y17: 66 | Z17: 65.4 | AA17: =SUMIF($C$6:$Z$6,AA$5,$C17:$Z17) -> 634.3 | AB17: =SUMIF($C$6:$Z$6,AB$5,$C17:$Z17) -> 753.8 | AC17: =IF(AA17=0,"",AB17/AA17-1) -> 0.18839666
A18: Sales – marketplace & payment fees | B18: ₹ lakh | C18: 70.8 | D18: 74.1 | E18: 74.9 | F18: 76.2 | G18: 73.6 | H18: 81.6 | I18: 105.4 | J18: 96.1 | K18: 92.2 | L18: 83.6 | M18: 85.4 | N18: 89.5 | O18: 83.1 | P18: 91.6 | Q18: 85.6 | R18: 85.3 | S18: 95.5 | T18: 99 | U18: 124.9 | V18: 116.5 | W18: 106.1 | X18: 103 | Y18: 97 | Z18: 99.3 | AA18: =SUMIF($C$6:$Z$6,AA$5,$C18:$Z18) -> 1003.4 | AB18: =SUMIF($C$6:$Z$6,AB$5,$C18:$Z18) -> 1186.9 | AC18: =IF(AA18=0,"",AB18/AA18-1) -> 0.18287821
A19: Sales – total | B19: ₹ lakh | C19: =C17+C18 -> 121.3 | D19: =D17+D18 -> 124.7 | E19: =E17+E18 -> 126.4 | F19: =F17+F18 -> 128 | G19: =G17+G18 -> 127.2 | H19: =H17+H18 -> 132.7 | I19: =I17+I18 -> 158.9 | J19: =J17+J18 -> 149.9 | ... AB19: =AB17+AB18 -> 1940.7 | AC19: =IF(AA19=0,"",AB19/AA19-1) -> 0.18501557
A20: Operations – personnel | B20: ₹ lakh | C20: 79.2 | D20: 78.6 | E20: 79.5 | F20: 78.5 | G20: 79.4 | H20: 79.3 | I20: 81.5 | J20: 79.4 | K20: 81.9 | L20: 81.5 | M20: 83.4 | N20: 83.6 | O20: 90.6 | P20: 90.1 | Q20: 88.2 | R20: 90.5 | S20: 89.9 | T20: 90.6 | U20: 93.5 | V20: 93.1 | W20: 92.3 | X20: 91.9 | Y20: 93.7 | Z20: 92.9 | AA20: =SUMIF($C$6:$Z$6,AA$5,$C20:$Z20) -> 965.8 | AB20: =SUMIF($C$6:$Z$6,AB$5,$C20:$Z20) -> 1097.3 | AC20: =IF(AA20=0,"",AB20/AA20-1) -> 0.13615655
A21: Operations – fulfilment & logistics | B21: ₹ lakh | C21: 173.2 | D21: 171.5 | E21: 178.1 | F21: 173.6 | G21: 176.4 | H21: 195.4 | I21: 238.5 | J21: 233.1 | K21: 211.5 | L21: 220.1 | M21: 216.7 | N21: 228 | O21: 224.6 | P21: 223.4 | Q21: 223.4 | R21: 214.8 | S21: 232.4 | T21: 238 | U21: 307 | V21: 289.8 | W21: 270.2 | X21: 257.2 | Y21: 263 | Z21: 260.1 | AA21: =SUMIF($C$6:$Z$6,AA$5,$C21:$Z21) -> 2416.1 | AB21: =SUMIF($C$6:$Z$6,AB$5,$C21:$Z21) -> 3003.9 | AC21: =IF(AA21=0,"",AB21/AA21-1) -> 0.24328463
A22: Operations – warehouse, QC & other | B22: ₹ lakh | C22: 26.9 | D22: 28.4 | E22: 28.7 | F22: 30.2 | G22: 29.9 | H22: 29.6 | I22: 31.1 | J22: 28.2 | K22: 29.1 | L22: 119 | M22: 29.8 | N22: 28.9 | O22: 31.6 | P22: 30.8 | Q22: 29.5 | R22: 30.3 | S22: 32.2 | T22: 33.1 | U22: 34.9 | V22: 36.4 | W22: 33.4 | X22: 31.8 | Y22: 30.5 | Z22: 34 | AA22: =SUMIF($C$6:$Z$6,AA$5,$C22:$Z22) -> 439.8 | AB22: =SUMIF($C$6:$Z$6,AB$5,$C22:$Z22) -> 388.5 | AC22: =IF(AA22=0,"",AB22/AA22-1) -> -0.11664393
A23: Operations – total | B23: ₹ lakh | C23: =C20+C21+C22 -> 279.3 | D23: =D20+D21+D22 -> 278.5 | E23: =E20+E21+E22 -> 286.3 | F23: =F20+F21+F22 -> 282.3 | G23: =G20+G21+G22 -> 285.7 | H23: =H20+H21+H22 -> 304.3 | I23: =I20+I21+I22 -> 351.1 | J23: =J20+J21+J22 -> 340.7 | ... AB23: =AB20+AB21+AB22 -> 4489.7 | AC23: =IF(AA23=0,"",AB23/AA23-1) -> 0.17479132
A24: Marketing – personnel | B24: ₹ lakh | C24: 66.3 | D24: 67.1 | E24: 69 | F24: 68.6 | G24: 67.4 | H24: 69.6 | I24: 70.6 | J24: 70.9 | K24: 71.9 | L24: 70 | M24: 71.2 | N24: 73.5 | O24: 76.6 | P24: 80.8 | Q24: 79.7 | R24: 81.5 | S24: 80.1 | T24: 81.4 | U24: 83 | V24: 82.2 | W24: 83.5 | X24: 83.5 | Y24: 83.7 | Z24: 84.4 | AA24: =SUMIF($C$6:$Z$6,AA$5,$C24:$Z24) -> 836.1 | AB24: =SUMIF($C$6:$Z$6,AB$5,$C24:$Z24) -> 980.4 | AC24: =IF(AA24=0,"",AB24/AA24-1) -> 0.17258701
A25: Marketing – performance marketing | B25: ₹ lakh | C25: 575.6 | D25: 571.5 | E25: 581.7 | F25: 582.6 | G25: 601.8 | H25: 700.6 | I25: 751.3 | J25: 739.4 | K25: 676.4 | L25: 655.7 | M25: 665.7 | N25: 723.3 | O25: 668.3 | P25: 698.7 | Q25: 653.9 | R25: 627.3 | S25: 689.9 | T25: 782.1 | U25: 904.5 | V25: 854.7 | W25: 815.8 | X25: 748.2 | Y25: 781.9 | Z25: 779.8 | AA25: =SUMIF($C$6:$Z$6,AA$5,$C25:$Z25) -> 7825.6 | AB25: =SUMIF($C$6:$Z$6,AB$5,$C25:$Z25) -> 9005.1 | AC25: =IF(AA25=0,"",AB25/AA25-1) -> 0.15072327
A26: Marketing – brand & influencer | B26: ₹ lakh | C26: 255.7 | D26: 253.4 | E26: 253.4 | F26: 262.5 | G26: 255.9 | H26: 268.2 | I26: 366.1 | J26: 364.7 | K26: 331.9 | L26: 297.8 | M26: 296.9 | N26: 315.8 | O26: 314.6 | P26: 310.5 | Q26: 293.4 | R26: 303.6 | S26: 324.5 | T26: 350.7 | U26: 448.5 | V26: 408.6 | W26: 345.7 | X26: 372 | Y26: 374.8 | Z26: 352.3 | AA26: =SUMIF($C$6:$Z$6,AA$5,$C26:$Z26) -> 3522.3 | AB26: =SUMIF($C$6:$Z$6,AB$5,$C26:$Z26) -> 4199.2 | AC26: =IF(AA26=0,"",AB26/AA26-1) -> 0.19217557
A27: Marketing – total | B27: ₹ lakh | C27: =C24+C25+C26 -> 897.6 | D27: =D24+D25+D26 -> 892 | E27: =E24+E25+E26 -> 904.1 | F27: =F24+F25+F26 -> 913.7 | G27: =G24+G25+G26 -> 925.1 | H27: =H24+H25+H26 -> 1038.4 | I27: =I24+I25+I26 -> 1188 | J27: =J24+J25+J26 -> 1175 | ... AB27: =AB24+AB25+AB26 -> 14184.7 | AC27: =IF(AA27=0,"",AB27/AA27-1) -> 0.16420716
A28: HR – personnel | B28: ₹ lakh | C28: 11.2 | D28: 11.2 | E28: 11.3 | F28: 11 | G28: 11.2 | H28: 11.4 | I28: 12 | J28: 12 | K28: 12.1 | L28: 12.2 | M28: 12.1 | N28: 12.3 | O28: 13.1 | P28: 13.1 | Q28: 13.1 | R28: 13.3 | S28: 12.9 | T28: 12.7 | U28: 14.2 | V28: 13.9 | W28: 14 | X28: 14.2 | Y28: 13.7 | Z28: 13.8 | AA28: =SUMIF($C$6:$Z$6,AA$5,$C28:$Z28) -> 140 | AB28: =SUMIF($C$6:$Z$6,AB$5,$C28:$Z28) -> 162 | AC28: =IF(AA28=0,"",AB28/AA28-1) -> 0.15714286
A29: HR – recruitment, training & other | B29: ₹ lakh | C29: 8.7 | D29: 10.1 | E29: 8.3 | F29: 8.5 | G29: 9.7 | H29: 9 | I29: 9.3 | J29: 9.3 | K29: 9.7 | L29: 10.6 | M29: 9.6 | N29: 10.1 | O29: 8.1 | P29: 9.7 | Q29: 9.1 | R29: 8.9 | S29: 9.2 | T29: 9.7 | U29: 10.8 | V29: 9 | W29: 10.2 | X29: 9.8 | Y29: 10 | Z29: 11.2 | AA29: =SUMIF($C$6:$Z$6,AA$5,$C29:$Z29) -> 112.9 | AB29: =SUMIF($C$6:$Z$6,AB$5,$C29:$Z29) -> 115.7 | AC29: =IF(AA29=0,"",AB29/AA29-1) -> 0.024800709
A30: HR – total | B30: ₹ lakh | C30: =C28+C29 -> 19.9 | D30: =D28+D29 -> 21.3 | E30: =E28+E29 -> 19.6 | F30: =F28+F29 -> 19.5 | G30: =G28+G29 -> 20.9 | H30: =H28+H29 -> 20.4 | I30: =I28+I29 -> 21.3 | J30: =J28+J29 -> 21.3 | ... AB30: =AB28+AB29 -> 277.7 | AC30: =IF(AA30=0,"",AB30/AA30-1) -> 0.098062475
A31: IT – personnel | B31: ₹ lakh | C31: 61.6 | D31: 62.2 | E31: 64.7 | F31: 64.8 | G31: 64.6 | H31: 63.3 | I31: 64.1 | J31: 66 | K31: 65.6 | L31: 66.3 | M31: 68.1 | N31: 67.6 | O31: 72.9 | P31: 72.5 | Q31: 74.4 | R31: 83.3 | S31: 83.8 | T31: 84.2 | U31: 86.5 | V31: 85.3 | W31: 86.2 | X31: 85.4 | Y31: 87.3 | Z31: 88.3 | AA31: =SUMIF($C$6:$Z$6,AA$5,$C31:$Z31) -> 778.9 | AB31: =SUMIF($C$6:$Z$6,AB$5,$C31:$Z31) -> 990.1 | AC31: =IF(AA31=0,"",AB31/AA31-1) -> 0.27115162
A32: IT – software, cloud & other | B32: ₹ lakh | C32: 36.6 | D32: 37.8 | E32: 36.6 | F32: 36.3 | G32: 157.2 | H32: 38.1 | I32: 38.4 | J32: 37.3 | K32: 39.1 | L32: 39.6 | M32: 42.8 | N32: 42.4 | O32: 39.5 | P32: 40.6 | Q32: 39.6 | R32: 47.1 | S32: 48.6 | T32: 50.2 | U32: 48.1 | V32: 48.6 | W32: 47.1 | X32: 50.1 | Y32: 49.4 | Z32: 50.5 | AA32: =SUMIF($C$6:$Z$6,AA$5,$C32:$Z32) -> 582.2 | AB32: =SUMIF($C$6:$Z$6,AB$5,$C32:$Z32) -> 559.4 | AC32: =IF(AA32=0,"",AB32/AA32-1) -> -0.0391618
A33: IT – total | B33: ₹ lakh | C33: =C31+C32 -> 98.2 | D33: =D31+D32 -> 100 | E33: =E31+E32 -> 101.3 | F33: =F31+F32 -> 101.1 | G33: =G31+G32 -> 221.8 | H33: =H31+H32 -> 101.4 | I33: =I31+I32 -> 102.5 | J33: =J31+J32 -> 103.3 | ... AB33: =AB31+AB32 -> 1549.5 | AC33: =IF(AA33=0,"",AB33/AA33-1) -> 0.13841746
A34: Finance – personnel | B34: ₹ lakh | C34: 28.8 | D34: 29 | E34: 29 | F34: 29.8 | G34: 30.4 | H34: 30.9 | I34: 30.5 | J34: 30.7 | K34: 31 | L34: 32.3 | M34: 31.7 | N34: 32.3 | O34: 34 | P34: 33.7 | Q34: 33.8 | R34: 34.6 | S34: 34.8 | T34: 35.1 | U34: 35.6 | V34: 35.9 | W34: 34.6 | X34: 36.6 | Y34: 36 | Z34: 36.6 | AA34: =SUMIF($C$6:$Z$6,AA$5,$C34:$Z34) -> 366.4 | AB34: =SUMIF($C$6:$Z$6,AB$5,$C34:$Z34) -> 421.3 | AC34: =IF(AA34=0,"",AB34/AA34-1) -> 0.14983624
A35: Finance – professional fees, rent & admin | B35: ₹ lakh | C35: 50.2 | D35: 52.2 | E35: 49 | F35: 50 | G35: 58 | H35: 51.1 | I35: 51.8 | J35: 58.6 | K35: 61.4 | L35: 52.8 | M35: 54.9 | N35: 111.9 | O35: 60.4 | P35: 54.7 | Q35: 56.8 | R35: 59.5 | S35: 59.2 | T35: 57.7 | U35: 58.6 | V35: 56.1 | W35: 59.2 | X35: 59.6 | Y35: 61.2 | Z35: 59.7 | AA35: =SUMIF($C$6:$Z$6,AA$5,$C35:$Z35) -> 701.9 | AB35: =SUMIF($C$6:$Z$6,AB$5,$C35:$Z35) -> 702.7 | AC35: =IF(AA35=0,"",AB35/AA35-1) -> 0.0011397635
A36: Finance – total | B36: ₹ lakh | C36: =C34+C35 -> 79 | D36: =D34+D35 -> 81.2 | E36: =E34+E35 -> 78 | F36: =F34+F35 -> 79.8 | G36: =G34+G35 -> 88.4 | H36: =H34+H35 -> 82 | I36: =I34+I35 -> 82.3 | J36: =J34+J35 -> 89.3 | ... AB36: =AB34+AB35 -> 1124 | AC36: =IF(AA36=0,"",AB36/AA36-1) -> 0.052138912
A37: Total operating cost & profitability (₹ lakh)
A38: Total operating cost | B38: ₹ lakh | C38: =C19+C23+C27+C30+C33+C36 -> 1495.3 | D38: =D19+D23+D27+D30+D33+D36 -> 1497.7 | E38: =E19+E23+E27+E30+E33+E36 -> 1515.7 | F38: =F19+F23+F27+F30+F33+F36 -> 1524.4 | G38: =G19+G23+G27+G30+G33+G36 -> 1669.1 | H38: =H19+H23+H27+H30+H33+H36 -> 1679.2 | I38: =I19+I23+I27+I30+I33+I36 -> 1904.1 | J38: =J19+J23+J27+J30+J33+J36 -> 1879.5 | ... AB38: =AB19+AB23+AB27+AB30+AB33+AB36 -> 23566.3 | AC38: =IF(AA38=0,"",AB38/AA38-1) -> 0.15943362
A39: EBITDA | B39: ₹ lakh | C39: =C14-C38 -> 132.07681 | D39: =D14-D38 -> 106.78244 | E39: =E14-E38 -> 136.93458 | F39: =F14-F38 -> 128.25903 | G39: =G14-G38 -> -20.742912 | H39: =H14-H38 -> 124.93876 | I39: =I14-I38 -> 386.38705 | J39: =J14-J38 -> 290.70694 | ... AB39: =AB14-AB38 -> 4009.7586 | AC39: =IF(AA39=0,"",AB39/AA39-1) -> 0.88436657
A40: EBITDA margin % | B40: % | C40: =IF(C12=0,0,C39/C12) -> 0.053907212 | D40: =IF(D12=0,0,D39/D12) -> 0.044110715 | E40: =IF(E12=0,0,E39/E12) -> 0.055148075 | F40: =IF(F12=0,0,F39/F12) -> 0.051917083 | G40: =IF(G12=0,0,G39/G12) -> -0.0083076088 | H40: =IF(H12=0,0,H39/H12) -> 0.046226726 | I40: =IF(I12=0,0,I39/I12) -> 0.11276149 | J40: =IF(J12=0,0,J39/J12) -> 0.08965223 | ... AB40: =IF(AB12=0,0,AB39/AB12) -> 0.10024407 | AC40: =AB40-AA40 -> 0.036709841
A41: Depreciation & amortisation | B41: ₹ lakh | C41: 54.1 | D41: 54.9 | E41: 55.2 | F41: 55.9 | G41: 56.4 | H41: 57 | I41: 57.5 | J41: 58.4 | K41: 58.9 | L41: 60.2 | M41: 60.7 | N41: 61 | O41: 61.3 | P41: 61.9 | Q41: 63.3 | R41: 63.7 | S41: 64.5 | T41: 64.5 | U41: 66.1 | V41: 66.6 | W41: 66.8 | X41: 67.8 | Y41: 68.8 | Z41: 69.5 | AA41: =SUMIF($C$6:$Z$6,AA$5,$C41:$Z41) -> 690.2 | AB41: =SUMIF($C$6:$Z$6,AB$5,$C41:$Z41) -> 784.8 | AC41: =IF(AA41=0,"",AB41/AA41-1) -> 0.13706172
A42: EBIT | B42: ₹ lakh | C42: =C39-C41 -> 77.97681 | D42: =D39-D41 -> 51.882444 | E42: =E39-E41 -> 81.734576 | F42: =F39-F41 -> 72.359026 | G42: =G39-G41 -> -77.142912 | H42: =H39-H41 -> 67.938765 | I42: =I39-I41 -> 328.88705 | J42: =J39-J41 -> 232.30694 | ... AB42: =AB39-AB41 -> 3224.9586 | AC42: =IF(AA42=0,"",AB42/AA42-1) -> 1.243125
A43: Headcount (closing)
A44: Headcount – Sales | B44: no. | C44: 50 | D44: 50 | E44: 51 | F44: 51 | G44: 52 | H44: 52 | I44: 53 | J44: 53 | K44: 53 | L44: 54 | M44: 54 | N44: 55 | O44: 55 | P44: 56 | Q44: 56 | R44: 57 | S44: 57 | T44: 57 | U44: 58 | V44: 58 | W44: 59 | X44: 59 | Y44: 60 | Z44: 60 | AA44: =AVERAGEIF($C$6:$Z$6,AA$5,$C44:$Z44) -> 52.333333 | AB44: =AVERAGEIF($C$6:$Z$6,AB$5,$C44:$Z44) -> 57.666667
A45: Headcount – Operations | B45: no. | C45: 132 | D45: 133 | E45: 134 | F45: 134 | G45: 135 | H45: 136 | I45: 137 | J45: 137 | K45: 138 | L45: 139 | M45: 140 | N45: 141 | O45: 141 | P45: 142 | Q45: 143 | R45: 144 | S45: 145 | T45: 145 | U45: 146 | V45: 147 | W45: 148 | X45: 148 | Y45: 149 | Z45: 150 | AA45: =AVERAGEIF($C$6:$Z$6,AA$5,$C45:$Z45) -> 136.33333 | AB45: =AVERAGEIF($C$6:$Z$6,AB$5,$C45:$Z45) -> 145.66667
A46: Headcount – Marketing | B46: no. | C46: 55 | D46: 55 | E46: 56 | F46: 56 | G46: 57 | H46: 57 | I46: 58 | J46: 58 | K46: 58 | L46: 59 | M46: 59 | N46: 60 | O46: 60 | P46: 61 | Q46: 61 | R46: 62 | S46: 62 | T46: 62 | U46: 63 | V46: 63 | W46: 64 | X46: 64 | Y46: 65 | Z46: 65 | AA46: =AVERAGEIF($C$6:$Z$6,AA$5,$C46:$Z46) -> 57.333333 | AB46: =AVERAGEIF($C$6:$Z$6,AB$5,$C46:$Z46) -> 62.666667
A47: Headcount – HR | B47: no. | C47: 12 | D47: 12 | E47: 12 | F47: 12 | G47: 12 | H47: 12 | I47: 13 | J47: 13 | K47: 13 | L47: 13 | M47: 13 | N47: 13 | O47: 13 | P47: 13 | Q47: 13 | R47: 13 | S47: 13 | T47: 13 | U47: 14 | V47: 14 | W47: 14 | X47: 14 | Y47: 14 | Z47: 14 | AA47: =AVERAGEIF($C$6:$Z$6,AA$5,$C47:$Z47) -> 12.5 | AB47: =AVERAGEIF($C$6:$Z$6,AB$5,$C47:$Z47) -> 13.5
A48: Headcount – IT | B48: no. | C48: 40 | D48: 40 | E48: 41 | F48: 41 | G48: 41 | H48: 41 | I48: 42 | J48: 42 | K48: 42 | L48: 42 | M48: 43 | N48: 43 | O48: 43 | P48: 43 | Q48: 44 | R48: 50 | S48: 50 | T48: 50 | U48: 51 | V48: 51 | W48: 51 | X48: 51 | Y48: 52 | Z48: 52 | AA48: =AVERAGEIF($C$6:$Z$6,AA$5,$C48:$Z48) -> 41.5 | AB48: =AVERAGEIF($C$6:$Z$6,AB$5,$C48:$Z48) -> 49
A49: Headcount – Finance | B49: no. | C49: 26 | D49: 26 | E49: 26 | F49: 27 | G49: 27 | H49: 27 | I49: 27 | J49: 27 | K49: 27 | L49: 28 | M49: 28 | N49: 28 | O49: 28 | P49: 28 | Q49: 28 | R49: 29 | S49: 29 | T49: 29 | U49: 29 | V49: 29 | W49: 29 | X49: 30 | Y49: 30 | Z49: 30 | AA49: =AVERAGEIF($C$6:$Z$6,AA$5,$C49:$Z49) -> 27 | AB49: =AVERAGEIF($C$6:$Z$6,AB$5,$C49:$Z49) -> 29
A50: Headcount – total | B50: no. | C50: =C44+C45+C46+C47+C48+C49 -> 315 | D50: =D44+D45+D46+D47+D48+D49 -> 316 | E50: =E44+E45+E46+E47+E48+E49 -> 320 | F50: =F44+F45+F46+F47+F48+F49 -> 321 | G50: =G44+G45+G46+G47+G48+G49 -> 324 | H50: =H44+H45+H46+H47+H48+H49 -> 325 | I50: =I44+I45+I46+I47+I48+I49 -> 330 | J50: =J44+J45+J46+J47+J48+J49 -> 330 | ... AB50: =AB44+AB45+AB46+AB47+AB48+AB49 -> 357.5 | AC50: =IF(AA50=0,"",AB50/AA50-1) -> 0.093272171
A51: Operating metrics
A52: Marketing spend % of revenue | B52: % | C52: =IF(C12=0,0,(C25+C26)/C12) -> 0.33929549 | D52: =IF(D12=0,0,(D25+D26)/D12) -> 0.34075759 | E52: =IF(E12=0,0,(E25+E26)/E12) -> 0.33632234 | F52: =IF(F12=0,0,(F25+F26)/F12) -> 0.34208218 | G52: =IF(G12=0,0,(G25+G26)/G12) -> 0.34351185 | H52: =IF(H12=0,0,(H25+H26)/H12) -> 0.35845122 | I52: =IF(I12=0,0,(I25+I26)/I12) -> 0.32609707 | J52: =IF(J12=0,0,(J25+J26)/J12) -> 0.34049764 | ... AB52: =IF(AB12=0,0,(AB25+AB26)/AB12) -> 0.33010784 | AC52: =AB52-AA52 -> -0.00871324
A53: Employee cost % of revenue | B53: % | C53: =IF(C12=0,0,(C17+C20+C24+C28+C31+C34)/C12) -> 0.12146558 | D53: =IF(D12=0,0,(D17+D20+D24+D28+D31+D34)/D12) -> 0.12338986 | E53: =IF(E12=0,0,(E17+E20+E24+E28+E31+E34)/E12) -> 0.12283357 | F53: =IF(F12=0,0,(F17+F20+F24+F28+F31+F34)/F12) -> 0.12325645 | G53: =IF(G12=0,0,(G17+G20+G24+G28+G31+G34)/G12) -> 0.12279437 | H53: =IF(H12=0,0,(H17+H20+H24+H28+H31+H34)/H12) -> 0.11307049 | I53: =IF(I12=0,0,(I17+I20+I24+I28+I31+I34)/I12) -> 0.091111066 | J53: =IF(J12=0,0,(J17+J20+J24+J28+J31+J34)/J12) -> 0.096465592 | ... AB53: =IF(AB12=0,0,(AB17+AB20+AB24+AB28+AB31+AB34)/AB12) -> 0.11012261 | AC53: =AB53-AA53 -> -0.00099245183
A54: Fulfilment cost per order (₹) | B54: ₹ | C54: =IF(C9=0,0,C21*100000/C9) -> 45.087142 | D54: =IF(D9=0,0,D21*100000/D9) -> 45.36905 | E54: =IF(E9=0,0,E21*100000/E9) -> 46.421553 | F54: =IF(F9=0,0,F21*100000/F9) -> 45.577344 | G54: =IF(G9=0,0,G21*100000/G9) -> 46.00651 | H54: =IF(H9=0,0,H21*100000/H9) -> 47.246113 | I54: =IF(I9=0,0,I21*100000/I9) -> 46.174487 | J54: =IF(J9=0,0,J21*100000/J9) -> 46.992273 | ... AB54: =IF(AB9=0,0,AB21*100000/AB9) -> 51.174785 | AC54: =IF(AA54=0,"",AB54/AA54-1) -> 0.084087652
A55: ROAS (revenue ÷ marketing spend) | B55: x | C55: =IF((C25+C26)=0,0,C12/(C25+C26)) -> 2.9472835 | D55: =IF((D25+D26)=0,0,D12/(D25+D26)) -> 2.9346375 | E55: =IF((E25+E26)=0,0,E12/(E25+E26)) -> 2.973338 | F55: =IF((F25+F26)=0,0,F12/(F25+F26)) -> 2.9232742 | G55: =IF((G25+G26)=0,0,G12/(G25+G26)) -> 2.9111077 | H55: =IF((H25+H26)=0,0,H12/(H25+H26)) -> 2.7897799 | I55: =IF((I25+I26)=0,0,I12/(I25+I26)) -> 3.0665715 | J55: =IF((J25+J26)=0,0,J12/(J25+J26)) -> 2.9368779 | ... AB55: =IF((AB25+AB26)=0,0,AB12/(AB25+AB26)) -> 3.0293131 | AC55: =IF(AA55=0,"",AB55/AA55-1) -> 0.026395132
A56: Revenue per head per month (₹ lakh) | B56: ₹ lakh | C56: =IF(C50=0,0,C12/(C50*1)) -> 7.7780216 | D56: =IF(D50=0,0,D12/(D50*1)) -> 7.6607039 | E56: =IF(E50=0,0,E12/(E50*1)) -> 7.7594831 | F56: =IF(F50=0,0,F12/(F50*1)) -> 7.696134 | G56: =IF(G50=0,0,G12/(G50*1)) -> 7.706349 | H56: =IF(H50=0,0,H12/(H50*1)) -> 8.3161193 | I56: =IF(I50=0,0,I12/(I50*1)) -> 10.383597 | J56: =IF(J50=0,0,J12/(J50*1)) -> 9.8260816 | ... Z56: =IF(Z50=0,0,Z12/(Z50*1)) -> 9.4705735 | AA56: =IF(AA50=0,0,AA12/(AA50*12)) -> 8.5352467 | AB56: =IF(AB50=0,0,AB12/(AB50*12)) -> 9.3239997 | AC56: =IF(AA56=0,"",AB56/AA56-1) -> 0.092411272
A57: Avg personnel cost per head per month (₹ lakh) | B57: ₹ lakh | C57: =IF(C50=0,0,(C17+C20+C24+C28+C31+C34)/(C50*1)) -> 0.9447619 | D57: =IF(D50=0,0,(D17+D20+D24+D28+D31+D34)/(D50*1)) -> 0.94525316 | E57: =IF(E50=0,0,(E17+E20+E24+E28+E31+E34)/(E50*1)) -> 0.953125 | F57: =IF(F50=0,0,(F17+F20+F24+F28+F31+F34)/(F50*1)) -> 0.94859813 | G57: =IF(G50=0,0,(G17+G20+G24+G28+G31+G34)/(G50*1)) -> 0.9462963 | H57: =IF(H50=0,0,(H17+H20+H24+H28+H31+H34)/(H50*1)) -> 0.94030769 | I57: =IF(I50=0,0,(I17+I20+I24+I28+I31+I34)/(I50*1)) -> 0.94606061 | J57: =IF(J50=0,0,(J17+J20+J24+J28+J31+J34)/(J50*1)) -> 0.94787879 | ... Z57: =IF(Z50=0,0,(Z17+Z20+Z24+Z28+Z31+Z34)/(Z50*1)) -> 1.0280323 | AA57: =IF(AA50=0,0,(AA17+AA20+AA24+AA28+AA31+AA34)/(AA50*12)) -> 0.9483945 | AB57: =IF(AB50=0,0,(AB17+AB20+AB24+AB28+AB31+AB34)/(AB50*12)) -> 1.0267832 | AC57: =IF(AA57=0,"",AB57/AA57-1) -> 0.082654129
A59: Memo
A60: One-off items included in costs above | B60: ₹ lakh | C60: 0 | D60: 0 | E60: 0 | F60: 0 | G60: 120 | H60: 0 | I60: 0 | J60: 0 | K60: 0 | L60: 90 | M60: 0 | N60: 55 | O60: 0 | P60: 0 | Q60: 0 | R60: 0 | S60: 0 | T60: 0 | U60: 0 | V60: 0 | W60: 0 | X60: 0 | Y60: 0 | Z60: 0 | AA60: =SUMIF($C$6:$Z$6,AA$5,$C60:$Z60) -> 265 | AB60: =SUMIF($C$6:$Z$6,AB$5,$C60:$Z60) -> 0
A62: Events built into the history (so later variance analysis has realistic patterns to classify)
A63: Month | B63: Cost line | C63: Event | K63: Type
A64: 45505 | B64: IT – software, cloud & other | C64: ERP implementation cost (+₹120 lakh) | K64: One-off
A65: 45536 | B65: Marketing – performance | C65: Festive campaign spend pulled forward into Sep (reverses in Oct) | K65: Timing
A66: 45658 | B66: Operations – warehouse & other | C66: Warehouse relocation (+₹90 lakh) | K66: One-off
A67: 45658 | B67: Operations – fulfilment | C67: Courier rate hike, about +₹4 per order, permanent | K67: Structural
A68: 45717 | B68: Finance – prof. fees & admin | C68: GST assessment settlement (+₹55 lakh) | K68: One-off
A69: 45748 | B69: All personnel lines | C69: Annual appraisal cycle, +7% cost per head | K69: Structural
A70: 45839 | B70: IT – personnel & software | C70: 6 additional tech hires and new tooling | K70: Structural
A71: 45901 | B71: Marketing – performance | C71: Festive campaign spend pulled forward into Sep (reverses in Oct) | K71: Timing

Sheet Assumptions & Budget
A1: Assumptions & FY27 Budget (Apr-26 to Mar-27)
A2: Part A: every driver in its own labelled cell. Part B: monthly budget built from those drivers. ₹ lakh unless stated.
A3: Yellow fill / blue text = key assumption you can change · Black = formula · Green = link from another sheet
A5: A1. General settings
A6: Actuals loaded through (first day of month) | B6: date | C6: 46266 | D6: Change when a new month of actuals is entered on the Actual vs Budget sheet
A7: Months of actuals elapsed in FY27 | B7: months | C7: =COUNTIF($C$61:$N$61,"<="&$C$6) -> 6
A8: Materiality – % of budget | B8: % | C8: 0.05 | D8: A variance is material only if it breaches BOTH the % and ₹ thresholds
A9: Materiality – absolute amount | B9: ₹ lakh | C9: 25 | D9: Tested on YTD variance and on the run-rate (look-back) variance
A10: Run-rate look-back window | B10: months | C10: 3 | D10: Used to catch variances that only started recently
A11: Timing-variance reversal period | B11: months | C11: 2 | D11: Timing variances are assumed to reverse evenly over this many forecast months
A12: Cut-spend recovery % | B12: % | C12: 0.5 | D12: Share of the run-rate overspend assumed recovered when action = Cut spend
A14: A2. Revenue drivers
A15: FY27 order growth vs FY26 | B15: % | C15: 0.09 | D15: Honasa FY26 revenue growth was about 16%; slower growth assumed as base scales
A16: Monthly net AOV growth (from Mar-26 AOV) | B16: % / month | C16: 0.003 | D16: About +3.7% a year: modest price/mix, no big price rise
A18: A3. Cost drivers
A19: Budget gross margin % | B19: % | C19: 0.69 | D19: Benchmark: Honasa FY26 gross margin about 70%; model FY26 about 69%
A20: Marketplace & payment fees % of revenue | B20: % | C20: 0.03 | D20: Held at FY26 level
A21: FY26 average fulfilment cost per order | B21: ₹ | C21: ='Historical Data'!$AB$21*100000/'Historical Data'!$AB$9 -> 51.174785 | D21: Derived from Historical Data
A22: Courier / fulfilment cost inflation for FY27 | B22: % | C22: 0.02
A23: Budget fulfilment cost per order | B23: ₹ | C23: =C21*(1+C22) -> 52.198281
A24: Performance marketing % of revenue | B24: % | C24: 0.215 | D24: FY26 about 22.4%; efficiency gains assumed. Honasa total ad spend about 33% of revenue
A25: Brand & influencer % of revenue | B25: % | C25: 0.1 | D25: FY26 about 10.3%
A26: Annual appraisal increase (effective April) | B26: % | C26: 0.08 | D26: Applied to Q4 FY26 cost per head
A27: Growth over FY26 monthly average – Operations warehouse & other | B27: % | C27: 0.06 | D27: Semi-fixed line
A28: Growth over FY26 monthly average – HR other | B28: % | C28: 0.05
A29: Growth over FY26 monthly average – IT software & other | B29: % | C29: 0.12 | D29: Higher: new tools from FY26 tech hires run a full year
A30: Growth over FY26 monthly average – Finance prof. fees & admin | B30: % | C30: 0.06
A31: Growth over FY26 monthly average – D&A | B31: % | C31: 0.08
A33: A4. Budget average monthly cost per head (Q4 FY26 actual × (1 + appraisal))
A34: Sales | B34: ₹ lakh | C34: =SUM('Historical Data'!$X$17:$Z$17)/SUM('Historical Data'!$X$44:$Z$44)*(1+$C$26) -> 1.1867933
A35: Operations | B35: ₹ lakh | C35: =SUM('Historical Data'!$X$20:$Z$20)/SUM('Historical Data'!$X$45:$Z$45)*(1+$C$26) -> 0.67288591
A36: Marketing | B36: ₹ lakh | C36: =SUM('Historical Data'!$X$24:$Z$24)/SUM('Historical Data'!$X$46:$Z$46)*(1+$C$26) -> 1.4006598
A37: HR | B37: ₹ lakh | C37: =SUM('Historical Data'!$X$28:$Z$28)/SUM('Historical Data'!$X$47:$Z$47)*(1+$C$26) -> 1.0722857
A38: IT | B38: ₹ lakh | C38: =SUM('Historical Data'!$X$31:$Z$31)/SUM('Historical Data'!$X$48:$Z$48)*(1+$C$26) -> 1.8185806
A39: Finance | B39: ₹ lakh | C39: =SUM('Historical Data'!$X$34:$Z$34)/SUM('Historical Data'!$X$49:$Z$49)*(1+$C$26) -> 1.3104
A41: A5. Line classification (drives flexed budget; documents the nature of each line)
A42: Line item | B42: Cost centre | C42: Kind | D42: Type | E42: Flex basis
A43: Net revenue | B43: – | C43: Income | D43: Volume-driven | E43: None
A44: Cost of goods sold | B44: – | C44: Cost | D44: Variable | E44: Revenue
A45: Sales – personnel | B45: Sales | C45: Cost | D45: Committed | E45: None
A46: Sales – marketplace & payment fees | B46: Sales | C46: Cost | D46: Variable | E46: Revenue
A47: Operations – personnel | B47: Operations | C47: Cost | D47: Committed | E47: None
A48: Operations – fulfilment & logistics | B48: Operations | C48: Cost | D48: Variable | E48: Orders
A49: Operations – warehouse, QC & other | B49: Operations | C49: Cost | D49: Committed | E49: None
A50: Marketing – personnel | B50: Marketing | C50: Cost | D50: Committed | E50: None
A51: Marketing – performance marketing | B51: Marketing | C51: Cost | D51: Discretionary | E51: None
A52: Marketing – brand & influencer | B52: Marketing | C52: Cost | D52: Discretionary | E52: None
A53: HR – personnel | B53: HR | C53: Cost | D53: Committed | E53: None
... A58: Finance – professional fees, rent & admin | B58: Finance | C58: Cost | D58: Committed | E58: None
A60: B. FY27 BUDGET (monthly)
A61: Line item | B61: Unit | C61: 46113 | D61: 46143 | E61: 46174 | F61: 46204 | G61: 46235 | H61: 46266 | I61: 46296 | J61: 46327 | K61: 46357 | L61: 46388 | M61: 46419 | N61: 46447 | O61: FY27 Budget | P61: FY26 Actual | Q61: Growth % / Δ pp
A62: Revenue drivers
A63: Seasonality index | B63: index | C63: 0.95 | D63: 0.95 | E63: 0.92 | F63: 0.9 | G63: 0.95 | H63: 1 | I63: 1.2 | J63: 1.15 | K63: 1.05 | L63: 1 | M63: 0.95 | N63: 0.98 | O63: =SUM($C63:$N63) -> 12
A64: Orders (no.) | B64: no. | C64: ='Historical Data'!$AB$9*(1+$C$15)*C63/SUM($C$63:$N$63) -> 506521.99 | D64: ='Historical Data'!$AB$9*(1+$C$15)*D63/SUM($C$63:$N$63) -> 506521.99 | E64: ='Historical Data'!$AB$9*(1+$C$15)*E63/SUM($C$63:$N$63) -> 490526.56 | F64: ='Historical Data'!$AB$9*(1+$C$15)*F63/SUM($C$63:$N$63) -> 479862.94 | G64: ='Historical Data'!$AB$9*(1+$C$15)*G63/SUM($C$63:$N$63) -> 506521.99 | H64: ='Historical Data'!$AB$9*(1+$C$15)*H63/SUM($C$63:$N$63) -> 533181.04 | I64: ='Historical Data'!$AB$9*(1+$C$15)*I63/SUM($C$63:$N$63) -> 639817.25 | J64: ='Historical Data'!$AB$9*(1+$C$15)*J63/SUM($C$63:$N$63) -> 613158.2 | ... N64: ='Historical Data'!$AB$9*(1+$C$15)*N63/SUM($C$63:$N$63) -> 522517.42 | O64: =SUM($C64:$N64) -> 6398172.5 | P64: ='Historical Data'!AB9 -> 5869883 | Q64: =IF(P64=0,"",O64/P64-1) -> 0.09
A65: Net AOV (₹ per order) | B65: ₹ | C65: ='Historical Data'!$Z$10*(1+$C$16) -> 696.8844 | D65: =C65*(1+$C$16) -> 698.97505 | E65: =D65*(1+$C$16) -> 701.07198 | F65: =E65*(1+$C$16) -> 703.17519 | G65: =F65*(1+$C$16) -> 705.28472 | H65: =G65*(1+$C$16) -> 707.40057 | I65: =H65*(1+$C$16) -> 709.52278 | J65: =I65*(1+$C$16) -> 711.65134 | K65: =J65*(1+$C$16) -> 713.7863 | ... N65: =M65*(1+$C$16) -> 720.22967 | O65: =IF(O64=0,0,O67*100000/O64) -> 708.71315 | P65: ='Historical Data'!AB10 -> 681.44388 | Q65: =IF(P65=0,"",O65/P65-1) -> 0.040016895
A66: Profit & loss (₹ lakh)
A67: Net revenue | B67: ₹ lakh | C67: =C64*C65/100000 -> 3529.8727 | D67: =D64*D65/100000 -> 3540.4623 | E67: =E64*E65/100000 -> 3438.9442 | F67: =F64*F65/100000 -> 3374.2771 | G67: =G64*G65/100000 -> 3572.4222 | H67: =H64*H65/100000 -> 3771.7257 | I67: =I64*I65/100000 -> 4539.6491 | J67: =J64*J65/100000 -> 4363.5485 | ... N67: =N64*N65/100000 -> 3763.3255 | O67: =SUM($C67:$N67) -> 45344.69 | P67: ='Historical Data'!AB12 -> 39999.959 | Q67: =IF(P67=0,"",O67/P67-1) -> 0.13361842
A68: Cost of goods sold | B68: ₹ lakh | C68: =C67*(1-$C$19) -> 1094.2605 | D68: =D67*(1-$C$19) -> 1097.5433 | E68: =E67*(1-$C$19) -> 1066.0727 | F68: =F67*(1-$C$19) -> 1046.0259 | G68: =G67*(1-$C$19) -> 1107.4509 | H68: =H67*(1-$C$19) -> 1169.235 | I68: =I67*(1-$C$19) -> 1407.2912 | J68: =J67*(1-$C$19) -> 1352.7 | ... N68: =N67*(1-$C$19) -> 1166.6309 | O68: =SUM($C68:$N68) -> 14056.854 | P68: ='Historical Data'!AB13 -> 12423.9 | Q68: =IF(P68=0,"",O68/P68-1) -> 0.13143649
A69: Gross profit | B69: ₹ lakh | C69: =C67-C68 -> 2435.6122 | D69: =D67-D68 -> 2442.919 | E69: =E67-E68 -> 2372.8715 | F69: =F67-F68 -> 2328.2512 | G69: =G67-G68 -> 2464.9713 | H69: =H67-H68 -> 2602.4908 | I69: =I67-I68 -> 3132.3579 | J69: =J67-J68 -> 3010.8485 | ... O69: =O67-O68 -> 31287.836 | P69: ='Historical Data'!AB14 -> 27576.059 | Q69: =IF(P69=0,"",O69/P69-1) -> 0.13460144
A70: Gross margin % | B70: % | C70: =IF(C67=0,0,C69/C67) -> 0.69 | D70: =IF(D67=0,0,D69/D67) -> 0.69 | E70: =IF(E67=0,0,E69/E67) -> 0.69 | F70: =IF(F67=0,0,F69/F67) -> 0.69 | G70: =IF(G67=0,0,G69/G67) -> 0.69 | H70: =IF(H67=0,0,H69/H67) -> 0.69 | I70: =IF(I67=0,0,I69/I67) -> 0.69 | J70: =IF(J67=0,0,J69/J67) -> 0.69 | ... O70: =IF(O67=0,0,O69/O67) -> 0.69 | P70: ='Historical Data'!AB15 -> 0.68940218 | Q70: =O70-P70 -> 0.00059782109
A71: Operating costs by cost centre (₹ lakh)
A72: Sales – personnel | B72: ₹ lakh | C72: =C99*$C$34 -> 71.207598 | D72: =D99*$C$34 -> 71.207598 | E72: =E99*$C$34 -> 71.207598 | F72: =F99*$C$34 -> 71.207598 | G72: =G99*$C$34 -> 71.207598 | H72: =H99*$C$34 -> 73.581184 | I72: =I99*$C$34 -> 73.581184 | J72: =J99*$C$34 -> 73.581184 | ... N72: =N99*$C$34 -> 74.767978 | O72: =SUM($C72:$N72) -> 874.66666 | P72: ='Historical Data'!AB17 -> 753.8 | Q72: =IF(P72=0,"",O72/P72-1) -> 0.16034314
A73: Sales – marketplace & payment fees | B73: ₹ lakh | C73: =C67*$C$20 -> 105.89618 | D73: =D67*$C$20 -> 106.21387 | E73: =E67*$C$20 -> 103.16833 | F73: =F67*$C$20 -> 101.22831 | G73: =G67*$C$20 -> 107.17267 | H73: =H67*$C$20 -> 113.15177 | I73: =I67*$C$20 -> 136.18947 | J73: =J67*$C$20 -> 130.90646 | ... N73: =N67*$C$20 -> 112.89976 | O73: =SUM($C73:$N73) -> 1360.3407 | P73: ='Historical Data'!AB18 -> 1186.9 | Q73: =IF(P73=0,"",O73/P73-1) -> 0.14612915
A74: Sales – total | B74: ₹ lakh | C74: =C72+C73 -> 177.10378 | D74: =D72+D73 -> 177.42147 | E74: =E72+E73 -> 174.37592 | F74: =F72+F73 -> 172.43591 | G74: =G72+G73 -> 178.38026 | H74: =H72+H73 -> 186.73296 | I74: =I72+I73 -> 209.77066 | J74: =J72+J73 -> 204.48764 | ... O74: =O72+O73 -> 2235.0074 | P74: ='Historical Data'!AB19 -> 1940.7 | Q74: =IF(P74=0,"",O74/P74-1) -> 0.1516501
A75: Operations – personnel | B75: ₹ lakh | C75: =C100*$C$35 -> 100.93289 | D75: =D100*$C$35 -> 100.93289 | E75: =E100*$C$35 -> 100.93289 | F75: =F100*$C$35 -> 100.93289 | G75: =G100*$C$35 -> 100.93289 | H75: =H100*$C$35 -> 100.93289 | I75: =I100*$C$35 -> 100.93289 | J75: =J100*$C$35 -> 100.93289 | ... N75: =N100*$C$35 -> 103.62443 | O75: =SUM($C75:$N75) -> 1221.9608 | P75: ='Historical Data'!AB20 -> 1097.3 | Q75: =IF(P75=0,"",O75/P75-1) -> 0.11360686
A76: Operations – fulfilment & logistics | B76: ₹ lakh | C76: =C64*$C$23/100000 -> 264.39577 | D76: =D64*$C$23/100000 -> 264.39577 | E76: =E64*$C$23/100000 -> 256.04643 | F76: =F64*$C$23/100000 -> 250.4802 | G76: =G64*$C$23/100000 -> 264.39577 | H76: =H64*$C$23/100000 -> 278.31133 | I76: =I64*$C$23/100000 -> 333.9736 | J76: =J64*$C$23/100000 -> 320.05804 | ... N76: =N64*$C$23/100000 -> 272.74511 | O76: =SUM($C76:$N76) -> 3339.736 | P76: ='Historical Data'!AB21 -> 3003.9 | Q76: =IF(P76=0,"",O76/P76-1) -> 0.1118
A77: Operations – warehouse, QC & other | B77: ₹ lakh | C77: ='Historical Data'!$AB$22/12*(1+$C$27) -> 34.3175 | D77: ='Historical Data'!$AB$22/12*(1+$C$27) -> 34.3175 | E77: ='Historical Data'!$AB$22/12*(1+$C$27) -> 34.3175 | F77: ='Historical Data'!$AB$22/12*(1+$C$27) -> 34.3175 | G77: ='Historical Data'!$AB$22/12*(1+$C$27) -> 34.3175 | H77: ='Historical Data'!$AB$22/12*(1+$C$27) -> 34.3175 | I77: ='Historical Data'!$AB$22/12*(1+$C$27) -> 34.3175 | J77: ='Historical Data'!$AB$22/12*(1+$C$27) -> 34.3175 | ... N77: ='Historical Data'!$AB$22/12*(1+$C$27) -> 34.3175 | O77: =SUM($C77:$N77) -> 411.81 | P77: ='Historical Data'!AB22 -> 388.5 | Q77: =IF(P77=0,"",O77/P77-1) -> 0.06
A78: Operations – total | B78: ₹ lakh | C78: =C75+C76+C77 -> 399.64615 | D78: =D75+D76+D77 -> 399.64615 | E78: =E75+E76+E77 -> 391.29681 | F78: =F75+F76+F77 -> 385.73059 | G78: =G75+G76+G77 -> 399.64615 | H78: =H75+H76+H77 -> 413.56172 | I78: =I75+I76+I77 -> 469.22399 | J78: =J75+J76+J77 -> 455.30842 | ... O78: =O75+O76+O77 -> 4973.5068 | P78: ='Historical Data'!AB23 -> 4489.7 | Q78: =IF(P78=0,"",O78/P78-1) -> 0.10775928
A79: Marketing – personnel | B79: ₹ lakh | C79: =C101*$C$36 -> 91.042887 | D79: =D101*$C$36 -> 91.042887 | E79: =E101*$C$36 -> 91.042887 | F79: =F101*$C$36 -> 93.844206 | G79: =G101*$C$36 -> 93.844206 | H79: =H101*$C$36 -> 93.844206 | I79: =I101*$C$36 -> 93.844206 | J79: =J101*$C$36 -> 93.844206 | ... N79: =N101*$C$36 -> 93.844206 | O79: =SUM($C79:$N79) -> 1117.7265 | P79: ='Historical Data'!AB24 -> 980.4 | Q79: =IF(P79=0,"",O79/P79-1) -> 0.14007193
A80: Marketing – performance marketing | B80: ₹ lakh | C80: =C67*$C$24 -> 758.92263 | D80: =D67*$C$24 -> 761.1994 | E80: =E67*$C$24 -> 739.37301 | F80: =F67*$C$24 -> 725.46958 | G80: =G67*$C$24 -> 768.07077 | H80: =H67*$C$24 -> 810.92103 | I80: =I67*$C$24 -> 976.02455 | J80: =J67*$C$24 -> 938.16294 | ... N80: =N67*$C$24 -> 809.11497 | O80: =SUM($C80:$N80) -> 9749.1083 | P80: ='Historical Data'!AB25 -> 9005.1 | Q80: =IF(P80=0,"",O80/P80-1) -> 0.08262077
A81: Marketing – brand & influencer | B81: ₹ lakh | C81: =C67*$C$25 -> 352.98727 | D81: =D67*$C$25 -> 354.04623 | E81: =E67*$C$25 -> 343.89442 | F81: =F67*$C$25 -> 337.42771 | G81: =G67*$C$25 -> 357.24222 | H81: =H67*$C$25 -> 377.17257 | I81: =I67*$C$25 -> 453.96491 | J81: =J67*$C$25 -> 436.35485 | ... N81: =N67*$C$25 -> 376.33255 | O81: =SUM($C81:$N81) -> 4534.469 | P81: ='Historical Data'!AB26 -> 4199.2 | Q81: =IF(P81=0,"",O81/P81-1) -> 0.079841155
A82: Marketing – total | B82: ₹ lakh | C82: =C79+C80+C81 -> 1202.9528 | D82: =D79+D80+D81 -> 1206.2885 | E82: =E79+E80+E81 -> 1174.3103 | F82: =F79+F80+F81 -> 1156.7415 | G82: =G79+G80+G81 -> 1219.1572 | H82: =H79+H80+H81 -> 1281.9378 | I82: =I79+I80+I81 -> 1523.8337 | J82: =J79+J80+J81 -> 1468.362 | ... O82: =O79+O80+O81 -> 15401.304 | P82: ='Historical Data'!AB27 -> 14184.7 | Q82: =IF(P82=0,"",O82/P82-1) -> 0.085768736
A83: HR – personnel | B83: ₹ lakh | C83: =C102*$C$37 -> 15.012 | D83: =D102*$C$37 -> 15.012 | E83: =E102*$C$37 -> 15.012 | F83: =F102*$C$37 -> 15.012 | G83: =G102*$C$37 -> 15.012 | H83: =H102*$C$37 -> 15.012 | I83: =I102*$C$37 -> 15.012 | J83: =J102*$C$37 -> 15.012 | ... N83: =N102*$C$37 -> 15.012 | O83: =SUM($C83:$N83) -> 180.144 | P83: ='Historical Data'!AB28 -> 162 | Q83: =IF(P83=0,"",O83/P83-1) -> 0.112
A84: HR – recruitment, training & other | B84: ₹ lakh | C84: ='Historical Data'!$AB$29/12*(1+$C$28) -> 10.12375 | D84: ='Historical Data'!$AB$29/12*(1+$C$28) -> 10.12375 | E84: ='Historical Data'!$AB$29/12*(1+$C$28) -> 10.12375 | F84: ='Historical Data'!$AB$29/12*(1+$C$28) -> 10.12375 | G84: ='Historical Data'!$AB$29/12*(1+$C$28) -> 10.12375 | H84: ='Historical Data'!$AB$29/12*(1+$C$28) -> 10.12375 | I84: ='Historical Data'!$AB$29/12*(1+$C$28) -> 10.12375 | J84: ='Historical Data'!$AB$29/12*(1+$C$28) -> 10.12375 | ... N84: ='Historical Data'!$AB$29/12*(1+$C$28) -> 10.12375 | O84: =SUM($C84:$N84) -> 121.485 | P84: ='Historical Data'!AB29 -> 115.7 | Q84: =IF(P84=0,"",O84/P84-1) -> 0.05
A85: HR – total | B85: ₹ lakh | C85: =C83+C84 -> 25.13575 | D85: =D83+D84 -> 25.13575 | E85: =E83+E84 -> 25.13575 | F85: =F83+F84 -> 25.13575 | G85: =G83+G84 -> 25.13575 | H85: =H83+H84 -> 25.13575 | I85: =I83+I84 -> 25.13575 | J85: =J83+J84 -> 25.13575 | ... O85: =O83+O84 -> 301.629 | P85: ='Historical Data'!AB30 -> 277.7 | Q85: =IF(P85=0,"",O85/P85-1) -> 0.086168527
A86: IT – personnel | B86: ₹ lakh | C86: =C103*$C$38 -> 94.566194 | D86: =D103*$C$38 -> 94.566194 | E86: =E103*$C$38 -> 94.566194 | F86: =F103*$C$38 -> 98.203355 | G86: =G103*$C$38 -> 98.203355 | H86: =H103*$C$38 -> 98.203355 | I86: =I103*$C$38 -> 98.203355 | J86: =J103*$C$38 -> 98.203355 | ... N86: =N103*$C$38 -> 98.203355 | O86: =SUM($C86:$N86) -> 1167.5288 | P86: ='Historical Data'!AB31 -> 990.1 | Q86: =IF(P86=0,"",O86/P86-1) -> 0.17920288
A87: IT – software, cloud & other | B87: ₹ lakh | C87: ='Historical Data'!$AB$32/12*(1+$C$29) -> 52.210667 | D87: ='Historical Data'!$AB$32/12*(1+$C$29) -> 52.210667 | E87: ='Historical Data'!$AB$32/12*(1+$C$29) -> 52.210667 | F87: ='Historical Data'!$AB$32/12*(1+$C$29) -> 52.210667 | G87: ='Historical Data'!$AB$32/12*(1+$C$29) -> 52.210667 | H87: ='Historical Data'!$AB$32/12*(1+$C$29) -> 52.210667 | I87: ='Historical Data'!$AB$32/12*(1+$C$29) -> 52.210667 | J87: ='Historical Data'!$AB$32/12*(1+$C$29) -> 52.210667 | ... N87: ='Historical Data'!$AB$32/12*(1+$C$29) -> 52.210667 | O87: =SUM($C87:$N87) -> 626.528 | P87: ='Historical Data'!AB32 -> 559.4 | Q87: =IF(P87=0,"",O87/P87-1) -> 0.12
A88: IT – total | B88: ₹ lakh | C88: =C86+C87 -> 146.77686 | D88: =D86+D87 -> 146.77686 | E88: =E86+E87 -> 146.77686 | F88: =F86+F87 -> 150.41402 | G88: =G86+G87 -> 150.41402 | H88: =H86+H87 -> 150.41402 | I88: =I86+I87 -> 150.41402 | J88: =J86+J87 -> 150.41402 | ... O88: =O86+O87 -> 1794.0568 | P88: ='Historical Data'!AB33 -> 1549.5 | Q88: =IF(P88=0,"",O88/P88-1) -> 0.15782948
A89: Finance – personnel | B89: ₹ lakh | C89: =C104*$C$39 -> 39.312 | D89: =D104*$C$39 -> 39.312 | E89: =E104*$C$39 -> 39.312 | F89: =F104*$C$39 -> 39.312 | G89: =G104*$C$39 -> 39.312 | H89: =H104*$C$39 -> 39.312 | I89: =I104*$C$39 -> 40.6224 | J89: =J104*$C$39 -> 40.6224 | ... N89: =N104*$C$39 -> 40.6224 | O89: =SUM($C89:$N89) -> 479.6064 | P89: ='Historical Data'!AB34 -> 421.3 | Q89: =IF(P89=0,"",O89/P89-1) -> 0.13839639
A90: Finance – professional fees, rent & admin | B90: ₹ lakh | C90: ='Historical Data'!$AB$35/12*(1+$C$30) -> 62.071833 | D90: ='Historical Data'!$AB$35/12*(1+$C$30) -> 62.071833 | E90: ='Historical Data'!$AB$35/12*(1+$C$30) -> 62.071833 | F90: ='Historical Data'!$AB$35/12*(1+$C$30) -> 62.071833 | G90: ='Historical Data'!$AB$35/12*(1+$C$30) -> 62.071833 | H90: ='Historical Data'!$AB$35/12*(1+$C$30) -> 62.071833 | I90: ='Historical Data'!$AB$35/12*(1+$C$30) -> 62.071833 | J90: ='Historical Data'!$AB$35/12*(1+$C$30) -> 62.071833 | ... N90: ='Historical Data'!$AB$35/12*(1+$C$30) -> 62.071833 | O90: =SUM($C90:$N90) -> 744.862 | P90: ='Historical Data'!AB35 -> 702.7 | Q90: =IF(P90=0,"",O90/P90-1) -> 0.06
A91: Finance – total | B91: ₹ lakh | C91: =C89+C90 -> 101.38383 | D91: =D89+D90 -> 101.38383 | E91: =E89+E90 -> 101.38383 | F91: =F89+F90 -> 101.38383 | G91: =G89+G90 -> 101.38383 | H91: =H89+H90 -> 101.38383 | I91: =I89+I90 -> 102.69423 | J91: =J89+J90 -> 102.69423 | ... O91: =O89+O90 -> 1224.4684 | P91: ='Historical Data'!AB36 -> 1124 | Q91: =IF(P91=0,"",O91/P91-1) -> 0.089384698
A92: Total operating cost & profitability (₹ lakh)
A93: Total operating cost | B93: ₹ lakh | C93: =C74+C78+C82+C85+C88+C91 -> 2052.9992 | D93: =D74+D78+D82+D85+D88+D91 -> 2056.6526 | E93: =E74+E78+E82+E85+E88+E91 -> 2013.2795 | F93: =F74+F78+F82+F85+F88+F91 -> 1991.8416 | G93: =G74+G78+G82+G85+G88+G91 -> 2074.1172 | H93: =H74+H78+H82+H85+H88+H91 -> 2159.1661 | I93: =I74+I78+I82+I85+I88+I91 -> 2481.0723 | J93: =J74+J78+J82+J85+J88+J91 -> 2406.4021 | ... O93: =O74+O78+O82+O85+O88+O91 -> 25929.972 | P93: ='Historical Data'!AB38 -> 23566.3 | Q93: =IF(P93=0,"",O93/P93-1) -> 0.10029882
A94: EBITDA | B94: ₹ lakh | C94: =C69-C93 -> 382.613 | D94: =D69-D93 -> 386.26642 | E94: =E69-E93 -> 359.59202 | F94: =F69-F93 -> 336.40961 | G94: =G69-G93 -> 390.85409 | H94: =H69-H93 -> 443.32466 | I94: =I69-I93 -> 651.28555 | J94: =J69-J93 -> 604.44643 | ... O94: =O69-O93 -> 5357.8638 | P94: ='Historical Data'!AB39 -> 4009.7586 | Q94: =IF(P94=0,"",O94/P94-1) -> 0.33620606
A95: EBITDA margin % | B95: % | C95: =IF(C67=0,0,C94/C67) -> 0.10839286 | D95: =IF(D67=0,0,D94/D67) -> 0.10910056 | E95: =IF(E67=0,0,E94/E67) -> 0.10456466 | F95: =IF(F67=0,0,F94/F67) -> 0.099698276 | G95: =IF(G67=0,0,G94/G67) -> 0.10940871 | H95: =IF(H67=0,0,H94/H67) -> 0.11753894 | I95: =IF(I67=0,0,I94/I67) -> 0.14346606 | J95: =IF(J67=0,0,J94/J67) -> 0.13852176 | ... O95: =IF(O67=0,0,O94/O67) -> 0.11815857 | P95: ='Historical Data'!AB40 -> 0.10024407 | Q95: =O95-P95 -> 0.017914502
A96: Depreciation & amortisation | B96: ₹ lakh | C96: ='Historical Data'!$AB$41/12*(1+$C$31) -> 70.632 | D96: ='Historical Data'!$AB$41/12*(1+$C$31) -> 70.632 | E96: ='Historical Data'!$AB$41/12*(1+$C$31) -> 70.632 | F96: ='Historical Data'!$AB$41/12*(1+$C$31) -> 70.632 | G96: ='Historical Data'!$AB$41/12*(1+$C$31) -> 70.632 | H96: ='Historical Data'!$AB$41/12*(1+$C$31) -> 70.632 | I96: ='Historical Data'!$AB$41/12*(1+$C$31) -> 70.632 | J96: ='Historical Data'!$AB$41/12*(1+$C$31) -> 70.632 | ... N96: ='Historical Data'!$AB$41/12*(1+$C$31) -> 70.632 | O96: =SUM($C96:$N96) -> 847.584 | P96: ='Historical Data'!AB41 -> 784.8 | Q96: =IF(P96=0,"",O96/P96-1) -> 0.08
A97: EBIT | B97: ₹ lakh | C97: =C94-C96 -> 311.981 | D97: =D94-D96 -> 315.63442 | E97: =E94-E96 -> 288.96002 | F97: =F94-F96 -> 265.77761 | G97: =G94-G96 -> 320.22209 | H97: =H94-H96 -> 372.69266 | I97: =I94-I96 -> 580.65355 | J97: =J94-J96 -> 533.81443 | ... O97: =O94-O96 -> 4510.2798 | P97: ='Historical Data'!AB42 -> 3224.9586 | Q97: =IF(P97=0,"",O97/P97-1) -> 0.3985543
A98: Headcount (closing)
A99: Headcount – Sales | B99: no. | C99: 60 | D99: 60 | E99: 60 | F99: 60 | G99: 60 | H99: 62 | I99: 62 | J99: 62 | K99: 62 | L99: 63 | M99: 63 | N99: 63 | O99: =AVERAGE($C99:$N99) -> 61.416667 | P99: ='Historical Data'!AB44 -> 57.666667 | Q99: =IF(P99=0,"",O99/P99-1) -> 0.065028902
A100: Headcount – Operations | B100: no. | C100: 150 | D100: 150 | E100: 150 | F100: 150 | G100: 150 | H100: 150 | I100: 150 | J100: 150 | K100: 154 | L100: 154 | M100: 154 | N100: 154 | O100: =AVERAGE($C100:$N100) -> 151.33333 | P100: ='Historical Data'!AB45 -> 145.66667 | Q100: =IF(P100=0,"",O100/P100-1) -> 0.038901602
A101: Headcount – Marketing | B101: no. | C101: 65 | D101: 65 | E101: 65 | F101: 67 | G101: 67 | H101: 67 | I101: 67 | J101: 67 | K101: 67 | L101: 67 | M101: 67 | N101: 67 | O101: =AVERAGE($C101:$N101) -> 66.5 | P101: ='Historical Data'!AB46 -> 62.666667 | Q101: =IF(P101=0,"",O101/P101-1) -> 0.061170213
A102: Headcount – HR | B102: no. | C102: 14 | D102: 14 | E102: 14 | F102: 14 | G102: 14 | H102: 14 | I102: 14 | J102: 14 | K102: 14 | L102: 14 | M102: 14 | N102: 14 | O102: =AVERAGE($C102:$N102) -> 14 | P102: ='Historical Data'!AB47 -> 13.5 | Q102: =IF(P102=0,"",O102/P102-1) -> 0.037037037
A103: Headcount – IT | B103: no. | C103: 52 | D103: 52 | E103: 52 | F103: 54 | G103: 54 | H103: 54 | I103: 54 | J103: 54 | K103: 54 | L103: 54 | M103: 54 | N103: 54 | O103: =AVERAGE($C103:$N103) -> 53.5 | P103: ='Historical Data'!AB48 -> 49 | Q103: =IF(P103=0,"",O103/P103-1) -> 0.091836735
A104: Headcount – Finance | B104: no. | C104: 30 | D104: 30 | E104: 30 | F104: 30 | G104: 30 | H104: 30 | I104: 31 | J104: 31 | K104: 31 | L104: 31 | M104: 31 | N104: 31 | O104: =AVERAGE($C104:$N104) -> 30.5 | P104: ='Historical Data'!AB49 -> 29 | Q104: =IF(P104=0,"",O104/P104-1) -> 0.051724138
A105: Headcount – total | B105: no. | C105: =C99+C100+C101+C102+C103+C104 -> 371 | D105: =D99+D100+D101+D102+D103+D104 -> 371 | E105: =E99+E100+E101+E102+E103+E104 -> 371 | F105: =F99+F100+F101+F102+F103+F104 -> 375 | G105: =G99+G100+G101+G102+G103+G104 -> 375 | H105: =H99+H100+H101+H102+H103+H104 -> 377 | I105: =I99+I100+I101+I102+I103+I104 -> 378 | J105: =J99+J100+J101+J102+J103+J104 -> 378 | ... O105: =O99+O100+O101+O102+O103+O104 -> 377.25 | P105: ='Historical Data'!AB50 -> 357.5 | Q105: =IF(P105=0,"",O105/P105-1) -> 0.055244755
A106: Operating metrics
A107: Marketing spend % of revenue | B107: % | C107: =IF(C67=0,0,(C80+C81)/C67) -> 0.315 | D107: =IF(D67=0,0,(D80+D81)/D67) -> 0.315 | E107: =IF(E67=0,0,(E80+E81)/E67) -> 0.315 | F107: =IF(F67=0,0,(F80+F81)/F67) -> 0.315 | G107: =IF(G67=0,0,(G80+G81)/G67) -> 0.315 | H107: =IF(H67=0,0,(H80+H81)/H67) -> 0.315 | I107: =IF(I67=0,0,(I80+I81)/I67) -> 0.315 | J107: =IF(J67=0,0,(J80+J81)/J67) -> 0.315 | ... O107: =IF(O67=0,0,(O80+O81)/O67) -> 0.315 | P107: ='Historical Data'!AB52 -> 0.33010784 | Q107: =O107-P107 -> -0.015107841
A108: Employee cost % of revenue | B108: % | C108: =IF(C67=0,0,(C72+C75+C79+C83+C86+C89)/C67) -> 0.11673893 | D108: =IF(D67=0,0,(D72+D75+D79+D83+D86+D89)/D67) -> 0.11638976 | E108: =IF(E67=0,0,(E72+E75+E79+E83+E86+E89)/E67) -> 0.1198256 | F108: =IF(F67=0,0,(F72+F75+F79+F83+F86+F89)/F67) -> 0.12403013 | G108: =IF(G67=0,0,(G72+G75+G79+G83+G86+G89)/G67) -> 0.11715078 | H108: =IF(H67=0,0,(H72+H75+H79+H83+H86+H89)/H67) -> 0.11158967 | I108: =IF(I67=0,0,(I72+I75+I79+I83+I86+I89)/I67) -> 0.093001909 | J108: =IF(J67=0,0,(J72+J75+J79+J83+J86+J89)/J67) -> 0.096755205 | ... O108: =IF(O67=0,0,(O72+O75+O79+O83+O86+O89)/O67) -> 0.11118464 | P108: ='Historical Data'!AB53 -> 0.11012261 | Q108: =O108-P108 -> 0.0010620294
A109: Fulfilment cost per order (₹) | B109: ₹ | C109: =IF(C64=0,0,C76*100000/C64) -> 52.198281 | D109: =IF(D64=0,0,D76*100000/D64) -> 52.198281 | E109: =IF(E64=0,0,E76*100000/E64) -> 52.198281 | F109: =IF(F64=0,0,F76*100000/F64) -> 52.198281 | G109: =IF(G64=0,0,G76*100000/G64) -> 52.198281 | H109: =IF(H64=0,0,H76*100000/H64) -> 52.198281 | I109: =IF(I64=0,0,I76*100000/I64) -> 52.198281 | J109: =IF(J64=0,0,J76*100000/J64) -> 52.198281 | ... O109: =IF(O64=0,0,O76*100000/O64) -> 52.198281 | P109: ='Historical Data'!AB54 -> 51.174785 | Q109: =IF(P109=0,"",O109/P109-1) -> 0.02
A110: ROAS (revenue ÷ marketing spend) | B110: x | C110: =IF((C80+C81)=0,0,C67/(C80+C81)) -> 3.1746032 | D110: =IF((D80+D81)=0,0,D67/(D80+D81)) -> 3.1746032 | E110: =IF((E80+E81)=0,0,E67/(E80+E81)) -> 3.1746032 | F110: =IF((F80+F81)=0,0,F67/(F80+F81)) -> 3.1746032 | G110: =IF((G80+G81)=0,0,G67/(G80+G81)) -> 3.1746032 | H110: =IF((H80+H81)=0,0,H67/(H80+H81)) -> 3.1746032 | I110: =IF((I80+I81)=0,0,I67/(I80+I81)) -> 3.1746032 | J110: =IF((J80+J81)=0,0,J67/(J80+J81)) -> 3.1746032 | ... O110: =IF((O80+O81)=0,0,O67/(O80+O81)) -> 3.1746032 | P110: ='Historical Data'!AB55 -> 3.0293131 | Q110: =IF(P110=0,"",O110/P110-1) -> 0.047961401
...

Sheet Actual vs Budget
A1: Actual vs Budget – FY27 (₹ lakh)
A2: Variances are signed so that POSITIVE = favourable and NEGATIVE = unfavourable on every line (costs: budget − actual; income: actual − budget).
A3: Actuals loaded through | C3: ='Assumptions & Budget'!$C$6 -> 46266 | D3: Months elapsed | F3: ='Assumptions & Budget'!$C$7 -> 6 | G3: Apr–Sep 2026 actuals are SIMULATED (synthetic) for demonstration. Replace blue cells with real actuals when available.
A5: Line item | B5: Unit | C5: ='Assumptions & Budget'!C61 -> 46113 | D5: ='Assumptions & Budget'!D61 -> 46143 | E5: ='Assumptions & Budget'!E61 -> 46174 | F5: ='Assumptions & Budget'!F61 -> 46204 | G5: ='Assumptions & Budget'!G61 -> 46235 | H5: ='Assumptions & Budget'!H61 -> 46266 | I5: ='Assumptions & Budget'!I61 -> 46296 | J5: ='Assumptions & Budget'!J61 -> 46327 | ... N5: ='Assumptions & Budget'!N61 -> 46447 | O5: YTD | P5: YTD var %
A6: Status | C6: =IF(C5<=$C$3,"Actual","–") -> Actual | D6: =IF(D5<=$C$3,"Actual","–") -> Actual | E6: =IF(E5<=$C$3,"Actual","–") -> Actual | F6: =IF(F5<=$C$3,"Actual","–") -> Actual | G6: =IF(G5<=$C$3,"Actual","–") -> Actual | H6: =IF(H5<=$C$3,"Actual","–") -> Actual | I6: =IF(I5<=$C$3,"Actual","–") -> – | J6: =IF(J5<=$C$3,"Actual","–") -> – | ... N6: =IF(N5<=$C$3,"Actual","–") -> –
A8: BLOCK 1 – ACTUALS (blue = input; enter monthly actuals as months close)
A9: Revenue drivers
A10: Orders (no.) | B10: no. | C10: 512605 | D10: 504896 | E10: 502172 | F10: 490655 | G10: 516802 | H10: 545874 | O10: =SUMIFS($C10:$N10,$C$5:$N$5,"<="&$C$3) -> 3073004
A11: Net AOV (₹ per order) | B11: ₹ | C11: 695.6 | D11: 693.3 | E11: 701.4 | F11: 696 | G11: 695.8 | H11: 700.1 | O11: =IF(O10=0,0,O13*100000/O10) -> 697.06677
A12: Profit & loss (₹ lakh)
A13: Net revenue | B13: ₹ lakh | C13: =C10*C11/100000 -> 3565.6804 | D13: =D10*D11/100000 -> 3500.444 | E13: =E10*E11/100000 -> 3522.2344 | F13: =F10*F11/100000 -> 3414.9588 | G13: =G10*G11/100000 -> 3595.9083 | H13: =H10*H11/100000 -> 3821.6639 | I13: =I10*I11/100000 -> 0 | J13: =J10*J11/100000 -> 0 | ... N13: =N10*N11/100000 -> 0 | O13: =SUMIFS($C13:$N13,$C$5:$N$5,"<="&$C$3) -> 21420.89
A14: Cost of goods sold | B14: ₹ lakh | C14: 1108.3 | D14: 1104.5 | E14: 1098.1 | F14: 997.8 | G14: 1036.4 | H14: 1119.8 | O14: =SUMIFS($C14:$N14,$C$5:$N$5,"<="&$C$3) -> 6464.9
A15: Gross profit | B15: ₹ lakh | C15: =C13-C14 -> 2457.3804 | D15: =D13-D14 -> 2395.944 | E15: =E13-E14 -> 2424.1344 | F15: =F13-F14 -> 2417.1588 | G15: =G13-G14 -> 2559.5083 | H15: =H13-H14 -> 2701.8639 | I15: =I13-I14 -> 0 | J15: =J13-J14 -> 0 | ... O15: =O13-O14 -> 14955.99
A16: Gross margin % | B16: % | C16: =IF(C13=0,0,C15/C13) -> 0.68917573 | D16: =IF(D13=0,0,D15/D13) -> 0.6844686 | E16: =IF(E13=0,0,E15/E13) -> 0.68823767 | F16: =IF(F13=0,0,F15/F13) -> 0.70781492 | G16: =IF(G13=0,0,G15/G13) -> 0.71178353 | H16: =IF(H13=0,0,H15/H13) -> 0.70698627 | I16: =IF(I13=0,0,I15/I13) -> 0 | J16: =IF(J13=0,0,J15/J13) -> 0 | ... O16: =IF(O13=0,0,O15/O13) -> 0.69819648
A17: Operating costs by cost centre (₹ lakh)
A18: Sales – personnel | B18: ₹ lakh | C18: 76.7 | D18: 77 | E18: 77.1 | F18: 77.5 | G18: 77.5 | H18: 80 | O18: =SUMIFS($C18:$N18,$C$5:$N$5,"<="&$C$3) -> 465.8
A19: Sales – marketplace & payment fees | B19: ₹ lakh | C19: 105.7 | D19: 101.5 | E19: 106 | F19: 120 | G19: 121.3 | H19: 129.9 | O19: =SUMIFS($C19:$N19,$C$5:$N$5,"<="&$C$3) -> 684.4
A20: Sales – total | B20: ₹ lakh | C20: =C18+C19 -> 182.4 | D20: =D18+D19 -> 178.5 | E20: =E18+E19 -> 183.1 | F20: =F18+F19 -> 197.5 | G20: =G18+G19 -> 198.8 | H20: =H18+H19 -> 209.9 | I20: =I18+I19 -> 0 | J20: =J18+J19 -> 0 | ... O20: =O18+O19 -> 1150.2
A21: Operations – personnel | B21: ₹ lakh | C21: 100.1 | D21: 101.2 | E21: 101 | F21: 100.4 | G21: 100.6 | H21: 101.4 | O21: =SUMIFS($C21:$N21,$C$5:$N$5,"<="&$C$3) -> 604.7
A22: Operations – fulfilment & logistics | B22: ₹ lakh | C22: 270.4 | D22: 266.5 | E22: 282.5 | F22: 279.7 | G22: 293.4 | H22: 306.9 | O22: =SUMIFS($C22:$N22,$C$5:$N$5,"<="&$C$3) -> 1699.4
A23: Operations – warehouse, QC & other | B23: ₹ lakh | C23: 35.7 | D23: 34.1 | E23: 34.4 | F23: 103.8 | G23: 35.9 | H23: 34.7 | O23: =SUMIFS($C23:$N23,$C$5:$N$5,"<="&$C$3) -> 278.6
A24: Operations – total | B24: ₹ lakh | C24: =C21+C22+C23 -> 406.2 | D24: =D21+D22+D23 -> 401.8 | E24: =E21+E22+E23 -> 417.9 | F24: =F21+F22+F23 -> 483.9 | G24: =G21+G22+G23 -> 429.9 | H24: =H21+H22+H23 -> 443 | I24: =I21+I22+I23 -> 0 | J24: =J21+J22+J23 -> 0 | ... O24: =O21+O22+O23 -> 2582.7
A25: Marketing – personnel | B25: ₹ lakh | C25: 90.7 | D25: 89.2 | E25: 92 | F25: 93.9 | G25: 93.5 | H25: 92.6 | O25: =SUMIFS($C25:$N25,$C$5:$N$5,"<="&$C$3) -> 551.9
A26: Marketing – performance marketing | B26: ₹ lakh | C26: 757.8 | D26: 745.1 | E26: 735.5 | F26: 718 | G26: 830.3 | H26: 948.7 | O26: =SUMIFS($C26:$N26,$C$5:$N$5,"<="&$C$3) -> 4735.4
A27: Marketing – brand & influencer | B27: ₹ lakh | C27: 360.1 | D27: 349.7 | E27: 401.3 | F27: 378 | G27: 405.6 | H27: 425.4 | O27: =SUMIFS($C27:$N27,$C$5:$N$5,"<="&$C$3) -> 2320.1
A28: Marketing – total | B28: ₹ lakh | C28: =C25+C26+C27 -> 1208.6 | D28: =D25+D26+D27 -> 1184 | E28: =E25+E26+E27 -> 1228.8 | F28: =F25+F26+F27 -> 1189.9 | G28: =G25+G26+G27 -> 1329.4 | H28: =H25+H26+H27 -> 1466.7 | I28: =I25+I26+I27 -> 0 | J28: =J25+J26+J27 -> 0 | ... O28: =O25+O26+O27 -> 7607.4
A29: HR – personnel | B29: ₹ lakh | C29: 14 | D29: 13.9 | E29: 13.9 | F29: 13.9 | G29: 13.9 | H29: 14.9 | O29: =SUMIFS($C29:$N29,$C$5:$N$5,"<="&$C$3) -> 84.5
A30: HR – recruitment, training & other | B30: ₹ lakh | C30: 10.2 | D30: 9.2 | E30: 9.7 | F30: 10.7 | G30: 10 | H30: 10.2 | O30: =SUMIFS($C30:$N30,$C$5:$N$5,"<="&$C$3) -> 60
A31: HR – total | B31: ₹ lakh | C31: =C29+C30 -> 24.2 | D31: =D29+D30 -> 23.1 | E31: =E29+E30 -> 23.6 | F31: =F29+F30 -> 24.6 | G31: =G29+G30 -> 23.9 | H31: =H29+H30 -> 25.1 | I31: =I29+I30 -> 0 | J31: =J29+J30 -> 0 | ... O31: =O29+O30 -> 144.5
A32: IT – personnel | B32: ₹ lakh | C32: 94 | D32: 94.3 | E32: 95.7 | F32: 98.9 | G32: 97.5 | H32: 99.5 | O32: =SUMIFS($C32:$N32,$C$5:$N$5,"<="&$C$3) -> 579.9
A33: IT – software, cloud & other | B33: ₹ lakh | C33: 52.2 | D33: 50.7 | E33: 138.4 | F33: 50.1 | G33: 52.2 | H33: 50.9 | O33: =SUMIFS($C33:$N33,$C$5:$N$5,"<="&$C$3) -> 394.5
A34: IT – total | B34: ₹ lakh | C34: =C32+C33 -> 146.2 | D34: =D32+D33 -> 145 | E34: =E32+E33 -> 234.1 | F34: =F32+F33 -> 149 | G34: =G32+G33 -> 149.7 | H34: =H32+H33 -> 150.4 | I34: =I32+I33 -> 0 | J34: =J32+J33 -> 0 | ... O34: =O32+O33 -> 974.4
A35: Finance – personnel | B35: ₹ lakh | C35: 39.5 | D35: 39.1 | E35: 39 | F35: 39.1 | G35: 39.2 | H35: 39.2 | O35: =SUMIFS($C35:$N35,$C$5:$N$5,"<="&$C$3) -> 235.1
A36: Finance – professional fees, rent & admin | B36: ₹ lakh | C36: 59.6 | D36: 64 | E36: 62.2 | F36: 63.3 | G36: 64.2 | H36: 62.5 | O36: =SUMIFS($C36:$N36,$C$5:$N$5,"<="&$C$3) -> 375.8
A37: Finance – total | B37: ₹ lakh | C37: =C35+C36 -> 99.1 | D37: =D35+D36 -> 103.1 | E37: =E35+E36 -> 101.2 | F37: =F35+F36 -> 102.4 | G37: =G35+G36 -> 103.4 | H37: =H35+H36 -> 101.7 | I37: =I35+I36 -> 0 | J37: =J35+J36 -> 0 | ... O37: =O35+O36 -> 610.9
A38: Total operating cost & profitability (₹ lakh)
A39: Total operating cost | B39: ₹ lakh | C39: =C20+C24+C28+C31+C34+C37 -> 2066.7 | D39: =D20+D24+D28+D31+D34+D37 -> 2035.5 | E39: =E20+E24+E28+E31+E34+E37 -> 2188.7 | F39: =F20+F24+F28+F31+F34+F37 -> 2147.3 | G39: =G20+G24+G28+G31+G34+G37 -> 2235.1 | H39: =H20+H24+H28+H31+H34+H37 -> 2396.8 | I39: =I20+I24+I28+I31+I34+I37 -> 0 | J39: =J20+J24+J28+J31+J34+J37 -> 0 | ... O39: =O20+O24+O28+O31+O34+O37 -> 13070.1
A40: EBITDA | B40: ₹ lakh | C40: =C15-C39 -> 390.68038 | D40: =D15-D39 -> 360.44397 | E40: =E15-E39 -> 235.43441 | F40: =F15-F39 -> 269.8588 | G40: =G15-G39 -> 324.40832 | H40: =H15-H39 -> 305.06387 | I40: =I15-I39 -> 0 | J40: =J15-J39 -> 0 | ... O40: =O15-O39 -> 1885.8897
A41: EBITDA margin % | B41: % | C41: =IF(C13=0,0,C40/C13) -> 0.10956685 | D41: =IF(D13=0,0,D40/D13) -> 0.10297093 | E41: =IF(E13=0,0,E40/E13) -> 0.066842345 | F41: =IF(F13=0,0,F40/F13) -> 0.079022564 | G41: =IF(G13=0,0,G40/G13) -> 0.090215959 | H41: =IF(H13=0,0,H40/H13) -> 0.079824884 | I41: =IF(I13=0,0,I40/I13) -> 0 | J41: =IF(J13=0,0,J40/J13) -> 0 | ... O41: =IF(O13=0,0,O40/O13) -> 0.088039749
A42: Depreciation & amortisation | B42: ₹ lakh | C42: 70.5 | D42: 70.3 | E42: 70.8 | F42: 69.9 | G42: 70.9 | H42: 70.8 | O42: =SUMIFS($C42:$N42,$C$5:$N$5,"<="&$C$3) -> 423.2
A43: EBIT | B43: ₹ lakh | C43: =C40-C42 -> 320.18038 | D43: =D40-D42 -> 290.14397 | E43: =E40-E42 -> 164.63441 | F43: =F40-F42 -> 199.9588 | G43: =G40-G42 -> 253.50832 | H43: =H40-H42 -> 234.26387 | I43: =I40-I42 -> 0 | J43: =J40-J42 -> 0 | ... O43: =O40-O42 -> 1462.6897
A44: Headcount (closing)
A45: Headcount – Sales | B45: no. | C45: 65 | D45: 65 | E45: 65 | F45: 65 | G45: 65 | H45: 67 | O45: =IFERROR(AVERAGEIFS($C45:$N45,$C$5:$N$5,"<="&$C$3),0) -> 65.333333
A46: Headcount – Operations | B46: no. | C46: 150 | D46: 150 | E46: 150 | F46: 150 | G46: 150 | H46: 150 | O46: =IFERROR(AVERAGEIFS($C46:$N46,$C$5:$N$5,"<="&$C$3),0) -> 150
A47: Headcount – Marketing | B47: no. | C47: 65 | D47: 65 | E47: 65 | F47: 67 | G47: 67 | H47: 67 | O47: =IFERROR(AVERAGEIFS($C47:$N47,$C$5:$N$5,"<="&$C$3),0) -> 66
A48: Headcount – HR | B48: no. | C48: 13 | D48: 13 | E48: 13 | F48: 13 | G48: 13 | H48: 14 | O48: =IFERROR(AVERAGEIFS($C48:$N48,$C$5:$N$5,"<="&$C$3),0) -> 13.166667
A49: Headcount – IT | B49: no. | C49: 52 | D49: 52 | E49: 52 | F49: 54 | G49: 54 | H49: 54 | O49: =IFERROR(AVERAGEIFS($C49:$N49,$C$5:$N$5,"<="&$C$3),0) -> 53
A50: Headcount – Finance | B50: no. | C50: 30 | D50: 30 | E50: 30 | F50: 30 | G50: 30 | H50: 30 | O50: =IFERROR(AVERAGEIFS($C50:$N50,$C$5:$N$5,"<="&$C$3),0) -> 30
A51: Headcount – total | B51: no. | C51: =C45+C46+C47+C48+C49+C50 -> 375 | D51: =D45+D46+D47+D48+D49+D50 -> 375 | E51: =E45+E46+E47+E48+E49+E50 -> 375 | F51: =F45+F46+F47+F48+F49+F50 -> 379 | G51: =G45+G46+G47+G48+G49+G50 -> 379 | H51: =H45+H46+H47+H48+H49+H50 -> 382 | I51: =I45+I46+I47+I48+I49+I50 -> 0 | J51: =J45+J46+J47+J48+J49+J50 -> 0 | ... O51: =O45+O46+O47+O48+O49+O50 -> 377.5
A52: Operating metrics
A53: Marketing spend % of revenue | B53: % | C53: =IF(C13=0,0,(C26+C27)/C13) -> 0.3135166 | D53: =IF(D13=0,0,(D26+D27)/D13) -> 0.31276033 | E53: =IF(E13=0,0,(E26+E27)/E13) -> 0.32274967 | F53: =IF(F13=0,0,(F26+F27)/F13) -> 0.32094091 | G53: =IF(G13=0,0,(G26+G27)/G13) -> 0.34369619 | H53: =IF(H13=0,0,(H26+H27)/H13) -> 0.35955543 | I53: =IF(I13=0,0,(I26+I27)/I13) -> 0 | J53: =IF(J13=0,0,(J26+J27)/J13) -> 0 | ... O53: =IF(O13=0,0,(O26+O27)/O13) -> 0.32937474
A54: Employee cost % of revenue | B54: % | C54: =IF(C13=0,0,(C18+C21+C25+C29+C32+C35)/C13) -> 0.11638732 | D54: =IF(D13=0,0,(D18+D21+D25+D29+D32+D35)/D13) -> 0.11847069 | E54: =IF(E13=0,0,(E18+E21+E25+E29+E32+E35)/E13) -> 0.11887341 | F54: =IF(F13=0,0,(F18+F21+F25+F29+F32+F35)/F13) -> 0.12407178 | G54: =IF(G13=0,0,(G18+G21+G25+G29+G32+G35)/G13) -> 0.11741122 | H54: =IF(H13=0,0,(H18+H21+H25+H29+H32+H35)/H13) -> 0.11188844 | I54: =IF(I13=0,0,(I18+I21+I25+I29+I32+I35)/I13) -> 0 | J54: =IF(J13=0,0,(J18+J21+J25+J29+J32+J35)/J13) -> 0 | ... O54: =IF(O13=0,0,(O18+O21+O25+O29+O32+O35)/O13) -> 0.11773087
A55: Fulfilment cost per order (₹) | B55: ₹ | C55: =IF(C10=0,0,C22*100000/C10) -> 52.750168 | D55: =IF(D10=0,0,D22*100000/D10) -> 52.783147 | E55: =IF(E10=0,0,E22*100000/E10) -> 56.255626 | F55: =IF(F10=0,0,F22*100000/F10) -> 57.005432 | G55: =IF(G10=0,0,G22*100000/G10) -> 56.772226 | H55: =IF(H10=0,0,H22*100000/H10) -> 56.221765 | I55: =IF(I10=0,0,I22*100000/I10) -> 0 | J55: =IF(J10=0,0,J22*100000/J10) -> 0 | ... O55: =IF(O10=0,0,O22*100000/O10) -> 55.300937
A56: ROAS (revenue ÷ marketing spend) | B56: x | C56: =IF((C26+C27)=0,0,C13/(C26+C27)) -> 3.1896237 | D56: =IF((D26+D27)=0,0,D13/(D26+D27)) -> 3.1973365 | E56: =IF((E26+E27)=0,0,E13/(E26+E27)) -> 3.0983765 | F56: =IF((F26+F27)=0,0,F13/(F26+F27)) -> 3.1158383 | G56: =IF((G26+G27)=0,0,G13/(G26+G27)) -> 2.9095463 | H56: =IF((H26+H27)=0,0,H13/(H26+H27)) -> 2.7812123 | I56: =IF((I26+I27)=0,0,I13/(I26+I27)) -> 0 | J56: =IF((J26+J27)=0,0,J13/(J26+J27)) -> 0 | ... O56: =IF((O26+O27)=0,0,O13/(O26+O27)) -> 3.0360555
A57: Revenue per head per month (₹ lakh) | B57: ₹ lakh | C57: =IF(C51=0,0,C13/(C51*1)) -> 9.508481 | D57: =IF(D51=0,0,D13/(D51*1)) -> 9.3345172 | E57: =IF(E51=0,0,E13/(E51*1)) -> 9.3926251 | F57: =IF(F51=0,0,F13/(F51*1)) -> 9.0104454 | G57: =IF(G51=0,0,G13/(G51*1)) -> 9.4878847 | H57: =IF(H51=0,0,H13/(H51*1)) -> 10.004356 | I57: =IF(I51=0,0,I13/(I51*1)) -> 0 | J57: =IF(J51=0,0,J13/(J51*1)) -> 0 | ... N57: =IF(N51=0,0,N13/(N51*1)) -> 0 | O57: =IF(O51=0,0,O13/(O51*$F$3)) -> 9.4573465
A58: Avg personnel cost per head per month (₹ lakh) | B58: ₹ lakh | C58: =IF(C51=0,0,(C18+C21+C25+C29+C32+C35)/(C51*1)) -> 1.1066667 | D58: =IF(D51=0,0,(D18+D21+D25+D29+D32+D35)/(D51*1)) -> 1.1058667 | E58: =IF(E51=0,0,(E18+E21+E25+E29+E32+E35)/(E51*1)) -> 1.1165333 | F58: =IF(F51=0,0,(F18+F21+F25+F29+F32+F35)/(F51*1)) -> 1.117942 | G58: =IF(G51=0,0,(G18+G21+G25+G29+G32+G35)/(G51*1)) -> 1.1139842 | H58: =IF(H51=0,0,(H18+H21+H25+H29+H32+H35)/(H51*1)) -> 1.1193717 | I58: =IF(I51=0,0,(I18+I21+I25+I29+I32+I35)/(I51*1)) -> 0 | J58: =IF(J51=0,0,(J18+J21+J25+J29+J32+J35)/(J51*1)) -> 0 | ... N58: =IF(N51=0,0,(N18+N21+N25+N29+N32+N35)/(N51*1)) -> 0 | O58: =IF(O51=0,0,(O18+O21+O25+O29+O32+O35)/(O51*$F$3)) -> 1.1134216
A60: BLOCK 2 – BUDGET (linked from Assumptions & Budget)
A61: Orders (no.) | B61: no. | C61: ='Assumptions & Budget'!C64 -> 506521.99 | D61: ='Assumptions & Budget'!D64 -> 506521.99 | E61: ='Assumptions & Budget'!E64 -> 490526.56 | F61: ='Assumptions & Budget'!F64 -> 479862.94 | G61: ='Assumptions & Budget'!G64 -> 506521.99 | H61: ='Assumptions & Budget'!H64 -> 533181.04 | I61: ='Assumptions & Budget'!I64 -> 639817.25 | J61: ='Assumptions & Budget'!J64 -> 613158.2 | ... N61: ='Assumptions & Budget'!N64 -> 522517.42 | O61: =SUMIFS($C61:$N61,$C$5:$N$5,"<="&$C$3) -> 3023136.5
A62: Net AOV (₹ per order) | B62: ₹ | C62: ='Assumptions & Budget'!C65 -> 696.8844 | D62: ='Assumptions & Budget'!D65 -> 698.97505 | E62: ='Assumptions & Budget'!E65 -> 701.07198 | F62: ='Assumptions & Budget'!F65 -> 703.17519 | G62: ='Assumptions & Budget'!G65 -> 705.28472 | H62: ='Assumptions & Budget'!H65 -> 707.40057 | I62: ='Assumptions & Budget'!I65 -> 709.52278 | J62: ='Assumptions & Budget'!J65 -> 711.65134 | ... N62: ='Assumptions & Budget'!N65 -> 720.22967 | O62: =IF(O61=0,0,O63*100000/O61) -> 702.17486
A63: Net revenue | B63: ₹ lakh | C63: ='Assumptions & Budget'!C67 -> 3529.8727 | D63: ='Assumptions & Budget'!D67 -> 3540.4623 | E63: ='Assumptions & Budget'!E67 -> 3438.9442 | F63: ='Assumptions & Budget'!F67 -> 3374.2771 | G63: ='Assumptions & Budget'!G67 -> 3572.4222 | H63: ='Assumptions & Budget'!H67 -> 3771.7257 | I63: ='Assumptions & Budget'!I67 -> 4539.6491 | J63: ='Assumptions & Budget'!J67 -> 4363.5485 | ... N63: ='Assumptions & Budget'!N67 -> 3763.3255 | O63: =SUMIFS($C63:$N63,$C$5:$N$5,"<="&$C$3) -> 21227.704
A64: Cost of goods sold | B64: ₹ lakh | C64: ='Assumptions & Budget'!C68 -> 1094.2605 | D64: ='Assumptions & Budget'!D68 -> 1097.5433 | E64: ='Assumptions & Budget'!E68 -> 1066.0727 | F64: ='Assumptions & Budget'!F68 -> 1046.0259 | G64: ='Assumptions & Budget'!G68 -> 1107.4509 | H64: ='Assumptions & Budget'!H68 -> 1169.235 | I64: ='Assumptions & Budget'!I68 -> 1407.2912 | J64: ='Assumptions & Budget'!J68 -> 1352.7 | ... N64: ='Assumptions & Budget'!N68 -> 1166.6309 | O64: =SUMIFS($C64:$N64,$C$5:$N$5,"<="&$C$3) -> 6580.5883
A65: Gross profit | B65: ₹ lakh | C65: ='Assumptions & Budget'!C69 -> 2435.6122 | D65: ='Assumptions & Budget'!D69 -> 2442.919 | E65: ='Assumptions & Budget'!E69 -> 2372.8715 | F65: ='Assumptions & Budget'!F69 -> 2328.2512 | G65: ='Assumptions & Budget'!G69 -> 2464.9713 | H65: ='Assumptions & Budget'!H69 -> 2602.4908 | I65: ='Assumptions & Budget'!I69 -> 3132.3579 | J65: ='Assumptions & Budget'!J69 -> 3010.8485 | ... N65: ='Assumptions & Budget'!N69 -> 2596.6946 | O65: =SUMIFS($C65:$N65,$C$5:$N$5,"<="&$C$3) -> 14647.116
A66: Sales – personnel | B66: ₹ lakh | C66: ='Assumptions & Budget'!C72 -> 71.207598 | D66: ='Assumptions & Budget'!D72 -> 71.207598 | E66: ='Assumptions & Budget'!E72 -> 71.207598 | F66: ='Assumptions & Budget'!F72 -> 71.207598 | G66: ='Assumptions & Budget'!G72 -> 71.207598 | H66: ='Assumptions & Budget'!H72 -> 73.581184 | I66: ='Assumptions & Budget'!I72 -> 73.581184 | J66: ='Assumptions & Budget'!J72 -> 73.581184 | ... N66: ='Assumptions & Budget'!N72 -> 74.767978 | O66: =SUMIFS($C66:$N66,$C$5:$N$5,"<="&$C$3) -> 429.61917
A67: Sales – marketplace & payment fees | B67: ₹ lakh | C67: ='Assumptions & Budget'!C73 -> 105.89618 | D67: ='Assumptions & Budget'!D73 -> 106.21387 | E67: ='Assumptions & Budget'!E73 -> 103.16833 | F67: ='Assumptions & Budget'!F73 -> 101.22831 | G67: ='Assumptions & Budget'!G73 -> 107.17267 | H67: ='Assumptions & Budget'!H73 -> 113.15177 | I67: ='Assumptions & Budget'!I73 -> 136.18947 | J67: ='Assumptions & Budget'!J73 -> 130.90646 | ... N67: ='Assumptions & Budget'!N73 -> 112.89976 | O67: =SUMIFS($C67:$N67,$C$5:$N$5,"<="&$C$3) -> 636.83113
A68: Sales – total | B68: ₹ lakh | C68: ='Assumptions & Budget'!C74 -> 177.10378 | D68: ='Assumptions & Budget'!D74 -> 177.42147 | E68: ='Assumptions & Budget'!E74 -> 174.37592 | F68: ='Assumptions & Budget'!F74 -> 172.43591 | G68: ='Assumptions & Budget'!G74 -> 178.38026 | H68: ='Assumptions & Budget'!H74 -> 186.73296 | I68: ='Assumptions & Budget'!I74 -> 209.77066 | J68: ='Assumptions & Budget'!J74 -> 204.48764 | ... N68: ='Assumptions & Budget'!N74 -> 187.66774 | O68: =SUMIFS($C68:$N68,$C$5:$N$5,"<="&$C$3) -> 1066.4503
A69: Operations – personnel | B69: ₹ lakh | C69: ='Assumptions & Budget'!C75 -> 100.93289 | D69: ='Assumptions & Budget'!D75 -> 100.93289 | E69: ='Assumptions & Budget'!E75 -> 100.93289 | F69: ='Assumptions & Budget'!F75 -> 100.93289 | G69: ='Assumptions & Budget'!G75 -> 100.93289 | H69: ='Assumptions & Budget'!H75 -> 100.93289 | I69: ='Assumptions & Budget'!I75 -> 100.93289 | J69: ='Assumptions & Budget'!J75 -> 100.93289 | ... N69: ='Assumptions & Budget'!N75 -> 103.62443 | O69: =SUMIFS($C69:$N69,$C$5:$N$5,"<="&$C$3) -> 605.59732
A70: Operations – fulfilment & logistics | B70: ₹ lakh | C70: ='Assumptions & Budget'!C76 -> 264.39577 | D70: ='Assumptions & Budget'!D76 -> 264.39577 | E70: ='Assumptions & Budget'!E76 -> 256.04643 | F70: ='Assumptions & Budget'!F76 -> 250.4802 | G70: ='Assumptions & Budget'!G76 -> 264.39577 | H70: ='Assumptions & Budget'!H76 -> 278.31133 | I70: ='Assumptions & Budget'!I76 -> 333.9736 | J70: ='Assumptions & Budget'!J76 -> 320.05804 | ... N70: ='Assumptions & Budget'!N76 -> 272.74511 | O70: =SUMIFS($C70:$N70,$C$5:$N$5,"<="&$C$3) -> 1578.0253
A71: Operations – warehouse, QC & other | B71: ₹ lakh | C71: ='Assumptions & Budget'!C77 -> 34.3175 | D71: ='Assumptions & Budget'!D77 -> 34.3175 | E71: ='Assumptions & Budget'!E77 -> 34.3175 | F71: ='Assumptions & Budget'!F77 -> 34.3175 | G71: ='Assumptions & Budget'!G77 -> 34.3175 | H71: ='Assumptions & Budget'!H77 -> 34.3175 | I71: ='Assumptions & Budget'!I77 -> 34.3175 | J71: ='Assumptions & Budget'!J77 -> 34.3175 | ... N71: ='Assumptions & Budget'!N77 -> 34.3175 | O71: =SUMIFS($C71:$N71,$C$5:$N$5,"<="&$C$3) -> 205.905
A72: Operations – total | B72: ₹ lakh | C72: ='Assumptions & Budget'!C78 -> 399.64615 | D72: ='Assumptions & Budget'!D78 -> 399.64615 | E72: ='Assumptions & Budget'!E78 -> 391.29681 | F72: ='Assumptions & Budget'!F78 -> 385.73059 | G72: ='Assumptions & Budget'!G78 -> 399.64615 | H72: ='Assumptions & Budget'!H78 -> 413.56172 | I72: ='Assumptions & Budget'!I78 -> 469.22399 | J72: ='Assumptions & Budget'!J78 -> 455.30842 | ... N72: ='Assumptions & Budget'!N78 -> 410.68704 | O72: =SUMIFS($C72:$N72,$C$5:$N$5,"<="&$C$3) -> 2389.5276
A73: Marketing – personnel | B73: ₹ lakh | C73: ='Assumptions & Budget'!C79 -> 91.042887 | D73: ='Assumptions & Budget'!D79 -> 91.042887 | E73: ='Assumptions & Budget'!E79 -> 91.042887 | F73: ='Assumptions & Budget'!F79 -> 93.844206 | G73: ='Assumptions & Budget'!G79 -> 93.844206 | H73: ='Assumptions & Budget'!H79 -> 93.844206 | I73: ='Assumptions & Budget'!I79 -> 93.844206 | J73: ='Assumptions & Budget'!J79 -> 93.844206 | ... N73: ='Assumptions & Budget'!N79 -> 93.844206 | O73: =SUMIFS($C73:$N73,$C$5:$N$5,"<="&$C$3) -> 554.66128
A74: Marketing – performance marketing | B74: ₹ lakh | C74: ='Assumptions & Budget'!C80 -> 758.92263 | D74: ='Assumptions & Budget'!D80 -> 761.1994 | E74: ='Assumptions & Budget'!E80 -> 739.37301 | F74: ='Assumptions & Budget'!F80 -> 725.46958 | G74: ='Assumptions & Budget'!G80 -> 768.07077 | H74: ='Assumptions & Budget'!H80 -> 810.92103 | I74: ='Assumptions & Budget'!I80 -> 976.02455 | J74: ='Assumptions & Budget'!J80 -> 938.16294 | ... N74: ='Assumptions & Budget'!N80 -> 809.11497 | O74: =SUMIFS($C74:$N74,$C$5:$N$5,"<="&$C$3) -> 4563.9564
A75: Marketing – brand & influencer | B75: ₹ lakh | C75: ='Assumptions & Budget'!C81 -> 352.98727 | D75: ='Assumptions & Budget'!D81 -> 354.04623 | E75: ='Assumptions & Budget'!E81 -> 343.89442 | F75: ='Assumptions & Budget'!F81 -> 337.42771 | G75: ='Assumptions & Budget'!G81 -> 357.24222 | H75: ='Assumptions & Budget'!H81 -> 377.17257 | I75: ='Assumptions & Budget'!I81 -> 453.96491 | J75: ='Assumptions & Budget'!J81 -> 436.35485 | ... N75: ='Assumptions & Budget'!N81 -> 376.33255 | O75: =SUMIFS($C75:$N75,$C$5:$N$5,"<="&$C$3) -> 2122.7704
A76: Marketing – total | B76: ₹ lakh | C76: ='Assumptions & Budget'!C82 -> 1202.9528 | D76: ='Assumptions & Budget'!D82 -> 1206.2885 | E76: ='Assumptions & Budget'!E82 -> 1174.3103 | F76: ='Assumptions & Budget'!F82 -> 1156.7415 | G76: ='Assumptions & Budget'!G82 -> 1219.1572 | H76: ='Assumptions & Budget'!H82 -> 1281.9378 | I76: ='Assumptions & Budget'!I82 -> 1523.8337 | J76: ='Assumptions & Budget'!J82 -> 1468.362 | ... N76: ='Assumptions & Budget'!N82 -> 1279.2917 | O76: =SUMIFS($C76:$N76,$C$5:$N$5,"<="&$C$3) -> 7241.3881
A77: HR – personnel | B77: ₹ lakh | C77: ='Assumptions & Budget'!C83 -> 15.012 | D77: ='Assumptions & Budget'!D83 -> 15.012 | E77: ='Assumptions & Budget'!E83 -> 15.012 | F77: ='Assumptions & Budget'!F83 -> 15.012 | G77: ='Assumptions & Budget'!G83 -> 15.012 | H77: ='Assumptions & Budget'!H83 -> 15.012 | I77: ='Assumptions & Budget'!I83 -> 15.012 | J77: ='Assumptions & Budget'!J83 -> 15.012 | ... N77: ='Assumptions & Budget'!N83 -> 15.012 | O77: =SUMIFS($C77:$N77,$C$5:$N$5,"<="&$C$3) -> 90.072
... A85: Finance – total | B85: ₹ lakh | C85: ='Assumptions & Budget'!C91 -> 101.38383 | D85: ='Assumptions & Budget'!D91 -> 101.38383 | E85: ='Assumptions & Budget'!E91 -> 101.38383 | F85: ='Assumptions & Budget'!F91 -> 101.38383 | G85: ='Assumptions & Budget'!G91 -> 101.38383 | H85: ='Assumptions & Budget'!H91 -> 101.38383 | I85: ='Assumptions & Budget'!I91 -> 102.69423 | J85: ='Assumptions & Budget'!J91 -> 102.69423 | ... N85: ='Assumptions & Budget'!N91 -> 102.69423 | O85: =SUMIFS($C85:$N85,$C$5:$N$5,"<="&$C$3) -> 608.303
A86: Total operating cost | B86: ₹ lakh | C86: ='Assumptions & Budget'!C93 -> 2052.9992 | D86: ='Assumptions & Budget'!D93 -> 2056.6526 | E86: ='Assumptions & Budget'!E93 -> 2013.2795 | F86: ='Assumptions & Budget'!F93 -> 1991.8416 | G86: ='Assumptions & Budget'!G93 -> 2074.1172 | H86: ='Assumptions & Budget'!H93 -> 2159.1661 | I86: ='Assumptions & Budget'!I93 -> 2481.0723 | J86: ='Assumptions & Budget'!J93 -> 2406.4021 | ... N86: ='Assumptions & Budget'!N93 -> 2155.8905 | O86: =SUMIFS($C86:$N86,$C$5:$N$5,"<="&$C$3) -> 12348.056
A87: EBITDA | B87: ₹ lakh | C87: ='Assumptions & Budget'!C94 -> 382.613 | D87: ='Assumptions & Budget'!D94 -> 386.26642 | E87: ='Assumptions & Budget'!E94 -> 359.59202 | F87: ='Assumptions & Budget'!F94 -> 336.40961 | G87: ='Assumptions & Budget'!G94 -> 390.85409 | H87: ='Assumptions & Budget'!H94 -> 443.32466 | I87: ='Assumptions & Budget'!I94 -> 651.28555 | J87: ='Assumptions & Budget'!J94 -> 604.44643 | ... N87: ='Assumptions & Budget'!N94 -> 440.80406 | O87: =SUMIFS($C87:$N87,$C$5:$N$5,"<="&$C$3) -> 2299.0598
A89: BLOCK 3 – FLEXED BUDGET (variable lines scaled to actual volume; others = budget)
A90: Revenue volume factor (actual ÷ budget revenue) | C90: =IF(C13=0,1,C13/C63) -> 1.0101442 | D90: =IF(D13=0,1,D13/D63) -> 0.98869685 | E90: =IF(E13=0,1,E13/E63) -> 1.0242197 | F90: =IF(F13=0,1,F13/F63) -> 1.0120564 | G90: =IF(G13=0,1,G13/G63) -> 1.0065743 | H90: =IF(H13=0,1,H13/H63) -> 1.0132401 | I90: =IF(I13=0,1,I13/I63) -> 1 | J90: =IF(J13=0,1,J13/J63) -> 1 | ... N90: =IF(N13=0,1,N13/N63) -> 1
A91: Order volume factor (actual ÷ budget orders) | C91: =IF(C10=0,1,C10/C61) -> 1.0120094 | D91: =IF(D10=0,1,D10/D61) -> 0.9967899 | E91: =IF(E10=0,1,E10/E61) -> 1.0237407 | F91: =IF(F10=0,1,F10/F61) -> 1.0224899 | G91: =IF(G10=0,1,G10/G61) -> 1.0202953 | H91: =IF(H10=0,1,H10/H61) -> 1.0238061 | I91: =IF(I10=0,1,I10/I61) -> 1 | J91: =IF(J10=0,1,J10/J61) -> 1 | ... N91: =IF(N10=0,1,N10/N61) -> 1
A92: Net revenue | B92: ₹ lakh | C92: =C63 -> 3529.8727 | D92: =D63 -> 3540.4623 | E92: =E63 -> 3438.9442 | F92: =F63 -> 3374.2771 | G92: =G63 -> 3572.4222 | H92: =H63 -> 3771.7257 | I92: =I63 -> 4539.6491 | J92: =J63 -> 4363.5485 | ... N92: =N63 -> 3763.3255 | O92: =SUMIFS($C92:$N92,$C$5:$N$5,"<="&$C$3) -> 21227.704
A93: Cost of goods sold | B93: ₹ lakh | C93: =C64*IF('Assumptions & Budget'!$E$44="Revenue",C$90,IF('Assumptions & Budget'!$E$44="Orders",C$91,1)) -> 1105.3609 | D93: =D64*IF('Assumptions & Budget'!$E$44="Revenue",D$90,IF('Assumptions & Budget'!$E$44="Orders",D$91,1)) -> 1085.1376 | E93: =E64*IF('Assumptions & Budget'!$E$44="Revenue",E$90,IF('Assumptions & Budget'!$E$44="Orders",E$91,1)) -> 1091.8927 | F93: =F64*IF('Assumptions & Budget'!$E$44="Revenue",F$90,IF('Assumptions & Budget'!$E$44="Orders",F$91,1)) -> 1058.6372 | G93: =G64*IF('Assumptions & Budget'!$E$44="Revenue",G$90,IF('Assumptions & Budget'!$E$44="Orders",G$91,1)) -> 1114.7316 | H93: =H64*IF('Assumptions & Budget'!$E$44="Revenue",H$90,IF('Assumptions & Budget'!$E$44="Orders",H$91,1)) -> 1184.7158 | I93: =I64*IF('Assumptions & Budget'!$E$44="Revenue",I$90,IF('Assumptions & Budget'!$E$44="Orders",I$91,1)) -> 1407.2912 | J93: =J64*IF('Assumptions & Budget'!$E$44="Revenue",J$90,IF('Assumptions & Budget'!$E$44="Orders",J$91,1)) -> 1352.7 | ... N93: =N64*IF('Assumptions & Budget'!$E$44="Revenue",N$90,IF('Assumptions & Budget'!$E$44="Orders",N$91,1)) -> 1166.6309 | O93: =SUMIFS($C93:$N93,$C$5:$N$5,"<="&$C$3) -> 6640.4758
A94: Gross profit | B94: ₹ lakh | C94: =C92-C93 -> 2424.5118 | D94: =D92-D93 -> 2455.3247 | E94: =E92-E93 -> 2347.0516 | F94: =F92-F93 -> 2315.6399 | G94: =G92-G93 -> 2457.6906 | H94: =H92-H93 -> 2587.0099 | I94: =I92-I93 -> 3132.3579 | J94: =J92-J93 -> 3010.8485 | ... N94: =N92-N93 -> 2596.6946 | O94: =SUMIFS($C94:$N94,$C$5:$N$5,"<="&$C$3) -> 14587.228
A95: Sales – personnel | B95: ₹ lakh | C95: =C66*IF('Assumptions & Budget'!$E$45="Revenue",C$90,IF('Assumptions & Budget'!$E$45="Orders",C$91,1)) -> 71.207598 | D95: =D66*IF('Assumptions & Budget'!$E$45="Revenue",D$90,IF('Assumptions & Budget'!$E$45="Orders",D$91,1)) -> 71.207598 | E95: =E66*IF('Assumptions & Budget'!$E$45="Revenue",E$90,IF('Assumptions & Budget'!$E$45="Orders",E$91,1)) -> 71.207598 | F95: =F66*IF('Assumptions & Budget'!$E$45="Revenue",F$90,IF('Assumptions & Budget'!$E$45="Orders",F$91,1)) -> 71.207598 | G95: =G66*IF('Assumptions & Budget'!$E$45="Revenue",G$90,IF('Assumptions & Budget'!$E$45="Orders",G$91,1)) -> 71.207598 | H95: =H66*IF('Assumptions & Budget'!$E$45="Revenue",H$90,IF('Assumptions & Budget'!$E$45="Orders",H$91,1)) -> 73.581184 | I95: =I66*IF('Assumptions & Budget'!$E$45="Revenue",I$90,IF('Assumptions & Budget'!$E$45="Orders",I$91,1)) -> 73.581184 | J95: =J66*IF('Assumptions & Budget'!$E$45="Revenue",J$90,IF('Assumptions & Budget'!$E$45="Orders",J$91,1)) -> 73.581184 | ... N95: =N66*IF('Assumptions & Budget'!$E$45="Revenue",N$90,IF('Assumptions & Budget'!$E$45="Orders",N$91,1)) -> 74.767978 | O95: =SUMIFS($C95:$N95,$C$5:$N$5,"<="&$C$3) -> 429.61917
A96: Sales – marketplace & payment fees | B96: ₹ lakh | C96: =C67*IF('Assumptions & Budget'!$E$46="Revenue",C$90,IF('Assumptions & Budget'!$E$46="Orders",C$91,1)) -> 106.97041 | D96: =D67*IF('Assumptions & Budget'!$E$46="Revenue",D$90,IF('Assumptions & Budget'!$E$46="Orders",D$91,1)) -> 105.01332 | E96: =E67*IF('Assumptions & Budget'!$E$46="Revenue",E$90,IF('Assumptions & Budget'!$E$46="Orders",E$91,1)) -> 105.66703 | F96: =F67*IF('Assumptions & Budget'!$E$46="Revenue",F$90,IF('Assumptions & Budget'!$E$46="Orders",F$91,1)) -> 102.44876 | G96: =G67*IF('Assumptions & Budget'!$E$46="Revenue",G$90,IF('Assumptions & Budget'!$E$46="Orders",G$91,1)) -> 107.87725 | H96: =H67*IF('Assumptions & Budget'!$E$46="Revenue",H$90,IF('Assumptions & Budget'!$E$46="Orders",H$91,1)) -> 114.64992 | I96: =I67*IF('Assumptions & Budget'!$E$46="Revenue",I$90,IF('Assumptions & Budget'!$E$46="Orders",I$91,1)) -> 136.18947 | J96: =J67*IF('Assumptions & Budget'!$E$46="Revenue",J$90,IF('Assumptions & Budget'!$E$46="Orders",J$91,1)) -> 130.90646 | ... N96: =N67*IF('Assumptions & Budget'!$E$46="Revenue",N$90,IF('Assumptions & Budget'!$E$46="Orders",N$91,1)) -> 112.89976 | O96: =SUMIFS($C96:$N96,$C$5:$N$5,"<="&$C$3) -> 642.62669
A97: Sales – total | B97: ₹ lakh | C97: =C95+C96 -> 178.17801 | D97: =D95+D96 -> 176.22092 | E97: =E95+E96 -> 176.87463 | F97: =F95+F96 -> 173.65636 | G97: =G95+G96 -> 179.08485 | H97: =H95+H96 -> 188.2311 | I97: =I95+I96 -> 209.77066 | J97: =J95+J96 -> 204.48764 | ... N97: =N95+N96 -> 187.66774 | O97: =SUMIFS($C97:$N97,$C$5:$N$5,"<="&$C$3) -> 1072.2459
A98: Operations – personnel | B98: ₹ lakh | C98: =C69*IF('Assumptions & Budget'!$E$47="Revenue",C$90,IF('Assumptions & Budget'!$E$47="Orders",C$91,1)) -> 100.93289 | D98: =D69*IF('Assumptions & Budget'!$E$47="Revenue",D$90,IF('Assumptions & Budget'!$E$47="Orders",D$91,1)) -> 100.93289 | E98: =E69*IF('Assumptions & Budget'!$E$47="Revenue",E$90,IF('Assumptions & Budget'!$E$47="Orders",E$91,1)) -> 100.93289 | F98: =F69*IF('Assumptions & Budget'!$E$47="Revenue",F$90,IF('Assumptions & Budget'!$E$47="Orders",F$91,1)) -> 100.93289 | G98: =G69*IF('Assumptions & Budget'!$E$47="Revenue",G$90,IF('Assumptions & Budget'!$E$47="Orders",G$91,1)) -> 100.93289 | H98: =H69*IF('Assumptions & Budget'!$E$47="Revenue",H$90,IF('Assumptions & Budget'!$E$47="Orders",H$91,1)) -> 100.93289 | I98: =I69*IF('Assumptions & Budget'!$E$47="Revenue",I$90,IF('Assumptions & Budget'!$E$47="Orders",I$91,1)) -> 100.93289 | J98: =J69*IF('Assumptions & Budget'!$E$47="Revenue",J$90,IF('Assumptions & Budget'!$E$47="Orders",J$91,1)) -> 100.93289 | ... N98: =N69*IF('Assumptions & Budget'!$E$47="Revenue",N$90,IF('Assumptions & Budget'!$E$47="Orders",N$91,1)) -> 103.62443 | O98: =SUMIFS($C98:$N98,$C$5:$N$5,"<="&$C$3) -> 605.59732
A99: Operations – fulfilment & logistics | B99: ₹ lakh | C99: =C70*IF('Assumptions & Budget'!$E$48="Revenue",C$90,IF('Assumptions & Budget'!$E$48="Orders",C$91,1)) -> 267.571 | D99: =D70*IF('Assumptions & Budget'!$E$48="Revenue",D$90,IF('Assumptions & Budget'!$E$48="Orders",D$91,1)) -> 263.54703 | E99: =E70*IF('Assumptions & Budget'!$E$48="Revenue",E$90,IF('Assumptions & Budget'!$E$48="Orders",E$91,1)) -> 262.12515 | F99: =F70*IF('Assumptions & Budget'!$E$48="Revenue",F$90,IF('Assumptions & Budget'!$E$48="Orders",F$91,1)) -> 256.11347 | G99: =G70*IF('Assumptions & Budget'!$E$48="Revenue",G$90,IF('Assumptions & Budget'!$E$48="Orders",G$91,1)) -> 269.76176 | H99: =H70*IF('Assumptions & Budget'!$E$48="Revenue",H$90,IF('Assumptions & Budget'!$E$48="Orders",H$91,1)) -> 284.93684 | I99: =I70*IF('Assumptions & Budget'!$E$48="Revenue",I$90,IF('Assumptions & Budget'!$E$48="Orders",I$91,1)) -> 333.9736 | J99: =J70*IF('Assumptions & Budget'!$E$48="Revenue",J$90,IF('Assumptions & Budget'!$E$48="Orders",J$91,1)) -> 320.05804 | ... N99: =N70*IF('Assumptions & Budget'!$E$48="Revenue",N$90,IF('Assumptions & Budget'!$E$48="Orders",N$91,1)) -> 272.74511 | O99: =SUMIFS($C99:$N99,$C$5:$N$5,"<="&$C$3) -> 1604.0553
A100: Operations – warehouse, QC & other | B100: ₹ lakh | C100: =C71*IF('Assumptions & Budget'!$E$49="Revenue",C$90,IF('Assumptions & Budget'!$E$49="Orders",C$91,1)) -> 34.3175 | D100: =D71*IF('Assumptions & Budget'!$E$49="Revenue",D$90,IF('Assumptions & Budget'!$E$49="Orders",D$91,1)) -> 34.3175 | E100: =E71*IF('Assumptions & Budget'!$E$49="Revenue",E$90,IF('Assumptions & Budget'!$E$49="Orders",E$91,1)) -> 34.3175 | F100: =F71*IF('Assumptions & Budget'!$E$49="Revenue",F$90,IF('Assumptions & Budget'!$E$49="Orders",F$91,1)) -> 34.3175 | G100: =G71*IF('Assumptions & Budget'!$E$49="Revenue",G$90,IF('Assumptions & Budget'!$E$49="Orders",G$91,1)) -> 34.3175 | H100: =H71*IF('Assumptions & Budget'!$E$49="Revenue",H$90,IF('Assumptions & Budget'!$E$49="Orders",H$91,1)) -> 34.3175 | I100: =I71*IF('Assumptions & Budget'!$E$49="Revenue",I$90,IF('Assumptions & Budget'!$E$49="Orders",I$91,1)) -> 34.3175 | J100: =J71*IF('Assumptions & Budget'!$E$49="Revenue",J$90,IF('Assumptions & Budget'!$E$49="Orders",J$91,1)) -> 34.3175 | ... N100: =N71*IF('Assumptions & Budget'!$E$49="Revenue",N$90,IF('Assumptions & Budget'!$E$49="Orders",N$91,1)) -> 34.3175 | O100: =SUMIFS($C100:$N100,$C$5:$N$5,"<="&$C$3) -> 205.905
A101: Operations – total | B101: ₹ lakh | C101: =C98+C99+C100 -> 402.82138 | D101: =D98+D99+D100 -> 398.79742 | E101: =E98+E99+E100 -> 397.37554 | F101: =F98+F99+F100 -> 391.36386 | G101: =G98+G99+G100 -> 405.01214 | H101: =H98+H99+H100 -> 420.18723 | I101: =I98+I99+I100 -> 469.22399 | J101: =J98+J99+J100 -> 455.30842 | ... N101: =N98+N99+N100 -> 410.68704 | O101: =SUMIFS($C101:$N101,$C$5:$N$5,"<="&$C$3) -> 2415.5576
A102: Marketing – personnel | B102: ₹ lakh | C102: =C73*IF('Assumptions & Budget'!$E$50="Revenue",C$90,IF('Assumptions & Budget'!$E$50="Orders",C$91,1)) -> 91.042887 | D102: =D73*IF('Assumptions & Budget'!$E$50="Revenue",D$90,IF('Assumptions & Budget'!$E$50="Orders",D$91,1)) -> 91.042887 | E102: =E73*IF('Assumptions & Budget'!$E$50="Revenue",E$90,IF('Assumptions & Budget'!$E$50="Orders",E$91,1)) -> 91.042887 | F102: =F73*IF('Assumptions & Budget'!$E$50="Revenue",F$90,IF('Assumptions & Budget'!$E$50="Orders",F$91,1)) -> 93.844206 | G102: =G73*IF('Assumptions & Budget'!$E$50="Revenue",G$90,IF('Assumptions & Budget'!$E$50="Orders",G$91,1)) -> 93.844206 | H102: =H73*IF('Assumptions & Budget'!$E$50="Revenue",H$90,IF('Assumptions & Budget'!$E$50="Orders",H$91,1)) -> 93.844206 | I102: =I73*IF('Assumptions & Budget'!$E$50="Revenue",I$90,IF('Assumptions & Budget'!$E$50="Orders",I$91,1)) -> 93.844206 | J102: =J73*IF('Assumptions & Budget'!$E$50="Revenue",J$90,IF('Assumptions & Budget'!$E$50="Orders",J$91,1)) -> 93.844206 | ... N102: =N73*IF('Assumptions & Budget'!$E$50="Revenue",N$90,IF('Assumptions & Budget'!$E$50="Orders",N$91,1)) -> 93.844206 | O102: =SUMIFS($C102:$N102,$C$5:$N$5,"<="&$C$3) -> 554.66128
A103: Marketing – performance marketing | B103: ₹ lakh | C103: =C74*IF('Assumptions & Budget'!$E$51="Revenue",C$90,IF('Assumptions & Budget'!$E$51="Orders",C$91,1)) -> 758.92263 | D103: =D74*IF('Assumptions & Budget'!$E$51="Revenue",D$90,IF('Assumptions & Budget'!$E$51="Orders",D$91,1)) -> 761.1994 | E103: =E74*IF('Assumptions & Budget'!$E$51="Revenue",E$90,IF('Assumptions & Budget'!$E$51="Orders",E$91,1)) -> 739.37301 | F103: =F74*IF('Assumptions & Budget'!$E$51="Revenue",F$90,IF('Assumptions & Budget'!$E$51="Orders",F$91,1)) -> 725.46958 | G103: =G74*IF('Assumptions & Budget'!$E$51="Revenue",G$90,IF('Assumptions & Budget'!$E$51="Orders",G$91,1)) -> 768.07077 | H103: =H74*IF('Assumptions & Budget'!$E$51="Revenue",H$90,IF('Assumptions & Budget'!$E$51="Orders",H$91,1)) -> 810.92103 | I103: =I74*IF('Assumptions & Budget'!$E$51="Revenue",I$90,IF('Assumptions & Budget'!$E$51="Orders",I$91,1)) -> 976.02455 | J103: =J74*IF('Assumptions & Budget'!$E$51="Revenue",J$90,IF('Assumptions & Budget'!$E$51="Orders",J$91,1)) -> 938.16294 | ... N103: =N74*IF('Assumptions & Budget'!$E$51="Revenue",N$90,IF('Assumptions & Budget'!$E$51="Orders",N$91,1)) -> 809.11497 | O103: =SUMIFS($C103:$N103,$C$5:$N$5,"<="&$C$3) -> 4563.9564
A104: Marketing – brand & influencer | B104: ₹ lakh | C104: =C75*IF('Assumptions & Budget'!$E$52="Revenue",C$90,IF('Assumptions & Budget'!$E$52="Orders",C$91,1)) -> 352.98727 | D104: =D75*IF('Assumptions & Budget'!$E$52="Revenue",D$90,IF('Assumptions & Budget'!$E$52="Orders",D$91,1)) -> 354.04623 | E104: =E75*IF('Assumptions & Budget'!$E$52="Revenue",E$90,IF('Assumptions & Budget'!$E$52="Orders",E$91,1)) -> 343.89442 | F104: =F75*IF('Assumptions & Budget'!$E$52="Revenue",F$90,IF('Assumptions & Budget'!$E$52="Orders",F$91,1)) -> 337.42771 | G104: =G75*IF('Assumptions & Budget'!$E$52="Revenue",G$90,IF('Assumptions & Budget'!$E$52="Orders",G$91,1)) -> 357.24222 | H104: =H75*IF('Assumptions & Budget'!$E$52="Revenue",H$90,IF('Assumptions & Budget'!$E$52="Orders",H$91,1)) -> 377.17257 | I104: =I75*IF('Assumptions & Budget'!$E$52="Revenue",I$90,IF('Assumptions & Budget'!$E$52="Orders",I$91,1)) -> 453.96491 | J104: =J75*IF('Assumptions & Budget'!$E$52="Revenue",J$90,IF('Assumptions & Budget'!$E$52="Orders",J$91,1)) -> 436.35485 | ... N104: =N75*IF('Assumptions & Budget'!$E$52="Revenue",N$90,IF('Assumptions & Budget'!$E$52="Orders",N$91,1)) -> 376.33255 | O104: =SUMIFS($C104:$N104,$C$5:$N$5,"<="&$C$3) -> 2122.7704
A105: Marketing – total | B105: ₹ lakh | C105: =C102+C103+C104 -> 1202.9528 | D105: =D102+D103+D104 -> 1206.2885 | E105: =E102+E103+E104 -> 1174.3103 | F105: =F102+F103+F104 -> 1156.7415 | G105: =G102+G103+G104 -> 1219.1572 | H105: =H102+H103+H104 -> 1281.9378 | I105: =I102+I103+I104 -> 1523.8337 | J105: =J102+J103+J104 -> 1468.362 | ... N105: =N102+N103+N104 -> 1279.2917 | O105: =SUMIFS($C105:$N105,$C$5:$N$5,"<="&$C$3) -> 7241.3881
A106: HR – personnel | B106: ₹ lakh | C106: =C77*IF('Assumptions & Budget'!$E$53="Revenue",C$90,IF('Assumptions & Budget'!$E$53="Orders",C$91,1)) -> 15.012 | D106: =D77*IF('Assumptions & Budget'!$E$53="Revenue",D$90,IF('Assumptions & Budget'!$E$53="Orders",D$91,1)) -> 15.012 | E106: =E77*IF('Assumptions & Budget'!$E$53="Revenue",E$90,IF('Assumptions & Budget'!$E$53="Orders",E$91,1)) -> 15.012 | F106: =F77*IF('Assumptions & Budget'!$E$53="Revenue",F$90,IF('Assumptions & Budget'!$E$53="Orders",F$91,1)) -> 15.012 | G106: =G77*IF('Assumptions & Budget'!$E$53="Revenue",G$90,IF('Assumptions & Budget'!$E$53="Orders",G$91,1)) -> 15.012 | H106: =H77*IF('Assumptions & Budget'!$E$53="Revenue",H$90,IF('Assumptions & Budget'!$E$53="Orders",H$91,1)) -> 15.012 | I106: =I77*IF('Assumptions & Budget'!$E$53="Revenue",I$90,IF('Assumptions & Budget'!$E$53="Orders",I$91,1)) -> 15.012 | J106: =J77*IF('Assumptions & Budget'!$E$53="Revenue",J$90,IF('Assumptions & Budget'!$E$53="Orders",J$91,1)) -> 15.012 | ... N106: =N77*IF('Assumptions & Budget'!$E$53="Revenue",N$90,IF('Assumptions & Budget'!$E$53="Orders",N$91,1)) -> 15.012 | O106: =SUMIFS($C106:$N106,$C$5:$N$5,"<="&$C$3) -> 90.072
A107: HR – recruitment, training & other | B107: ₹ lakh | C107: =C78*IF('Assumptions & Budget'!$E$54="Revenue",C$90,IF('Assumptions & Budget'!$E$54="Orders",C$91,1)) -> 10.12375 | D107: =D78*IF('Assumptions & Budget'!$E$54="Revenue",D$90,IF('Assumptions & Budget'!$E$54="Orders",D$91,1)) -> 10.12375 | E107: =E78*IF('Assumptions & Budget'!$E$54="Revenue",E$90,IF('Assumptions & Budget'!$E$54="Orders",E$91,1)) -> 10.12375 | F107: =F78*IF('Assumptions & Budget'!$E$54="Revenue",F$90,IF('Assumptions & Budget'!$E$54="Orders",F$91,1)) -> 10.12375 | G107: =G78*IF('Assumptions & Budget'!$E$54="Revenue",G$90,IF('Assumptions & Budget'!$E$54="Orders",G$91,1)) -> 10.12375 | H107: =H78*IF('Assumptions & Budget'!$E$54="Revenue",H$90,IF('Assumptions & Budget'!$E$54="Orders",H$91,1)) -> 10.12375 | I107: =I78*IF('Assumptions & Budget'!$E$54="Revenue",I$90,IF('Assumptions & Budget'!$E$54="Orders",I$91,1)) -> 10.12375 | J107: =J78*IF('Assumptions & Budget'!$E$54="Revenue",J$90,IF('Assumptions & Budget'!$E$54="Orders",J$91,1)) -> 10.12375 | ... N107: =N78*IF('Assumptions & Budget'!$E$54="Revenue",N$90,IF('Assumptions & Budget'!$E$54="Orders",N$91,1)) -> 10.12375 | O107: =SUMIFS($C107:$N107,$C$5:$N$5,"<="&$C$3) -> 60.7425
A108: HR – total | B108: ₹ lakh | C108: =C106+C107 -> 25.13575 | D108: =D106+D107 -> 25.13575 | E108: =E106+E107 -> 25.13575 | F108: =F106+F107 -> 25.13575 | G108: =G106+G107 -> 25.13575 | H108: =H106+H107 -> 25.13575 | I108: =I106+I107 -> 25.13575 | J108: =J106+J107 -> 25.13575 | ... N108: =N106+N107 -> 25.13575 | O108: =SUMIFS($C108:$N108,$C$5:$N$5,"<="&$C$3) -> 150.8145
A109: IT – personnel | B109: ₹ lakh | C109: =C80*IF('Assumptions & Budget'!$E$55="Revenue",C$90,IF('Assumptions & Budget'!$E$55="Orders",C$91,1)) -> 94.566194 | D109: =D80*IF('Assumptions & Budget'!$E$55="Revenue",D$90,IF('Assumptions & Budget'!$E$55="Orders",D$91,1)) -> 94.566194 | E109: =E80*IF('Assumptions & Budget'!$E$55="Revenue",E$90,IF('Assumptions & Budget'!$E$55="Orders",E$91,1)) -> 94.566194 | F109: =F80*IF('Assumptions & Budget'!$E$55="Revenue",F$90,IF('Assumptions & Budget'!$E$55="Orders",F$91,1)) -> 98.203355 | G109: =G80*IF('Assumptions & Budget'!$E$55="Revenue",G$90,IF('Assumptions & Budget'!$E$55="Orders",G$91,1)) -> 98.203355 | H109: =H80*IF('Assumptions & Budget'!$E$55="Revenue",H$90,IF('Assumptions & Budget'!$E$55="Orders",H$91,1)) -> 98.203355 | I109: =I80*IF('Assumptions & Budget'!$E$55="Revenue",I$90,IF('Assumptions & Budget'!$E$55="Orders",I$91,1)) -> 98.203355 | J109: =J80*IF('Assumptions & Budget'!$E$55="Revenue",J$90,IF('Assumptions & Budget'!$E$55="Orders",J$91,1)) -> 98.203355 | ... N109: =N80*IF('Assumptions & Budget'!$E$55="Revenue",N$90,IF('Assumptions & Budget'!$E$55="Orders",N$91,1)) -> 98.203355 | O109: =SUMIFS($C109:$N109,$C$5:$N$5,"<="&$C$3) -> 578.30865
A110: IT – software, cloud & other | B110: ₹ lakh | C110: =C81*IF('Assumptions & Budget'!$E$56="Revenue",C$90,IF('Assumptions & Budget'!$E$56="Orders",C$91,1)) -> 52.210667 | D110: =D81*IF('Assumptions & Budget'!$E$56="Revenue",D$90,IF('Assumptions & Budget'!$E$56="Orders",D$91,1)) -> 52.210667 | E110: =E81*IF('Assumptions & Budget'!$E$56="Revenue",E$90,IF('Assumptions & Budget'!$E$56="Orders",E$91,1)) -> 52.210667 | F110: =F81*IF('Assumptions & Budget'!$E$56="Revenue",F$90,IF('Assumptions & Budget'!$E$56="Orders",F$91,1)) -> 52.210667 | G110: =G81*IF('Assumptions & Budget'!$E$56="Revenue",G$90,IF('Assumptions & Budget'!$E$56="Orders",G$91,1)) -> 52.210667 | H110: =H81*IF('Assumptions & Budget'!$E$56="Revenue",H$90,IF('Assumptions & Budget'!$E$56="Orders",H$91,1)) -> 52.210667 | I110: =I81*IF('Assumptions & Budget'!$E$56="Revenue",I$90,IF('Assumptions & Budget'!$E$56="Orders",I$91,1)) -> 52.210667 | J110: =J81*IF('Assumptions & Budget'!$E$56="Revenue",J$90,IF('Assumptions & Budget'!$E$56="Orders",J$91,1)) -> 52.210667 | ... N110: =N81*IF('Assumptions & Budget'!$E$56="Revenue",N$90,IF('Assumptions & Budget'!$E$56="Orders",N$91,1)) -> 52.210667 | O110: =SUMIFS($C110:$N110,$C$5:$N$5,"<="&$C$3) -> 313.264
A111: IT – total | B111: ₹ lakh | C111: =C109+C110 -> 146.77686 | D111: =D109+D110 -> 146.77686 | E111: =E109+E110 -> 146.77686 | F111: =F109+F110 -> 150.41402 | G111: =G109+G110 -> 150.41402 | H111: =H109+H110 -> 150.41402 | I111: =I109+I110 -> 150.41402 | J111: =J109+J110 -> 150.41402 | ... N111: =N109+N110 -> 150.41402 | O111: =SUMIFS($C111:$N111,$C$5:$N$5,"<="&$C$3) -> 891.57265
...

Sheet Variance-to-Action Log
A1: Variance-to-Action Log
A2: Every material variance is classified (Timing / One-off / Structural) and mapped to an action. Variances are measured against the FLEXED budget.
A3: Actuals loaded through | C3: ='Assumptions & Budget'!$C$6 -> 46266 | D3: Materiality: ≥ | F3: ='Assumptions & Budget'!$C$8 -> 0.05 | G3: and ≥ ₹ lakh | H3: ='Assumptions & Budget'!$C$9 -> 25 | I3: Look-back (months) | K3: ='Assumptions & Budget'!$C$10 -> 3
A4: Rules: Timing → Ignore (reversal built into forecast) · One-off → Ignore (excluded from run-rate) · Structural → Reforecast by default. Analyst may override with a documented reason (e.g. Cut spend). Blue cells in columns O, P, R, S are analyst inputs.
A7: Line item | B7: Cost centre | C7: Type | D7: YTD budget | E7: YTD actual | F7: YTD flexed budget | G7: YTD var vs flexed | H7: YTD var % | I7: Look-back flexed budget | J7: Look-back actual | K7: Look-back var | L7: Look-back var % | M7: Trigger | N7: Fav / Unfav | O7: Cause (analyst) | P7: Evidence / rationale | Q7: Suggested action | R7: Analyst override | S7: Override reason | T7: FINAL ACTION | U7: Run-rate adj % | V7: Forecast adj % applied | W7: Timing reversal (₹ lakh) | X7: Trigger variance (₹ lakh)
A8: Net revenue | B8: ='Assumptions & Budget'!B43 -> – | C8: ='Assumptions & Budget'!D43 -> Volume-driven | D8: ='Actual vs Budget'!O63 -> 21227.704 | E8: ='Actual vs Budget'!O13 -> 21420.89 | F8: ='Actual vs Budget'!O92 -> 21227.704 | G8: ='Actual vs Budget'!O146 -> 193.18544 | H8: ='Actual vs Budget'!P146 -> 0.0091006278 | I8: =SUMIFS('Actual vs Budget'!$C92:$N92,'Actual vs Budget'!$C$5:$N$5,">"&EDATE($C$3,-$K$3),'Actual vs Budget'!$C$5:$N$5,"<="&$C$3) -> 10718.425 | J8: =SUMIFS('Actual vs Budget'!$C13:$N13,'Actual vs Budget'!$C$5:$N$5,">"&EDATE($C$3,-$K$3),'Actual vs Budget'!$C$5:$N$5,"<="&$C$3) -> 10832.531 | K8: =SUMIFS('Actual vs Budget'!$C146:$N146,'Actual vs Budget'!$C$5:$N$5,">"&EDATE($C$3,-$K$3),'Actual vs Budget'!$C$5:$N$5,"<="&$C$3) -> 114.10595 | L8: =IF(I8=0,0,K8/I8) -> 0.010645776 | M8: =IF(AND(ABS(H8)>=$F$3,ABS(G8)>=$H$3),"YTD",IF(AND(ABS(L8)>=$F$3,ABS(K8)>=$H$3),"Run-rate","–")) -> – | N8: =IF(M8="–","–",IF(IF(M8="YTD",G8,K8)<0,"Unfav","Fav")) -> – | Q8: =IF(M8="–","No action",IF(O8="","Classify cause",IF(O8="Structural","Reforecast","Ignore"))) -> No action | T8: =IF(M8="–","No action",IF(O8="","Classify cause",IF(R8<>"",IF(S8="","Reason required",R8),Q8))) -> No action | U8: 0 | V8: =IF(T8="Reforecast",U8,IF(T8="Cut spend",U8*(1-'Assumptions & Budget'!$C$12),0)) -> 0 | W8: 0 | X8: =IF(M8="–",0,IF(M8="YTD",G8,K8)) -> 0
A9: Cost of goods sold | B9: ='Assumptions & Budget'!B44 -> – | C9: ='Assumptions & Budget'!D44 -> Variable | D9: ='Actual vs Budget'!O64 -> 6580.5883 | E9: ='Actual vs Budget'!O14 -> 6464.9 | F9: ='Actual vs Budget'!O93 -> 6640.4758 | G9: ='Actual vs Budget'!O147 -> 175.57582 | H9: ='Actual vs Budget'!P147 -> 0.026440247 | I9: =SUMIFS('Actual vs Budget'!$C93:$N93,'Actual vs Budget'!$C$5:$N$5,">"&EDATE($C$3,-$K$3),'Actual vs Budget'!$C$5:$N$5,"<="&$C$3) -> 3358.0846 | J9: =SUMIFS('Actual vs Budget'!$C14:$N14,'Actual vs Budget'!$C$5:$N$5,">"&EDATE($C$3,-$K$3),'Actual vs Budget'!$C$5:$N$5,"<="&$C$3) -> 3154 | K9: =SUMIFS('Actual vs Budget'!$C147:$N147,'Actual vs Budget'!$C$5:$N$5,">"&EDATE($C$3,-$K$3),'Actual vs Budget'!$C$5:$N$5,"<="&$C$3) -> 204.08461 | L9: =IF(I9=0,0,K9/I9) -> 0.060774111 | M9: =IF(AND(ABS(H9)>=$F$3,ABS(G9)>=$H$3),"YTD",IF(AND(ABS(L9)>=$F$3,ABS(K9)>=$H$3),"Run-rate","–")) -> Run-rate | N9: =IF(M9="–","–",IF(IF(M9="YTD",G9,K9)<0,"Unfav","Fav")) -> Fav | O9: Structural | P9: Gross margin up from Jul: supplier price renegotiation and lower inbound freight; contract runs multi-year. | Q9: =IF(M9="–","No action",IF(O9="","Classify cause",IF(O9="Structural","Reforecast","Ignore"))) -> Reforecast | T9: =IF(M9="–","No action",IF(O9="","Classify cause",IF(R9<>"",IF(S9="","Reason required",R9),Q9))) -> Reforecast | U9: =-L9 -> -0.060774111 | V9: =IF(T9="Reforecast",U9,IF(T9="Cut spend",U9*(1-'Assumptions & Budget'!$C$12),0)) -> -0.060774111 | W9: =IF(O9="Timing",G9,0) -> 0 | X9: =IF(M9="–",0,IF(M9="YTD",G9,K9)) -> 204.08461
A10: Sales – personnel | B10: ='Assumptions & Budget'!B45 -> Sales | C10: ='Assumptions & Budget'!D45 -> Committed | D10: ='Actual vs Budget'!O66 -> 429.61917 | E10: ='Actual vs Budget'!O18 -> 465.8 | F10: ='Actual vs Budget'!O95 -> 429.61917 | G10: ='Actual vs Budget'!O149 -> -36.180827 | H10: ='Actual vs Budget'!P149 -> -0.084216043 | I10: =SUMIFS('Actual vs Budget'!$C95:$N95,'Actual vs Budget'!$C$5:$N$5,">"&EDATE($C$3,-$K$3),'Actual vs Budget'!$C$5:$N$5,"<="&$C$3) -> 215.99638 | J10: =SUMIFS('Actual vs Budget'!$C18:$N18,'Actual vs Budget'!$C$5:$N$5,">"&EDATE($C$3,-$K$3),'Actual vs Budget'!$C$5:$N$5,"<="&$C$3) -> 235 | K10: =SUMIFS('Actual vs Budget'!$C149:$N149,'Actual vs Budget'!$C$5:$N$5,">"&EDATE($C$3,-$K$3),'Actual vs Budget'!$C$5:$N$5,"<="&$C$3) -> -19.00362 | L10: =IF(I10=0,0,K10/I10) -> -0.087981197 | M10: =IF(AND(ABS(H10)>=$F$3,ABS(G10)>=$H$3),"YTD",IF(AND(ABS(L10)>=$F$3,ABS(K10)>=$H$3),"Run-rate","–")) -> YTD | N10: =IF(M10="–","–",IF(IF(M10="YTD",G10,K10)<0,"Unfav","Fav")) -> Unfav | O10: Structural | P10: 5 unplanned sales hires since Apr for marketplace / quick-commerce accounts; permanent run-rate cost. | Q10: =IF(M10="–","No action",IF(O10="","Classify cause",IF(O10="Structural","Reforecast","Ignore"))) -> Reforecast | T10: =IF(M10="–","No action",IF(O10="","Classify cause",IF(R10<>"",IF(S10="","Reason required",R10),Q10))) -> Reforecast | U10: =-L10 -> 0.087981197 | V10: =IF(T10="Reforecast",U10,IF(T10="Cut spend",U10*(1-'Assumptions & Budget'!$C$12),0)) -> 0.087981197 | W10: =IF(O10="Timing",G10,0) -> 0 | X10: =IF(M10="–",0,IF(M10="YTD",G10,K10)) -> -36.180827
A11: Sales – marketplace & payment fees | B11: ='Assumptions & Budget'!B46 -> Sales | C11: ='Assumptions & Budget'!D46 -> Variable | D11: ='Actual vs Budget'!O67 -> 636.83113 | E11: ='Actual vs Budget'!O19 -> 684.4 | F11: ='Actual vs Budget'!O96 -> 642.62669 | G11: ='Actual vs Budget'!O150 -> -41.773308 | H11: ='Actual vs Budget'!P150 -> -0.065004003 | I11: =SUMIFS('Actual vs Budget'!$C96:$N96,'Actual vs Budget'!$C$5:$N$5,">"&EDATE($C$3,-$K$3),'Actual vs Budget'!$C$5:$N$5,"<="&$C$3) -> 324.97593 | J11: =SUMIFS('Actual vs Budget'!$C19:$N19,'Actual vs Budget'!$C$5:$N$5,">"&EDATE($C$3,-$K$3),'Actual vs Budget'!$C$5:$N$5,"<="&$C$3) -> 371.2 | K11: =SUMIFS('Actual vs Budget'!$C150:$N150,'Actual vs Budget'!$C$5:$N$5,">"&EDATE($C$3,-$K$3),'Actual vs Budget'!$C$5:$N$5,"<="&$C$3) -> -46.22407 | L11: =IF(I11=0,0,K11/I11) -> -0.14223844 | M11: =IF(AND(ABS(H11)>=$F$3,ABS(G11)>=$H$3),"YTD",IF(AND(ABS(L11)>=$F$3,ABS(K11)>=$H$3),"Run-rate","–")) -> YTD | N11: =IF(M11="–","–",IF(IF(M11="YTD",G11,K11)<0,"Unfav","Fav")) -> Unfav | O11: Structural | P11: Marketplace commission and platform-fee revision (~0.4 pp of sales) effective Jul. | Q11: =IF(M11="–","No action",IF(O11="","Classify cause",IF(O11="Structural","Reforecast","Ignore"))) -> Reforecast | T11: =IF(M11="–","No action",IF(O11="","Classify cause",IF(R11<>"",IF(S11="","Reason required",R11),Q11))) -> Reforecast | U11: =-L11 -> 0.14223844 | V11: =IF(T11="Reforecast",U11,IF(T11="Cut spend",U11*(1-'Assumptions & Budget'!$C$12),0)) -> 0.14223844 | W11: =IF(O11="Timing",G11,0) -> 0 | X11: =IF(M11="–",0,IF(M11="YTD",G11,K11)) -> -41.773308
A12: Operations – personnel | B12: ='Assumptions & Budget'!B47 -> Operations | C12: ='Assumptions & Budget'!D47 -> Committed | D12: ='Actual vs Budget'!O69 -> 605.59732 | E12: ='Actual vs Budget'!O21 -> 604.7 | F12: ='Actual vs Budget'!O98 -> 605.59732 | G12: ='Actual vs Budget'!O152 -> 0.89731544 | H12: ='Actual vs Budget'!P152 -> 0.0014817031 | I12: =SUMIFS('Actual vs Budget'!$C98:$N98,'Actual vs Budget'!$C$5:$N$5,">"&EDATE($C$3,-$K$3),'Actual vs Budget'!$C$5:$N$5,"<="&$C$3) -> 302.79866 | J12: =SUMIFS('Actual vs Budget'!$C21:$N21,'Actual vs Budget'!$C$5:$N$5,">"&EDATE($C$3,-$K$3),'Actual vs Budget'!$C$5:$N$5,"<="&$C$3) -> 302.4 | K12: =SUMIFS('Actual vs Budget'!$C152:$N152,'Actual vs Budget'!$C$5:$N$5,">"&EDATE($C$3,-$K$3),'Actual vs Budget'!$C$5:$N$5,"<="&$C$3) -> 0.39865772 | L12: =IF(I12=0,0,K12/I12) -> 0.0013165769 | M12: =IF(AND(ABS(H12)>=$F$3,ABS(G12)>=$H$3),"YTD",IF(AND(ABS(L12)>=$F$3,ABS(K12)>=$H$3),"Run-rate","–")) -> – | N12: =IF(M12="–","–",IF(IF(M12="YTD",G12,K12)<0,"Unfav","Fav")) -> – | Q12: =IF(M12="–","No action",IF(O12="","Classify cause",IF(O12="Structural","Reforecast","Ignore"))) -> No action | T12: =IF(M12="–","No action",IF(O12="","Classify cause",IF(R12<>"",IF(S12="","Reason required",R12),Q12))) -> No action | U12: =-L12 -> -0.0013165769 | V12: =IF(T12="Reforecast",U12,IF(T12="Cut spend",U12*(1-'Assumptions & Budget'!$C$12),0)) -> 0 | W12: =IF(O12="Timing",G12,0) -> 0 | X12: =IF(M12="–",0,IF(M12="YTD",G12,K12)) -> 0
A13: Operations – fulfilment & logistics | B13: ='Assumptions & Budget'!B48 -> Operations | C13: ='Assumptions & Budget'!D48 -> Variable | D13: ='Actual vs Budget'!O70 -> 1578.0253 | E13: ='Actual vs Budget'!O22 -> 1699.4 | F13: ='Actual vs Budget'!O99 -> 1604.0553 | G13: ='Actual vs Budget'!O153 -> -95.344749 | H13: ='Actual vs Budget'!P153 -> -0.059439816 | I13: =SUMIFS('Actual vs Budget'!$C99:$N99,'Actual vs Budget'!$C$5:$N$5,">"&EDATE($C$3,-$K$3),'Actual vs Budget'!$C$5:$N$5,"<="&$C$3) -> 810.81207 | J13: =SUMIFS('Actual vs Budget'!$C22:$N22,'Actual vs Budget'!$C$5:$N$5,">"&EDATE($C$3,-$K$3),'Actual vs Budget'!$C$5:$N$5,"<="&$C$3) -> 880 | K13: =SUMIFS('Actual vs Budget'!$C153:$N153,'Actual vs Budget'!$C$5:$N$5,">"&EDATE($C$3,-$K$3),'Actual vs Budget'!$C$5:$N$5,"<="&$C$3) -> -69.187926 | L13: =IF(I13=0,0,K13/I13) -> -0.085331642 | M13: =IF(AND(ABS(H13)>=$F$3,ABS(G13)>=$H$3),"YTD",IF(AND(ABS(L13)>=$F$3,ABS(K13)>=$H$3),"Run-rate","–")) -> YTD | N13: =IF(M13="–","–",IF(IF(M13="YTD",G13,K13)<0,"Unfav","Fav")) -> Unfav | O13: Structural | P13: Courier rate-card revision from Jun (+9% per order) plus higher RTO share. | Q13: =IF(M13="–","No action",IF(O13="","Classify cause",IF(O13="Structural","Reforecast","Ignore"))) -> Reforecast | T13: =IF(M13="–","No action",IF(O13="","Classify cause",IF(R13<>"",IF(S13="","Reason required",R13),Q13))) -> Reforecast | U13: =-L13 -> 0.085331642 | V13: =IF(T13="Reforecast",U13,IF(T13="Cut spend",U13*(1-'Assumptions & Budget'!$C$12),0)) -> 0.085331642 | W13: =IF(O13="Timing",G13,0) -> 0 | X13: =IF(M13="–",0,IF(M13="YTD",G13,K13)) -> -95.344749
A14: Operations – warehouse, QC & other | B14: ='Assumptions & Budget'!B49 -> Operations | C14: ='Assumptions & Budget'!D49 -> Committed | D14: ='Actual vs Budget'!O71 -> 205.905 | E14: ='Actual vs Budget'!O23 -> 278.6 | F14: ='Actual vs Budget'!O100 -> 205.905 | G14: ='Actual vs Budget'!O154 -> -72.695 | H14: ='Actual vs Budget'!P154 -> -0.35305116 | I14: =SUMIFS('Actual vs Budget'!$C100:$N100,'Actual vs Budget'!$C$5:$N$5,">"&EDATE($C$3,-$K$3),'Actual vs Budget'!$C$5:$N$5,"<="&$C$3) -> 102.9525 | J14: =SUMIFS('Actual vs Budget'!$C23:$N23,'Actual vs Budget'!$C$5:$N$5,">"&EDATE($C$3,-$K$3),'Actual vs Budget'!$C$5:$N$5,"<="&$C$3) -> 174.4 | K14: =SUMIFS('Actual vs Budget'!$C154:$N154,'Actual vs Budget'!$C$5:$N$5,">"&EDATE($C$3,-$K$3),'Actual vs Budget'!$C$5:$N$5,"<="&$C$3) -> -71.4475 | L14: =IF(I14=0,0,K14/I14) -> -0.69398509 | M14: =IF(AND(ABS(H14)>=$F$3,ABS(G14)>=$H$3),"YTD",IF(AND(ABS(L14)>=$F$3,ABS(K14)>=$H$3),"Run-rate","–")) -> YTD | N14: =IF(M14="–","–",IF(IF(M14="YTD",G14,K14)<0,"Unfav","Fav")) -> Unfav | O14: One-off | P14: Jul: expired-inventory write-off and warehouse re-racking; non-recurring. | Q14: =IF(M14="–","No action",IF(O14="","Classify cause",IF(O14="Structural","Reforecast","Ignore"))) -> Ignore | T14: =IF(M14="–","No action",IF(O14="","Classify cause",IF(R14<>"",IF(S14="","Reason required",R14),Q14))) -> Ignore | U14: =-L14 -> 0.69398509 | V14: =IF(T14="Reforecast",U14,IF(T14="Cut spend",U14*(1-'Assumptions & Budget'!$C$12),0)) -> 0 | W14: =IF(O14="Timing",G14,0) -> 0 | X14: =IF(M14="–",0,IF(M14="YTD",G14,K14)) -> -72.695
A15: Marketing – personnel | B15: ='Assumptions & Budget'!B50 -> Marketing | C15: ='Assumptions & Budget'!D50 -> Committed | D15: ='Actual vs Budget'!O73 -> 554.66128 | E15: ='Actual vs Budget'!O25 -> 551.9 | F15: ='Actual vs Budget'!O102 -> 554.66128 | G15: ='Actual vs Budget'!O156 -> 2.7612784 | H15: ='Actual vs Budget'!P156 -> 0.0049783146 | I15: =SUMIFS('Actual vs Budget'!$C102:$N102,'Actual vs Budget'!$C$5:$N$5,">"&EDATE($C$3,-$K$3),'Actual vs Budget'!$C$5:$N$5,"<="&$C$3) -> 281.53262 | J15: =SUMIFS('Actual vs Budget'!$C25:$N25,'Actual vs Budget'!$C$5:$N$5,">"&EDATE($C$3,-$K$3),'Actual vs Budget'!$C$5:$N$5,"<="&$C$3) -> 280 | K15: =SUMIFS('Actual vs Budget'!$C156:$N156,'Actual vs Budget'!$C$5:$N$5,">"&EDATE($C$3,-$K$3),'Actual vs Budget'!$C$5:$N$5,"<="&$C$3) -> 1.5326186 | L15: =IF(I15=0,0,K15/I15) -> 0.0054438401 | M15: =IF(AND(ABS(H15)>=$F$3,ABS(G15)>=$H$3),"YTD",IF(AND(ABS(L15)>=$F$3,ABS(K15)>=$H$3),"Run-rate","–")) -> – | N15: =IF(M15="–","–",IF(IF(M15="YTD",G15,K15)<0,"Unfav","Fav")) -> – | Q15: =IF(M15="–","No action",IF(O15="","Classify cause",IF(O15="Structural","Reforecast","Ignore"))) -> No action | T15: =IF(M15="–","No action",IF(O15="","Classify cause",IF(R15<>"",IF(S15="","Reason required",R15),Q15))) -> No action | U15: =-L15 -> -0.0054438401 | V15: =IF(T15="Reforecast",U15,IF(T15="Cut spend",U15*(1-'Assumptions & Budget'!$C$12),0)) -> 0 | W15: =IF(O15="Timing",G15,0) -> 0 | X15: =IF(M15="–",0,IF(M15="YTD",G15,K15)) -> 0
A16: Marketing – performance marketing | B16: ='Assumptions & Budget'!B51 -> Marketing | C16: ='Assumptions & Budget'!D51 -> Discretionary | D16: ='Actual vs Budget'!O74 -> 4563.9564 | E16: ='Actual vs Budget'!O26 -> 4735.4 | F16: ='Actual vs Budget'!O103 -> 4563.9564 | G16: ='Actual vs Budget'!O157 -> -171.44357 | H16: ='Actual vs Budget'!P157 -> -0.037564682 | I16: =SUMIFS('Actual vs Budget'!$C103:$N103,'Actual vs Budget'!$C$5:$N$5,">"&EDATE($C$3,-$K$3),'Actual vs Budget'!$C$5:$N$5,"<="&$C$3) -> 2304.4614 | J16: =SUMIFS('Actual vs Budget'!$C26:$N26,'Actual vs Budget'!$C$5:$N$5,">"&EDATE($C$3,-$K$3),'Actual vs Budget'!$C$5:$N$5,"<="&$C$3) -> 2497 | K16: =SUMIFS('Actual vs Budget'!$C157:$N157,'Actual vs Budget'!$C$5:$N$5,">"&EDATE($C$3,-$K$3),'Actual vs Budget'!$C$5:$N$5,"<="&$C$3) -> -192.53862 | L16: =IF(I16=0,0,K16/I16) -> -0.083550377 | M16: =IF(AND(ABS(H16)>=$F$3,ABS(G16)>=$H$3),"YTD",IF(AND(ABS(L16)>=$F$3,ABS(K16)>=$H$3),"Run-rate","–")) -> Run-rate | N16: =IF(M16="–","–",IF(IF(M16="YTD",G16,K16)<0,"Unfav","Fav")) -> Unfav | O16: Timing | P16: Sep: Diwali campaign spend pulled forward to lock in CPMs and inventory; reverses Oct–Nov. | Q16: =IF(M16="–","No action",IF(O16="","Classify cause",IF(O16="Structural","Reforecast","Ignore"))) -> Ignore | T16: =IF(M16="–","No action",IF(O16="","Classify cause",IF(R16<>"",IF(S16="","Reason required",R16),Q16))) -> Ignore | U16: =-L16 -> 0.083550377 | V16: =IF(T16="Reforecast",U16,IF(T16="Cut spend",U16*(1-'Assumptions & Budget'!$C$12),0)) -> 0 | W16: =IF(O16="Timing",G16,0) -> -171.44357 | X16: =IF(M16="–",0,IF(M16="YTD",G16,K16)) -> -192.53862
A17: Marketing – brand & influencer | B17: ='Assumptions & Budget'!B52 -> Marketing | C17: ='Assumptions & Budget'!D52 -> Discretionary | D17: ='Actual vs Budget'!O75 -> 2122.7704 | E17: ='Actual vs Budget'!O27 -> 2320.1 | F17: ='Actual vs Budget'!O104 -> 2122.7704 | G17: ='Actual vs Budget'!O158 -> -197.32957 | H17: ='Actual vs Budget'!P158 -> -0.092958507 | I17: =SUMIFS('Actual vs Budget'!$C104:$N104,'Actual vs Budget'!$C$5:$N$5,">"&EDATE($C$3,-$K$3),'Actual vs Budget'!$C$5:$N$5,"<="&$C$3) -> 1071.8425 | J17: =SUMIFS('Actual vs Budget'!$C27:$N27,'Actual vs Budget'!$C$5:$N$5,">"&EDATE($C$3,-$K$3),'Actual vs Budget'!$C$5:$N$5,"<="&$C$3) -> 1209 | K17: =SUMIFS('Actual vs Budget'!$C158:$N158,'Actual vs Budget'!$C$5:$N$5,">"&EDATE($C$3,-$K$3),'Actual vs Budget'!$C$5:$N$5,"<="&$C$3) -> -137.1575 | L17: =IF(I17=0,0,K17/I17) -> -0.12796423 | M17: =IF(AND(ABS(H17)>=$F$3,ABS(G17)>=$H$3),"YTD",IF(AND(ABS(L17)>=$F$3,ABS(K17)>=$H$3),"Run-rate","–")) -> YTD | N17: =IF(M17="–","–",IF(IF(M17="YTD",G17,K17)<0,"Unfav","Fav")) -> Unfav | O17: Structural | P17: Creator / influencer retainers stepped up from Jun beyond approved plan. | Q17: =IF(M17="–","No action",IF(O17="","Classify cause",IF(O17="Structural","Reforecast","Ignore"))) -> Reforecast | R17: Cut spend | S17: Discretionary line: brand lead agreed to cap retainers from Nov and recover ~half of the overspend. | T17: =IF(M17="–","No action",IF(O17="","Classify cause",IF(R17<>"",IF(S17="","Reason required",R17),Q17))) -> Cut spend | U17: =-L17 -> 0.12796423 | V17: =IF(T17="Reforecast",U17,IF(T17="Cut spend",U17*(1-'Assumptions & Budget'!$C$12),0)) -> 0.063982113 | W17: =IF(O17="Timing",G17,0) -> 0 | X17: =IF(M17="–",0,IF(M17="YTD",G17,K17)) -> -197.32957
A18: HR – personnel | B18: ='Assumptions & Budget'!B53 -> HR | C18: ='Assumptions & Budget'!D53 -> Committed | D18: ='Actual vs Budget'!O77 -> 90.072 | E18: ='Actual vs Budget'!O29 -> 84.5 | F18: ='Actual vs Budget'!O106 -> 90.072 | G18: ='Actual vs Budget'!O160 -> 5.572 | H18: ='Actual vs Budget'!P160 -> 0.061861622 | I18: =SUMIFS('Actual vs Budget'!$C106:$N106,'Actual vs Budget'!$C$5:$N$5,">"&EDATE($C$3,-$K$3),'Actual vs Budget'!$C$5:$N$5,"<="&$C$3) -> 45.036 | J18: =SUMIFS('Actual vs Budget'!$C29:$N29,'Actual vs Budget'!$C$5:$N$5,">"&EDATE($C$3,-$K$3),'Actual vs Budget'!$C$5:$N$5,"<="&$C$3) -> 42.7 | K18: =SUMIFS('Actual vs Budget'!$C160:$N160,'Actual vs Budget'!$C$5:$N$5,">"&EDATE($C$3,-$K$3),'Actual vs Budget'!$C$5:$N$5,"<="&$C$3) -> 2.336 | L18: =IF(I18=0,0,K18/I18) -> 0.051869615 | M18: =IF(AND(ABS(H18)>=$F$3,ABS(G18)>=$H$3),"YTD",IF(AND(ABS(L18)>=$F$3,ABS(K18)>=$H$3),"Run-rate","–")) -> – | N18: =IF(M18="–","–",IF(IF(M18="YTD",G18,K18)<0,"Unfav","Fav")) -> – | Q18: =IF(M18="–","No action",IF(O18="","Classify cause",IF(O18="Structural","Reforecast","Ignore"))) -> No action | T18: =IF(M18="–","No action",IF(O18="","Classify cause",IF(R18<>"",IF(S18="","Reason required",R18),Q18))) -> No action | U18: =-L18 -> -0.051869615 | V18: =IF(T18="Reforecast",U18,IF(T18="Cut spend",U18*(1-'Assumptions & Budget'!$C$12),0)) -> 0 | W18: =IF(O18="Timing",G18,0) -> 0 | X18: =IF(M18="–",0,IF(M18="YTD",G18,K18)) -> 0
A19: HR – recruitment, training & other | B19: ='Assumptions & Budget'!B54 -> HR | C19: ='Assumptions & Budget'!D54 -> Discretionary | D19: ='Actual vs Budget'!O78 -> 60.7425 | E19: ='Actual vs Budget'!O30 -> 60 | F19: ='Actual vs Budget'!O107 -> 60.7425 | G19: ='Actual vs Budget'!O161 -> 0.7425 | H19: ='Actual vs Budget'!P161 -> 0.012223731 | I19: =SUMIFS('Actual vs Budget'!$C107:$N107,'Actual vs Budget'!$C$5:$N$5,">"&EDATE($C$3,-$K$3),'Actual vs Budget'!$C$5:$N$5,"<="&$C$3) -> 30.37125 | J19: =SUMIFS('Actual vs Budget'!$C30:$N30,'Actual vs Budget'!$C$5:$N$5,">"&EDATE($C$3,-$K$3),'Actual vs Budget'!$C$5:$N$5,"<="&$C$3) -> 30.9 | K19: =SUMIFS('Actual vs Budget'!$C161:$N161,'Actual vs Budget'!$C$5:$N$5,">"&EDATE($C$3,-$K$3),'Actual vs Budget'!$C$5:$N$5,"<="&$C$3) -> -0.52875 | L19: =IF(I19=0,0,K19/I19) -> -0.017409557 | M19: =IF(AND(ABS(H19)>=$F$3,ABS(G19)>=$H$3),"YTD",IF(AND(ABS(L19)>=$F$3,ABS(K19)>=$H$3),"Run-rate","–")) -> – | N19: =IF(M19="–","–",IF(IF(M19="YTD",G19,K19)<0,"Unfav","Fav")) -> – | Q19: =IF(M19="–","No action",IF(O19="","Classify cause",IF(O19="Structural","Reforecast","Ignore"))) -> No action | T19: =IF(M19="–","No action",IF(O19="","Classify cause",IF(R19<>"",IF(S19="","Reason required",R19),Q19))) -> No action | U19: =-L19 -> 0.017409557 | V19: =IF(T19="Reforecast",U19,IF(T19="Cut spend",U19*(1-'Assumptions & Budget'!$C$12),0)) -> 0 | W19: =IF(O19="Timing",G19,0) -> 0 | X19: =IF(M19="–",0,IF(M19="YTD",G19,K19)) -> 0
A20: IT – personnel | B20: ='Assumptions & Budget'!B55 -> IT | C20: ='Assumptions & Budget'!D55 -> Committed | D20: ='Actual vs Budget'!O80 -> 578.30865 | E20: ='Actual vs Budget'!O32 -> 579.9 | F20: ='Actual vs Budget'!O109 -> 578.30865 | G20: ='Actual vs Budget'!O163 -> -1.5913548 | H20: ='Actual vs Budget'!P163 -> -0.0027517397 | I20: =SUMIFS('Actual vs Budget'!$C109:$N109,'Actual vs Budget'!$C$5:$N$5,">"&EDATE($C$3,-$K$3),'Actual vs Budget'!$C$5:$N$5,"<="&$C$3) -> 294.61006 | J20: =SUMIFS('Actual vs Budget'!$C32:$N32,'Actual vs Budget'!$C$5:$N$5,">"&EDATE($C$3,-$K$3),'Actual vs Budget'!$C$5:$N$5,"<="&$C$3) -> 295.9 | K20: =SUMIFS('Actual vs Budget'!$C163:$N163,'Actual vs Budget'!$C$5:$N$5,">"&EDATE($C$3,-$K$3),'Actual vs Budget'!$C$5:$N$5,"<="&$C$3) -> -1.2899355 | L20: =IF(I20=0,0,K20/I20) -> -0.0043784502 | M20: =IF(AND(ABS(H20)>=$F$3,ABS(G20)>=$H$3),"YTD",IF(AND(ABS(L20)>=$F$3,ABS(K20)>=$H$3),"Run-rate","–")) -> – | N20: =IF(M20="–","–",IF(IF(M20="YTD",G20,K20)<0,"Unfav","Fav")) -> – | Q20: =IF(M20="–","No action",IF(O20="","Classify cause",IF(O20="Structural","Reforecast","Ignore"))) -> No action | T20: =IF(M20="–","No action",IF(O20="","Classify cause",IF(R20<>"",IF(S20="","Reason required",R20),Q20))) -> No action | U20: =-L20 -> 0.0043784502 | V20: =IF(T20="Reforecast",U20,IF(T20="Cut spend",U20*(1-'Assumptions & Budget'!$C$12),0)) -> 0 | W20: =IF(O20="Timing",G20,0) -> 0 | X20: =IF(M20="–",0,IF(M20="YTD",G20,K20)) -> 0
A21: IT – software, cloud & other | B21: ='Assumptions & Budget'!B56 -> IT | C21: ='Assumptions & Budget'!D56 -> Committed | D21: ='Actual vs Budget'!O81 -> 313.264 | E21: ='Actual vs Budget'!O33 -> 394.5 | F21: ='Actual vs Budget'!O110 -> 313.264 | G21: ='Actual vs Budget'!O164 -> -81.236 | H21: ='Actual vs Budget'!P164 -> -0.25932121 | I21: =SUMIFS('Actual vs Budget'!$C110:$N110,'Actual vs Budget'!$C$5:$N$5,">"&EDATE($C$3,-$K$3),'Actual vs Budget'!$C$5:$N$5,"<="&$C$3) -> 156.632 | J21: =SUMIFS('Actual vs Budget'!$C33:$N33,'Actual vs Budget'!$C$5:$N$5,">"&EDATE($C$3,-$K$3),'Actual vs Budget'!$C$5:$N$5,"<="&$C$3) -> 153.2 | K21: =SUMIFS('Actual vs Budget'!$C164:$N164,'Actual vs Budget'!$C$5:$N$5,">"&EDATE($C$3,-$K$3),'Actual vs Budget'!$C$5:$N$5,"<="&$C$3) -> 3.432 | L21: =IF(I21=0,0,K21/I21) -> 0.021911231 | M21: =IF(AND(ABS(H21)>=$F$3,ABS(G21)>=$H$3),"YTD",IF(AND(ABS(L21)>=$F$3,ABS(K21)>=$H$3),"Run-rate","–")) -> YTD | N21: =IF(M21="–","–",IF(IF(M21="YTD",G21,K21)<0,"Unfav","Fav")) -> Unfav | O21: One-off | P21: Jun: cybersecurity audit and data-migration project; non-recurring. | Q21: =IF(M21="–","No action",IF(O21="","Classify cause",IF(O21="Structural","Reforecast","Ignore"))) -> Ignore | T21: =IF(M21="–","No action",IF(O21="","Classify cause",IF(R21<>"",IF(S21="","Reason required",R21),Q21))) -> Ignore | U21: =-L21 -> -0.021911231 | V21: =IF(T21="Reforecast",U21,IF(T21="Cut spend",U21*(1-'Assumptions & Budget'!$C$12),0)) -> 0 | W21: =IF(O21="Timing",G21,0) -> 0 | X21: =IF(M21="–",0,IF(M21="YTD",G21,K21)) -> -81.236
A22: Finance – personnel | B22: ='Assumptions & Budget'!B57 -> Finance | C22: ='Assumptions & Budget'!D57 -> Committed | D22: ='Actual vs Budget'!O83 -> 235.872 | E22: ='Actual vs Budget'!O35 -> 235.1 | F22: ='Actual vs Budget'!O112 -> 235.872 | G22: ='Actual vs Budget'!O166 -> 0.772 | H22: ='Actual vs Budget'!P166 -> 0.0032729616 | I22: =SUMIFS('Actual vs Budget'!$C112:$N112,'Actual vs Budget'!$C$5:$N$5,">"&EDATE($C$3,-$K$3),'Actual vs Budget'!$C$5:$N$5,"<="&$C$3) -> 117.936 | J22: =SUMIFS('Actual vs Budget'!$C35:$N35,'Actual vs Budget'!$C$5:$N$5,">"&EDATE($C$3,-$K$3),'Actual vs Budget'!$C$5:$N$5,"<="&$C$3) -> 117.5 | K22: =SUMIFS('Actual vs Budget'!$C166:$N166,'Actual vs Budget'!$C$5:$N$5,">"&EDATE($C$3,-$K$3),'Actual vs Budget'!$C$5:$N$5,"<="&$C$3) -> 0.436 | L22: =IF(I22=0,0,K22/I22) -> 0.0036969204 | M22: =IF(AND(ABS(H22)>=$F$3,ABS(G22)>=$H$3),"YTD",IF(AND(ABS(L22)>=$F$3,ABS(K22)>=$H$3),"Run-rate","–")) -> – | N22: =IF(M22="–","–",IF(IF(M22="YTD",G22,K22)<0,"Unfav","Fav")) -> – | Q22: =IF(M22="–","No action",IF(O22="","Classify cause",IF(O22="Structural","Reforecast","Ignore"))) -> No action | T22: =IF(M22="–","No action",IF(O22="","Classify cause",IF(R22<>"",IF(S22="","Reason required",R22),Q22))) -> No action | U22: =-L22 -> -0.0036969204 | V22: =IF(T22="Reforecast",U22,IF(T22="Cut spend",U22*(1-'Assumptions & Budget'!$C$12),0)) -> 0 | W22: =IF(O22="Timing",G22,0) -> 0 | X22: =IF(M22="–",0,IF(M22="YTD",G22,K22)) -> 0
A23: Finance – professional fees, rent & admin | B23: ='Assumptions & Budget'!B58 -> Finance | C23: ='Assumptions & Budget'!D58 -> Committed | D23: ='Actual vs Budget'!O84 -> 372.431 | E23: ='Actual vs Budget'!O36 -> 375.8 | F23: ='Actual vs Budget'!O113 -> 372.431 | G23: ='Actual vs Budget'!O167 -> -3.369 | H23: ='Actual vs Budget'!P167 -> -0.0090459709 | I23: =SUMIFS('Actual vs Budget'!$C113:$N113,'Actual vs Budget'!$C$5:$N$5,">"&EDATE($C$3,-$K$3),'Actual vs Budget'!$C$5:$N$5,"<="&$C$3) -> 186.2155 | J23: =SUMIFS('Actual vs Budget'!$C36:$N36,'Actual vs Budget'!$C$5:$N$5,">"&EDATE($C$3,-$K$3),'Actual vs Budget'!$C$5:$N$5,"<="&$C$3) -> 190 | K23: =SUMIFS('Actual vs Budget'!$C167:$N167,'Actual vs Budget'!$C$5:$N$5,">"&EDATE($C$3,-$K$3),'Actual vs Budget'!$C$5:$N$5,"<="&$C$3) -> -3.7845 | L23: =IF(I23=0,0,K23/I23) -> -0.020323228 | M23: =IF(AND(ABS(H23)>=$F$3,ABS(G23)>=$H$3),"YTD",IF(AND(ABS(L23)>=$F$3,ABS(K23)>=$H$3),"Run-rate","–")) -> – | N23: =IF(M23="–","–",IF(IF(M23="YTD",G23,K23)<0,"Unfav","Fav")) -> – | Q23: =IF(M23="–","No action",IF(O23="","Classify cause",IF(O23="Structural","Reforecast","Ignore"))) -> No action | T23: =IF(M23="–","No action",IF(O23="","Classify cause",IF(R23<>"",IF(S23="","Reason required",R23),Q23))) -> No action | U23: =-L23 -> 0.020323228 | V23: =IF(T23="Reforecast",U23,IF(T23="Cut spend",U23*(1-'Assumptions & Budget'!$C$12),0)) -> 0 | W23: =IF(O23="Timing",G23,0) -> 0 | X23: =IF(M23="–",0,IF(M23="YTD",G23,K23)) -> 0
A25: Log summary
A26: Lines tested | C26: =COUNTA(A8:A23) -> 16
A27: Material variances | C27: =COUNTIF(M8:M23,"YTD")+COUNTIF(M8:M23,"Run-rate") -> 8
A28: of which Timing | C28: =COUNTIF(O8:O23,"Timing") -> 1
A29: of which One-off | C29: =COUNTIF(O8:O23,"One-off") -> 2
A30: of which Structural | C30: =COUNTIF(O8:O23,"Structural") -> 5
A31: Awaiting classification | C31: =COUNTIF(T8:T23,"Classify cause") -> 0
A32: Final action: Reforecast | C32: =COUNTIF(T8:T23,"Reforecast") -> 4
A33: Final action: Cut spend | C33: =COUNTIF(T8:T23,"Cut spend") -> 1
A34: Final action: Ignore | C34: =COUNTIF(T8:T23,"Ignore") -> 3
A35: Analyst overrides in use | C35: =COUNTIF(R8:R23,"?*") -> 1
A36: Overrides missing a reason | C36: =COUNTIF(T8:T23,"Reason required") -> 0
A38: Revenue-driver run-rate (look-back window; used in Rolling Forecast when revenue action = Reforecast)
A39: Orders: actual vs budget over look-back | C39: =IF(SUMIFS('Actual vs Budget'!$C61:$N61,'Actual vs Budget'!$C$5:$N$5,">"&EDATE($C$3,-$K$3),'Actual vs Budget'!$C$5:$N$5,"<="&$C$3)=0,0,SUMIFS('Actual vs Budget'!$C10:$N10,'Actual vs Budget'!$C$5:$N$5,">"&EDATE($C$3,-$K$3),'Actual vs Budget'!$C$5:$N$5,"<="&$C$3)/SUMIFS('Actual vs Budget'!$C61:$N61,'Actual vs Budget'!$C$5:$N$5,">"&EDATE($C$3,-$K$3),'Actual vs Budget'!$C$5:$N$5,"<="&$C$3)-1) -> 0.022220186
A40: Net AOV: actual vs budget over look-back | C40: =IF(OR(SUMIFS('Actual vs Budget'!$C10:$N10,'Actual vs Budget'!$C$5:$N$5,">"&EDATE($C$3,-$K$3),'Actual vs Budget'!$C$5:$N$5,"<="&$C$3)=0,SUMIFS('Actual vs Budget'!$C61:$N61,'Actual vs Budget'!$C$5:$N$5,">"&EDATE($C$3,-$K$3),'Actual vs Budget'!$C$5:$N$5,"<="&$C$3)=0,SUMIFS('Actual vs Budget'!$C63:$N63,'Actual vs Budget'!$C$5:$N$5,">"&EDATE($C$3,-$K$3),'Actual vs Budget'!$C$5:$N$5,"<="&$C$3)=0),0,(SUMIFS('Actual vs Budget'!$C13:$N13,'Actual vs Budget'!$C$5:$N$5,">"&EDATE($C$3,-$K$3),'Actual vs Budget'!$C$5:$N$5,"<="&$C$3)/SUMIFS('Actual vs Budget'!$C10:$N10,'Actual vs Budget'!$C$5:$N$5,">"&EDATE($C$3,-$K$3),'Actual vs Budget'!$C$5:$N$5,"<="&$C$3))/(SUMIFS('Actual vs Budget'!$C63:$N63,'Actual vs Budget'!$C$5:$N$5,">"&EDATE($C$3,-$K$3),'Actual vs Budget'!$C$5:$N$5,"<="&$C$3)/SUMIFS('Actual vs Budget'!$C61:$N61,'Actual vs Budget'!$C$5:$N$5,">"&EDATE($C$3,-$K$3),'Actual vs Budget'!$C$5:$N$5,"<="&$C$3))-1) -> -0.011322815

Sheet Rolling Forecast
A1: Rolling Forecast – FY27 (₹ lakh)
A2: Closed months = actuals. Open months = budget × volume factor × (1 + run-rate adjustment from the Variance-to-Action Log) ± timing reversal.
A3: Actuals loaded through | C3: ='Assumptions & Budget'!$C$6 -> 46266 | D3: Reversal months | F3: ='Assumptions & Budget'!$C$11 -> 2
A5: Line item | B5: Unit | C5: ='Assumptions & Budget'!C61 -> 46113 | D5: ='Assumptions & Budget'!D61 -> 46143 | E5: ='Assumptions & Budget'!E61 -> 46174 | F5: ='Assumptions & Budget'!F61 -> 46204 | G5: ='Assumptions & Budget'!G61 -> 46235 | H5: ='Assumptions & Budget'!H61 -> 46266 | I5: ='Assumptions & Budget'!I61 -> 46296 | J5: ='Assumptions & Budget'!J61 -> 46327 | ... N5: ='Assumptions & Budget'!N61 -> 46447 | O5: FY27 Rolling Fcst | P5: FY27 Budget | Q5: Var ₹ / Δ pp (fav +) | R5: Var %
A6: Status | C6: =IF(C5<=$C$3,"Actual","Forecast") -> Actual | D6: =IF(D5<=$C$3,"Actual","Forecast") -> Actual | E6: =IF(E5<=$C$3,"Actual","Forecast") -> Actual | F6: =IF(F5<=$C$3,"Actual","Forecast") -> Actual | G6: =IF(G5<=$C$3,"Actual","Forecast") -> Actual | H6: =IF(H5<=$C$3,"Actual","Forecast") -> Actual | I6: =IF(I5<=$C$3,"Actual","Forecast") -> Forecast | J6: =IF(J5<=$C$3,"Actual","Forecast") -> Forecast | ... N6: =IF(N5<=$C$3,"Actual","Forecast") -> Forecast
A7: Forecast month number | C7: =MAX(0,(YEAR(C5)-YEAR($C$3))*12+MONTH(C5)-MONTH($C$3)) -> 0 | D7: =MAX(0,(YEAR(D5)-YEAR($C$3))*12+MONTH(D5)-MONTH($C$3)) -> 0 | E7: =MAX(0,(YEAR(E5)-YEAR($C$3))*12+MONTH(E5)-MONTH($C$3)) -> 0 | F7: =MAX(0,(YEAR(F5)-YEAR($C$3))*12+MONTH(F5)-MONTH($C$3)) -> 0 | G7: =MAX(0,(YEAR(G5)-YEAR($C$3))*12+MONTH(G5)-MONTH($C$3)) -> 0 | H7: =MAX(0,(YEAR(H5)-YEAR($C$3))*12+MONTH(H5)-MONTH($C$3)) -> 0 | I7: =MAX(0,(YEAR(I5)-YEAR($C$3))*12+MONTH(I5)-MONTH($C$3)) -> 1 | J7: =MAX(0,(YEAR(J5)-YEAR($C$3))*12+MONTH(J5)-MONTH($C$3)) -> 2 | ... N7: =MAX(0,(YEAR(N5)-YEAR($C$3))*12+MONTH(N5)-MONTH($C$3)) -> 6
A8: Revenue drivers
A9: Orders (no.) | B9: no. | C9: =IF(C$5<=$C$3,'Actual vs Budget'!C10,'Assumptions & Budget'!C64*(1+IF('Variance-to-Action Log'!$T$8="Reforecast",'Variance-to-Action Log'!$C$39,0))) -> 512605 | D9: =IF(D$5<=$C$3,'Actual vs Budget'!D10,'Assumptions & Budget'!D64*(1+IF('Variance-to-Action Log'!$T$8="Reforecast",'Variance-to-Action Log'!$C$39,0))) -> 504896 | E9: =IF(E$5<=$C$3,'Actual vs Budget'!E10,'Assumptions & Budget'!E64*(1+IF('Variance-to-Action Log'!$T$8="Reforecast",'Variance-to-Action Log'!$C$39,0))) -> 502172 | F9: =IF(F$5<=$C$3,'Actual vs Budget'!F10,'Assumptions & Budget'!F64*(1+IF('Variance-to-Action Log'!$T$8="Reforecast",'Variance-to-Action Log'!$C$39,0))) -> 490655 | G9: =IF(G$5<=$C$3,'Actual vs Budget'!G10,'Assumptions & Budget'!G64*(1+IF('Variance-to-Action Log'!$T$8="Reforecast",'Variance-to-Action Log'!$C$39,0))) -> 516802 | H9: =IF(H$5<=$C$3,'Actual vs Budget'!H10,'Assumptions & Budget'!H64*(1+IF('Variance-to-Action Log'!$T$8="Reforecast",'Variance-to-Action Log'!$C$39,0))) -> 545874 | I9: =IF(I$5<=$C$3,'Actual vs Budget'!I10,'Assumptions & Budget'!I64*(1+IF('Variance-to-Action Log'!$T$8="Reforecast",'Variance-to-Action Log'!$C$39,0))) -> 639817.25 | J9: =IF(J$5<=$C$3,'Actual vs Budget'!J10,'Assumptions & Budget'!J64*(1+IF('Variance-to-Action Log'!$T$8="Reforecast",'Variance-to-Action Log'!$C$39,0))) -> 613158.2 | ... N9: =IF(N$5<=$C$3,'Actual vs Budget'!N10,'Assumptions & Budget'!N64*(1+IF('Variance-to-Action Log'!$T$8="Reforecast",'Variance-to-Action Log'!$C$39,0))) -> 522517.42 | O9: =SUM($C9:$N9) -> 6448040 | P9: ='Assumptions & Budget'!O64 -> 6398172.5 | Q9: =O9-P9 -> 49867.508 | R9: =IF(P9=0,0,Q9/P9) -> 0.0077940237
A10: Net AOV (₹ per order) | B10: ₹ | C10: =IF(C$5<=$C$3,'Actual vs Budget'!C11,'Assumptions & Budget'!C65*(1+IF('Variance-to-Action Log'!$T$8="Reforecast",'Variance-to-Action Log'!$C$40,0))) -> 695.6 | D10: =IF(D$5<=$C$3,'Actual vs Budget'!D11,'Assumptions & Budget'!D65*(1+IF('Variance-to-Action Log'!$T$8="Reforecast",'Variance-to-Action Log'!$C$40,0))) -> 693.3 | E10: =IF(E$5<=$C$3,'Actual vs Budget'!E11,'Assumptions & Budget'!E65*(1+IF('Variance-to-Action Log'!$T$8="Reforecast",'Variance-to-Action Log'!$C$40,0))) -> 701.4 | F10: =IF(F$5<=$C$3,'Actual vs Budget'!F11,'Assumptions & Budget'!F65*(1+IF('Variance-to-Action Log'!$T$8="Reforecast",'Variance-to-Action Log'!$C$40,0))) -> 696 | G10: =IF(G$5<=$C$3,'Actual vs Budget'!G11,'Assumptions & Budget'!G65*(1+IF('Variance-to-Action Log'!$T$8="Reforecast",'Variance-to-Action Log'!$C$40,0))) -> 695.8 | H10: =IF(H$5<=$C$3,'Actual vs Budget'!H11,'Assumptions & Budget'!H65*(1+IF('Variance-to-Action Log'!$T$8="Reforecast",'Variance-to-Action Log'!$C$40,0))) -> 700.1 | I10: =IF(I$5<=$C$3,'Actual vs Budget'!I11,'Assumptions & Budget'!I65*(1+IF('Variance-to-Action Log'!$T$8="Reforecast",'Variance-to-Action Log'!$C$40,0))) -> 709.52278 | J10: =IF(J$5<=$C$3,'Actual vs Budget'!J11,'Assumptions & Budget'!J65*(1+IF('Variance-to-Action Log'!$T$8="Reforecast",'Variance-to-Action Log'!$C$40,0))) -> 711.65134 | ... N10: =IF(N$5<=$C$3,'Actual vs Budget'!N11,'Assumptions & Budget'!N65*(1+IF('Variance-to-Action Log'!$T$8="Reforecast",'Variance-to-Action Log'!$C$40,0))) -> 720.22967 | O10: =IF(O9=0,0,O12*100000/O9) -> 706.22818 | P10: ='Assumptions & Budget'!O65 -> 708.71315 | Q10: =O10-P10 -> -2.4849745 | R10: =IF(P10=0,0,Q10/P10) -> -0.0035063192
A11: Profit & loss (₹ lakh)
A12: Net revenue | B12: ₹ lakh | C12: =C9*C10/100000 -> 3565.6804 | D12: =D9*D10/100000 -> 3500.444 | E12: =E9*E10/100000 -> 3522.2344 | F12: =F9*F10/100000 -> 3414.9588 | G12: =G9*G10/100000 -> 3595.9083 | H12: =H9*H10/100000 -> 3821.6639 | I12: =I9*I10/100000 -> 4539.6491 | J12: =J9*J10/100000 -> 4363.5485 | ... N12: =N9*N10/100000 -> 3763.3255 | O12: =SUM($C12:$N12) -> 45537.875 | P12: ='Assumptions & Budget'!O67 -> 45344.69 | Q12: =O12-P12 -> 193.18544 | R12: =IF(P12=0,0,Q12/P12) -> 0.0042603762
A13: Cost of goods sold | B13: ₹ lakh | C13: =IF(C$5<=$C$3,'Actual vs Budget'!C14,'Assumptions & Budget'!C68*IF('Assumptions & Budget'!$E$44="Revenue",C12/'Assumptions & Budget'!C67,IF('Assumptions & Budget'!$E$44="Orders",C9/'Assumptions & Budget'!C64,1))*(1+'Variance-to-Action Log'!$V$9)+IF(AND(C$7>=1,C$7<=$F$3),'Variance-to-Action Log'!$W$9/$F$3,0)) -> 1108.3 | D13: =IF(D$5<=$C$3,'Actual vs Budget'!D14,'Assumptions & Budget'!D68*IF('Assumptions & Budget'!$E$44="Revenue",D12/'Assumptions & Budget'!D67,IF('Assumptions & Budget'!$E$44="Orders",D9/'Assumptions & Budget'!D64,1))*(1+'Variance-to-Action Log'!$V$9)+IF(AND(D$7>=1,D$7<=$F$3),'Variance-to-Action Log'!$W$9/$F$3,0)) -> 1104.5 | E13: =IF(E$5<=$C$3,'Actual vs Budget'!E14,'Assumptions & Budget'!E68*IF('Assumptions & Budget'!$E$44="Revenue",E12/'Assumptions & Budget'!E67,IF('Assumptions & Budget'!$E$44="Orders",E9/'Assumptions & Budget'!E64,1))*(1+'Variance-to-Action Log'!$V$9)+IF(AND(E$7>=1,E$7<=$F$3),'Variance-to-Action Log'!$W$9/$F$3,0)) -> 1098.1 | F13: =IF(F$5<=$C$3,'Actual vs Budget'!F14,'Assumptions & Budget'!F68*IF('Assumptions & Budget'!$E$44="Revenue",F12/'Assumptions & Budget'!F67,IF('Assumptions & Budget'!$E$44="Orders",F9/'Assumptions & Budget'!F64,1))*(1+'Variance-to-Action Log'!$V$9)+IF(AND(F$7>=1,F$7<=$F$3),'Variance-to-Action Log'!$W$9/$F$3,0)) -> 997.8 | G13: =IF(G$5<=$C$3,'Actual vs Budget'!G14,'Assumptions & Budget'!G68*IF('Assumptions & Budget'!$E$44="Revenue",G12/'Assumptions & Budget'!G67,IF('Assumptions & Budget'!$E$44="Orders",G9/'Assumptions & Budget'!G64,1))*(1+'Variance-to-Action Log'!$V$9)+IF(AND(G$7>=1,G$7<=$F$3),'Variance-to-Action Log'!$W$9/$F$3,0)) -> 1036.4 | H13: =IF(H$5<=$C$3,'Actual vs Budget'!H14,'Assumptions & Budget'!H68*IF('Assumptions & Budget'!$E$44="Revenue",H12/'Assumptions & Budget'!H67,IF('Assumptions & Budget'!$E$44="Orders",H9/'Assumptions & Budget'!H64,1))*(1+'Variance-to-Action Log'!$V$9)+IF(AND(H$7>=1,H$7<=$F$3),'Variance-to-Action Log'!$W$9/$F$3,0)) -> 1119.8 | I13: =IF(I$5<=$C$3,'Actual vs Budget'!I14,'Assumptions & Budget'!I68*IF('Assumptions & Budget'!$E$44="Revenue",I12/'Assumptions & Budget'!I67,IF('Assumptions & Budget'!$E$44="Orders",I9/'Assumptions & Budget'!I64,1))*(1+'Variance-to-Action Log'!$V$9)+IF(AND(I$7>=1,I$7<=$F$3),'Variance-to-Action Log'!$W$9/$F$3,0)) -> 1321.7643 | J13: =IF(J$5<=$C$3,'Actual vs Budget'!J14,'Assumptions & Budget'!J68*IF('Assumptions & Budget'!$E$44="Revenue",J12/'Assumptions & Budget'!J67,IF('Assumptions & Budget'!$E$44="Orders",J9/'Assumptions & Budget'!J64,1))*(1+'Variance-to-Action Log'!$V$9)+IF(AND(J$7>=1,J$7<=$F$3),'Variance-to-Action Log'!$W$9/$F$3,0)) -> 1270.4909 | ... N13: =IF(N$5<=$C$3,'Actual vs Budget'!N14,'Assumptions & Budget'!N68*IF('Assumptions & Budget'!$E$44="Revenue",N12/'Assumptions & Budget'!N67,IF('Assumptions & Budget'!$E$44="Orders",N9/'Assumptions & Budget'!N64,1))*(1+'Variance-to-Action Log'!$V$9)+IF(AND(N$7>=1,N$7<=$F$3),'Variance-to-Action Log'!$W$9/$F$3,0)) -> 1095.7299 | O13: =SUM($C13:$N13) -> 13486.802 | P13: ='Assumptions & Budget'!O68 -> 14056.854 | Q13: =P13-O13 -> 570.05173 | R13: =IF(P13=0,0,Q13/P13) -> 0.040553294
A14: Gross profit | B14: ₹ lakh | C14: =C12-C13 -> 2457.3804 | D14: =D12-D13 -> 2395.944 | E14: =E12-E13 -> 2424.1344 | F14: =F12-F13 -> 2417.1588 | G14: =G12-G13 -> 2559.5083 | H14: =H12-H13 -> 2701.8639 | I14: =I12-I13 -> 3217.8847 | J14: =J12-J13 -> 3093.0576 | ... O14: =O12-O13 -> 32051.073 | P14: ='Assumptions & Budget'!O69 -> 31287.836 | Q14: =O14-P14 -> 763.23716 | R14: =IF(P14=0,0,Q14/P14) -> 0.024394054
A15: Gross margin % | B15: % | C15: =IF(C12=0,0,C14/C12) -> 0.68917573 | D15: =IF(D12=0,0,D14/D12) -> 0.6844686 | E15: =IF(E12=0,0,E14/E12) -> 0.68823767 | F15: =IF(F12=0,0,F14/F12) -> 0.70781492 | G15: =IF(G12=0,0,G14/G12) -> 0.71178353 | H15: =IF(H12=0,0,H14/H12) -> 0.70698627 | I15: =IF(I12=0,0,I14/I12) -> 0.70883997 | J15: =IF(J12=0,0,J14/J12) -> 0.70883997 | ... O15: =IF(O12=0,0,O14/O12) -> 0.7038333 | P15: ='Assumptions & Budget'!O70 -> 0.69 | Q15: =O15-P15 -> 0.013833303
A16: Operating costs by cost centre (₹ lakh)
A17: Sales – personnel | B17: ₹ lakh | C17: =IF(C$5<=$C$3,'Actual vs Budget'!C18,'Assumptions & Budget'!C72*IF('Assumptions & Budget'!$E$45="Revenue",C12/'Assumptions & Budget'!C67,IF('Assumptions & Budget'!$E$45="Orders",C9/'Assumptions & Budget'!C64,1))*(1+'Variance-to-Action Log'!$V$10)+IF(AND(C$7>=1,C$7<=$F$3),'Variance-to-Action Log'!$W$10/$F$3,0)) -> 76.7 | D17: =IF(D$5<=$C$3,'Actual vs Budget'!D18,'Assumptions & Budget'!D72*IF('Assumptions & Budget'!$E$45="Revenue",D12/'Assumptions & Budget'!D67,IF('Assumptions & Budget'!$E$45="Orders",D9/'Assumptions & Budget'!D64,1))*(1+'Variance-to-Action Log'!$V$10)+IF(AND(D$7>=1,D$7<=$F$3),'Variance-to-Action Log'!$W$10/$F$3,0)) -> 77 | E17: =IF(E$5<=$C$3,'Actual vs Budget'!E18,'Assumptions & Budget'!E72*IF('Assumptions & Budget'!$E$45="Revenue",E12/'Assumptions & Budget'!E67,IF('Assumptions & Budget'!$E$45="Orders",E9/'Assumptions & Budget'!E64,1))*(1+'Variance-to-Action Log'!$V$10)+IF(AND(E$7>=1,E$7<=$F$3),'Variance-to-Action Log'!$W$10/$F$3,0)) -> 77.1 | F17: =IF(F$5<=$C$3,'Actual vs Budget'!F18,'Assumptions & Budget'!F72*IF('Assumptions & Budget'!$E$45="Revenue",F12/'Assumptions & Budget'!F67,IF('Assumptions & Budget'!$E$45="Orders",F9/'Assumptions & Budget'!F64,1))*(1+'Variance-to-Action Log'!$V$10)+IF(AND(F$7>=1,F$7<=$F$3),'Variance-to-Action Log'!$W$10/$F$3,0)) -> 77.5 | G17: =IF(G$5<=$C$3,'Actual vs Budget'!G18,'Assumptions & Budget'!G72*IF('Assumptions & Budget'!$E$45="Revenue",G12/'Assumptions & Budget'!G67,IF('Assumptions & Budget'!$E$45="Orders",G9/'Assumptions & Budget'!G64,1))*(1+'Variance-to-Action Log'!$V$10)+IF(AND(G$7>=1,G$7<=$F$3),'Variance-to-Action Log'!$W$10/$F$3,0)) -> 77.5 | H17: =IF(H$5<=$C$3,'Actual vs Budget'!H18,'Assumptions & Budget'!H72*IF('Assumptions & Budget'!$E$45="Revenue",H12/'Assumptions & Budget'!H67,IF('Assumptions & Budget'!$E$45="Orders",H9/'Assumptions & Budget'!H64,1))*(1+'Variance-to-Action Log'!$V$10)+IF(AND(H$7>=1,H$7<=$F$3),'Variance-to-Action Log'!$W$10/$F$3,0)) -> 80 | I17: =IF(I$5<=$C$3,'Actual vs Budget'!I18,'Assumptions & Budget'!I72*IF('Assumptions & Budget'!$E$45="Revenue",I12/'Assumptions & Budget'!I67,IF('Assumptions & Budget'!$E$45="Orders",I9/'Assumptions & Budget'!I64,1))*(1+'Variance-to-Action Log'!$V$10)+IF(AND(I$7>=1,I$7<=$F$3),'Variance-to-Action Log'!$W$10/$F$3,0)) -> 80.054945 | J17: =IF(J$5<=$C$3,'Actual vs Budget'!J18,'Assumptions & Budget'!J72*IF('Assumptions & Budget'!$E$45="Revenue",J12/'Assumptions & Budget'!J67,IF('Assumptions & Budget'!$E$45="Orders",J9/'Assumptions & Budget'!J64,1))*(1+'Variance-to-Action Log'!$V$10)+IF(AND(J$7>=1,J$7<=$F$3),'Variance-to-Action Log'!$W$10/$F$3,0)) -> 80.054945 | ... N17: =IF(N$5<=$C$3,'Actual vs Budget'!N18,'Assumptions & Budget'!N72*IF('Assumptions & Budget'!$E$45="Revenue",N12/'Assumptions & Budget'!N67,IF('Assumptions & Budget'!$E$45="Orders",N9/'Assumptions & Budget'!N64,1))*(1+'Variance-to-Action Log'!$V$10)+IF(AND(N$7>=1,N$7<=$F$3),'Variance-to-Action Log'!$W$10/$F$3,0)) -> 81.346154 | O17: =SUM($C17:$N17) -> 950.0033 | P17: ='Assumptions & Budget'!O72 -> 874.66666 | Q17: =P17-O17 -> -75.336637 | R17: =IF(P17=0,0,Q17/P17) -> -0.086131827
A18: Sales – marketplace & payment fees | B18: ₹ lakh | C18: =IF(C$5<=$C$3,'Actual vs Budget'!C19,'Assumptions & Budget'!C73*IF('Assumptions & Budget'!$E$46="Revenue",C12/'Assumptions & Budget'!C67,IF('Assumptions & Budget'!$E$46="Orders",C9/'Assumptions & Budget'!C64,1))*(1+'Variance-to-Action Log'!$V$11)+IF(AND(C$7>=1,C$7<=$F$3),'Variance-to-Action Log'!$W$11/$F$3,0)) -> 105.7 | D18: =IF(D$5<=$C$3,'Actual vs Budget'!D19,'Assumptions & Budget'!D73*IF('Assumptions & Budget'!$E$46="Revenue",D12/'Assumptions & Budget'!D67,IF('Assumptions & Budget'!$E$46="Orders",D9/'Assumptions & Budget'!D64,1))*(1+'Variance-to-Action Log'!$V$11)+IF(AND(D$7>=1,D$7<=$F$3),'Variance-to-Action Log'!$W$11/$F$3,0)) -> 101.5 | E18: =IF(E$5<=$C$3,'Actual vs Budget'!E19,'Assumptions & Budget'!E73*IF('Assumptions & Budget'!$E$46="Revenue",E12/'Assumptions & Budget'!E67,IF('Assumptions & Budget'!$E$46="Orders",E9/'Assumptions & Budget'!E64,1))*(1+'Variance-to-Action Log'!$V$11)+IF(AND(E$7>=1,E$7<=$F$3),'Variance-to-Action Log'!$W$11/$F$3,0)) -> 106 | F18: =IF(F$5<=$C$3,'Actual vs Budget'!F19,'Assumptions & Budget'!F73*IF('Assumptions & Budget'!$E$46="Revenue",F12/'Assumptions & Budget'!F67,IF('Assumptions & Budget'!$E$46="Orders",F9/'Assumptions & Budget'!F64,1))*(1+'Variance-to-Action Log'!$V$11)+IF(AND(F$7>=1,F$7<=$F$3),'Variance-to-Action Log'!$W$11/$F$3,0)) -> 120 | G18: =IF(G$5<=$C$3,'Actual vs Budget'!G19,'Assumptions & Budget'!G73*IF('Assumptions & Budget'!$E$46="Revenue",G12/'Assumptions & Budget'!G67,IF('Assumptions & Budget'!$E$46="Orders",G9/'Assumptions & Budget'!G64,1))*(1+'Variance-to-Action Log'!$V$11)+IF(AND(G$7>=1,G$7<=$F$3),'Variance-to-Action Log'!$W$11/$F$3,0)) -> 121.3 | H18: =IF(H$5<=$C$3,'Actual vs Budget'!H19,'Assumptions & Budget'!H73*IF('Assumptions & Budget'!$E$46="Revenue",H12/'Assumptions & Budget'!H67,IF('Assumptions & Budget'!$E$46="Orders",H9/'Assumptions & Budget'!H64,1))*(1+'Variance-to-Action Log'!$V$11)+IF(AND(H$7>=1,H$7<=$F$3),'Variance-to-Action Log'!$W$11/$F$3,0)) -> 129.9 | I18: =IF(I$5<=$C$3,'Actual vs Budget'!I19,'Assumptions & Budget'!I73*IF('Assumptions & Budget'!$E$46="Revenue",I12/'Assumptions & Budget'!I67,IF('Assumptions & Budget'!$E$46="Orders",I9/'Assumptions & Budget'!I64,1))*(1+'Variance-to-Action Log'!$V$11)+IF(AND(I$7>=1,I$7<=$F$3),'Variance-to-Action Log'!$W$11/$F$3,0)) -> 155.56085 | J18: =IF(J$5<=$C$3,'Actual vs Budget'!J19,'Assumptions & Budget'!J73*IF('Assumptions & Budget'!$E$46="Revenue",J12/'Assumptions & Budget'!J67,IF('Assumptions & Budget'!$E$46="Orders",J9/'Assumptions & Budget'!J64,1))*(1+'Variance-to-Action Log'!$V$11)+IF(AND(J$7>=1,J$7<=$F$3),'Variance-to-Action Log'!$W$11/$F$3,0)) -> 149.52639 | ... N18: =IF(N$5<=$C$3,'Actual vs Budget'!N19,'Assumptions & Budget'!N73*IF('Assumptions & Budget'!$E$46="Revenue",N12/'Assumptions & Budget'!N67,IF('Assumptions & Budget'!$E$46="Orders",N9/'Assumptions & Budget'!N64,1))*(1+'Variance-to-Action Log'!$V$11)+IF(AND(N$7>=1,N$7<=$F$3),'Variance-to-Action Log'!$W$11/$F$3,0)) -> 128.95845 | O18: =SUM($C18:$N18) -> 1510.8204 | P18: ='Assumptions & Budget'!O73 -> 1360.3407 | Q18: =P18-O18 -> -150.47974 | R18: =IF(P18=0,0,Q18/P18) -> -0.11061916
A19: Sales – total | B19: ₹ lakh | C19: =C17+C18 -> 182.4 | D19: =D17+D18 -> 178.5 | E19: =E17+E18 -> 183.1 | F19: =F17+F18 -> 197.5 | G19: =G17+G18 -> 198.8 | H19: =H17+H18 -> 209.9 | I19: =I17+I18 -> 235.6158 | J19: =J17+J18 -> 229.58133 | ... O19: =O17+O18 -> 2460.8237 | P19: ='Assumptions & Budget'!O74 -> 2235.0074 | Q19: =P19-O19 -> -225.81638 | R19: =IF(P19=0,0,Q19/P19) -> -0.10103608
A20: Operations – personnel | B20: ₹ lakh | C20: =IF(C$5<=$C$3,'Actual vs Budget'!C21,'Assumptions & Budget'!C75*IF('Assumptions & Budget'!$E$47="Revenue",C12/'Assumptions & Budget'!C67,IF('Assumptions & Budget'!$E$47="Orders",C9/'Assumptions & Budget'!C64,1))*(1+'Variance-to-Action Log'!$V$12)+IF(AND(C$7>=1,C$7<=$F$3),'Variance-to-Action Log'!$W$12/$F$3,0)) -> 100.1 | D20: =IF(D$5<=$C$3,'Actual vs Budget'!D21,'Assumptions & Budget'!D75*IF('Assumptions & Budget'!$E$47="Revenue",D12/'Assumptions & Budget'!D67,IF('Assumptions & Budget'!$E$47="Orders",D9/'Assumptions & Budget'!D64,1))*(1+'Variance-to-Action Log'!$V$12)+IF(AND(D$7>=1,D$7<=$F$3),'Variance-to-Action Log'!$W$12/$F$3,0)) -> 101.2 | E20: =IF(E$5<=$C$3,'Actual vs Budget'!E21,'Assumptions & Budget'!E75*IF('Assumptions & Budget'!$E$47="Revenue",E12/'Assumptions & Budget'!E67,IF('Assumptions & Budget'!$E$47="Orders",E9/'Assumptions & Budget'!E64,1))*(1+'Variance-to-Action Log'!$V$12)+IF(AND(E$7>=1,E$7<=$F$3),'Variance-to-Action Log'!$W$12/$F$3,0)) -> 101 | F20: =IF(F$5<=$C$3,'Actual vs Budget'!F21,'Assumptions & Budget'!F75*IF('Assumptions & Budget'!$E$47="Revenue",F12/'Assumptions & Budget'!F67,IF('Assumptions & Budget'!$E$47="Orders",F9/'Assumptions & Budget'!F64,1))*(1+'Variance-to-Action Log'!$V$12)+IF(AND(F$7>=1,F$7<=$F$3),'Variance-to-Action Log'!$W$12/$F$3,0)) -> 100.4 | G20: =IF(G$5<=$C$3,'Actual vs Budget'!G21,'Assumptions & Budget'!G75*IF('Assumptions & Budget'!$E$47="Revenue",G12/'Assumptions & Budget'!G67,IF('Assumptions & Budget'!$E$47="Orders",G9/'Assumptions & Budget'!G64,1))*(1+'Variance-to-Action Log'!$V$12)+IF(AND(G$7>=1,G$7<=$F$3),'Variance-to-Action Log'!$W$12/$F$3,0)) -> 100.6 | H20: =IF(H$5<=$C$3,'Actual vs Budget'!H21,'Assumptions & Budget'!H75*IF('Assumptions & Budget'!$E$47="Revenue",H12/'Assumptions & Budget'!H67,IF('Assumptions & Budget'!$E$47="Orders",H9/'Assumptions & Budget'!H64,1))*(1+'Variance-to-Action Log'!$V$12)+IF(AND(H$7>=1,H$7<=$F$3),'Variance-to-Action Log'!$W$12/$F$3,0)) -> 101.4 | I20: =IF(I$5<=$C$3,'Actual vs Budget'!I21,'Assumptions & Budget'!I75*IF('Assumptions & Budget'!$E$47="Revenue",I12/'Assumptions & Budget'!I67,IF('Assumptions & Budget'!$E$47="Orders",I9/'Assumptions & Budget'!I64,1))*(1+'Variance-to-Action Log'!$V$12)+IF(AND(I$7>=1,I$7<=$F$3),'Variance-to-Action Log'!$W$12/$F$3,0)) -> 100.93289 | J20: =IF(J$5<=$C$3,'Actual vs Budget'!J21,'Assumptions & Budget'!J75*IF('Assumptions & Budget'!$E$47="Revenue",J12/'Assumptions & Budget'!J67,IF('Assumptions & Budget'!$E$47="Orders",J9/'Assumptions & Budget'!J64,1))*(1+'Variance-to-Action Log'!$V$12)+IF(AND(J$7>=1,J$7<=$F$3),'Variance-to-Action Log'!$W$12/$F$3,0)) -> 100.93289 | ... N20: =IF(N$5<=$C$3,'Actual vs Budget'!N21,'Assumptions & Budget'!N75*IF('Assumptions & Budget'!$E$47="Revenue",N12/'Assumptions & Budget'!N67,IF('Assumptions & Budget'!$E$47="Orders",N9/'Assumptions & Budget'!N64,1))*(1+'Variance-to-Action Log'!$V$12)+IF(AND(N$7>=1,N$7<=$F$3),'Variance-to-Action Log'!$W$12/$F$3,0)) -> 103.62443 | O20: =SUM($C20:$N20) -> 1221.0635 | P20: ='Assumptions & Budget'!O75 -> 1221.9608 | Q20: =P20-O20 -> 0.89731544 | R20: =IF(P20=0,0,Q20/P20) -> 0.00073432424
A21: Operations – fulfilment & logistics | B21: ₹ lakh | C21: =IF(C$5<=$C$3,'Actual vs Budget'!C22,'Assumptions & Budget'!C76*IF('Assumptions & Budget'!$E$48="Revenue",C12/'Assumptions & Budget'!C67,IF('Assumptions & Budget'!$E$48="Orders",C9/'Assumptions & Budget'!C64,1))*(1+'Variance-to-Action Log'!$V$13)+IF(AND(C$7>=1,C$7<=$F$3),'Variance-to-Action Log'!$W$13/$F$3,0)) -> 270.4 | D21: =IF(D$5<=$C$3,'Actual vs Budget'!D22,'Assumptions & Budget'!D76*IF('Assumptions & Budget'!$E$48="Revenue",D12/'Assumptions & Budget'!D67,IF('Assumptions & Budget'!$E$48="Orders",D9/'Assumptions & Budget'!D64,1))*(1+'Variance-to-Action Log'!$V$13)+IF(AND(D$7>=1,D$7<=$F$3),'Variance-to-Action Log'!$W$13/$F$3,0)) -> 266.5 | E21: =IF(E$5<=$C$3,'Actual vs Budget'!E22,'Assumptions & Budget'!E76*IF('Assumptions & Budget'!$E$48="Revenue",E12/'Assumptions & Budget'!E67,IF('Assumptions & Budget'!$E$48="Orders",E9/'Assumptions & Budget'!E64,1))*(1+'Variance-to-Action Log'!$V$13)+IF(AND(E$7>=1,E$7<=$F$3),'Variance-to-Action Log'!$W$13/$F$3,0)) -> 282.5 | F21: =IF(F$5<=$C$3,'Actual vs Budget'!F22,'Assumptions & Budget'!F76*IF('Assumptions & Budget'!$E$48="Revenue",F12/'Assumptions & Budget'!F67,IF('Assumptions & Budget'!$E$48="Orders",F9/'Assumptions & Budget'!F64,1))*(1+'Variance-to-Action Log'!$V$13)+IF(AND(F$7>=1,F$7<=$F$3),'Variance-to-Action Log'!$W$13/$F$3,0)) -> 279.7 | G21: =IF(G$5<=$C$3,'Actual vs Budget'!G22,'Assumptions & Budget'!G76*IF('Assumptions & Budget'!$E$48="Revenue",G12/'Assumptions & Budget'!G67,IF('Assumptions & Budget'!$E$48="Orders",G9/'Assumptions & Budget'!G64,1))*(1+'Variance-to-Action Log'!$V$13)+IF(AND(G$7>=1,G$7<=$F$3),'Variance-to-Action Log'!$W$13/$F$3,0)) -> 293.4 | H21: =IF(H$5<=$C$3,'Actual vs Budget'!H22,'Assumptions & Budget'!H76*IF('Assumptions & Budget'!$E$48="Revenue",H12/'Assumptions & Budget'!H67,IF('Assumptions & Budget'!$E$48="Orders",H9/'Assumptions & Budget'!H64,1))*(1+'Variance-to-Action Log'!$V$13)+IF(AND(H$7>=1,H$7<=$F$3),'Variance-to-Action Log'!$W$13/$F$3,0)) -> 306.9 | I21: =IF(I$5<=$C$3,'Actual vs Budget'!I22,'Assumptions & Budget'!I76*IF('Assumptions & Budget'!$E$48="Revenue",I12/'Assumptions & Budget'!I67,IF('Assumptions & Budget'!$E$48="Orders",I9/'Assumptions & Budget'!I64,1))*(1+'Variance-to-Action Log'!$V$13)+IF(AND(I$7>=1,I$7<=$F$3),'Variance-to-Action Log'!$W$13/$F$3,0)) -> 362.47212 | J21: =IF(J$5<=$C$3,'Actual vs Budget'!J22,'Assumptions & Budget'!J76*IF('Assumptions & Budget'!$E$48="Revenue",J12/'Assumptions & Budget'!J67,IF('Assumptions & Budget'!$E$48="Orders",J9/'Assumptions & Budget'!J64,1))*(1+'Variance-to-Action Log'!$V$13)+IF(AND(J$7>=1,J$7<=$F$3),'Variance-to-Action Log'!$W$13/$F$3,0)) -> 347.36911 | ... N21: =IF(N$5<=$C$3,'Actual vs Budget'!N22,'Assumptions & Budget'!N76*IF('Assumptions & Budget'!$E$48="Revenue",N12/'Assumptions & Budget'!N67,IF('Assumptions & Budget'!$E$48="Orders",N9/'Assumptions & Budget'!N64,1))*(1+'Variance-to-Action Log'!$V$13)+IF(AND(N$7>=1,N$7<=$F$3),'Variance-to-Action Log'!$W$13/$F$3,0)) -> 296.0189 | O21: =SUM($C21:$N21) -> 3611.4404 | P21: ='Assumptions & Budget'!O76 -> 3339.736 | Q21: =P21-O21 -> -271.7044 | R21: =IF(P21=0,0,Q21/P21) -> -0.081355053
A22: Operations – warehouse, QC & other | B22: ₹ lakh | C22: =IF(C$5<=$C$3,'Actual vs Budget'!C23,'Assumptions & Budget'!C77*IF('Assumptions & Budget'!$E$49="Revenue",C12/'Assumptions & Budget'!C67,IF('Assumptions & Budget'!$E$49="Orders",C9/'Assumptions & Budget'!C64,1))*(1+'Variance-to-Action Log'!$V$14)+IF(AND(C$7>=1,C$7<=$F$3),'Variance-to-Action Log'!$W$14/$F$3,0)) -> 35.7 | D22: =IF(D$5<=$C$3,'Actual vs Budget'!D23,'Assumptions & Budget'!D77*IF('Assumptions & Budget'!$E$49="Revenue",D12/'Assumptions & Budget'!D67,IF('Assumptions & Budget'!$E$49="Orders",D9/'Assumptions & Budget'!D64,1))*(1+'Variance-to-Action Log'!$V$14)+IF(AND(D$7>=1,D$7<=$F$3),'Variance-to-Action Log'!$W$14/$F$3,0)) -> 34.1 | E22: =IF(E$5<=$C$3,'Actual vs Budget'!E23,'Assumptions & Budget'!E77*IF('Assumptions & Budget'!$E$49="Revenue",E12/'Assumptions & Budget'!E67,IF('Assumptions & Budget'!$E$49="Orders",E9/'Assumptions & Budget'!E64,1))*(1+'Variance-to-Action Log'!$V$14)+IF(AND(E$7>=1,E$7<=$F$3),'Variance-to-Action Log'!$W$14/$F$3,0)) -> 34.4 | F22: =IF(F$5<=$C$3,'Actual vs Budget'!F23,'Assumptions & Budget'!F77*IF('Assumptions & Budget'!$E$49="Revenue",F12/'Assumptions & Budget'!F67,IF('Assumptions & Budget'!$E$49="Orders",F9/'Assumptions & Budget'!F64,1))*(1+'Variance-to-Action Log'!$V$14)+IF(AND(F$7>=1,F$7<=$F$3),'Variance-to-Action Log'!$W$14/$F$3,0)) -> 103.8 | G22: =IF(G$5<=$C$3,'Actual vs Budget'!G23,'Assumptions & Budget'!G77*IF('Assumptions & Budget'!$E$49="Revenue",G12/'Assumptions & Budget'!G67,IF('Assumptions & Budget'!$E$49="Orders",G9/'Assumptions & Budget'!G64,1))*(1+'Variance-to-Action Log'!$V$14)+IF(AND(G$7>=1,G$7<=$F$3),'Variance-to-Action Log'!$W$14/$F$3,0)) -> 35.9 | H22: =IF(H$5<=$C$3,'Actual vs Budget'!H23,'Assumptions & Budget'!H77*IF('Assumptions & Budget'!$E$49="Revenue",H12/'Assumptions & Budget'!H67,IF('Assumptions & Budget'!$E$49="Orders",H9/'Assumptions & Budget'!H64,1))*(1+'Variance-to-Action Log'!$V$14)+IF(AND(H$7>=1,H$7<=$F$3),'Variance-to-Action Log'!$W$14/$F$3,0)) -> 34.7 | I22: =IF(I$5<=$C$3,'Actual vs Budget'!I23,'Assumptions & Budget'!I77*IF('Assumptions & Budget'!$E$49="Revenue",I12/'Assumptions & Budget'!I67,IF('Assumptions & Budget'!$E$49="Orders",I9/'Assumptions & Budget'!I64,1))*(1+'Variance-to-Action Log'!$V$14)+IF(AND(I$7>=1,I$7<=$F$3),'Variance-to-Action Log'!$W$14/$F$3,0)) -> 34.3175 | J22: =IF(J$5<=$C$3,'Actual vs Budget'!J23,'Assumptions & Budget'!J77*IF('Assumptions & Budget'!$E$49="Revenue",J12/'Assumptions & Budget'!J67,IF('Assumptions & Budget'!$E$49="Orders",J9/'Assumptions & Budget'!J64,1))*(1+'Variance-to-Action Log'!$V$14)+IF(AND(J$7>=1,J$7<=$F$3),'Variance-to-Action Log'!$W$14/$F$3,0)) -> 34.3175 | ... N22: =IF(N$5<=$C$3,'Actual vs Budget'!N23,'Assumptions & Budget'!N77*IF('Assumptions & Budget'!$E$49="Revenue",N12/'Assumptions & Budget'!N67,IF('Assumptions & Budget'!$E$49="Orders",N9/'Assumptions & Budget'!N64,1))*(1+'Variance-to-Action Log'!$V$14)+IF(AND(N$7>=1,N$7<=$F$3),'Variance-to-Action Log'!$W$14/$F$3,0)) -> 34.3175 | O22: =SUM($C22:$N22) -> 484.505 | P22: ='Assumptions & Budget'!O77 -> 411.81 | Q22: =P22-O22 -> -72.695 | R22: =IF(P22=0,0,Q22/P22) -> -0.17652558
A23: Operations – total | B23: ₹ lakh | C23: =C20+C21+C22 -> 406.2 | D23: =D20+D21+D22 -> 401.8 | E23: =E20+E21+E22 -> 417.9 | F23: =F20+F21+F22 -> 483.9 | G23: =G20+G21+G22 -> 429.9 | H23: =H20+H21+H22 -> 443 | I23: =I20+I21+I22 -> 497.7225 | J23: =J20+J21+J22 -> 482.6195 | ... O23: =O20+O21+O22 -> 5317.0089 | P23: ='Assumptions & Budget'!O78 -> 4973.5068 | Q23: =P23-O23 -> -343.50209 | R23: =IF(P23=0,0,Q23/P23) -> -0.069066375
A24: Marketing – personnel | B24: ₹ lakh | C24: =IF(C$5<=$C$3,'Actual vs Budget'!C25,'Assumptions & Budget'!C79*IF('Assumptions & Budget'!$E$50="Revenue",C12/'Assumptions & Budget'!C67,IF('Assumptions & Budget'!$E$50="Orders",C9/'Assumptions & Budget'!C64,1))*(1+'Variance-to-Action Log'!$V$15)+IF(AND(C$7>=1,C$7<=$F$3),'Variance-to-Action Log'!$W$15/$F$3,0)) -> 90.7 | D24: =IF(D$5<=$C$3,'Actual vs Budget'!D25,'Assumptions & Budget'!D79*IF('Assumptions & Budget'!$E$50="Revenue",D12/'Assumptions & Budget'!D67,IF('Assumptions & Budget'!$E$50="Orders",D9/'Assumptions & Budget'!D64,1))*(1+'Variance-to-Action Log'!$V$15)+IF(AND(D$7>=1,D$7<=$F$3),'Variance-to-Action Log'!$W$15/$F$3,0)) -> 89.2 | E24: =IF(E$5<=$C$3,'Actual vs Budget'!E25,'Assumptions & Budget'!E79*IF('Assumptions & Budget'!$E$50="Revenue",E12/'Assumptions & Budget'!E67,IF('Assumptions & Budget'!$E$50="Orders",E9/'Assumptions & Budget'!E64,1))*(1+'Variance-to-Action Log'!$V$15)+IF(AND(E$7>=1,E$7<=$F$3),'Variance-to-Action Log'!$W$15/$F$3,0)) -> 92 | F24: =IF(F$5<=$C$3,'Actual vs Budget'!F25,'Assumptions & Budget'!F79*IF('Assumptions & Budget'!$E$50="Revenue",F12/'Assumptions & Budget'!F67,IF('Assumptions & Budget'!$E$50="Orders",F9/'Assumptions & Budget'!F64,1))*(1+'Variance-to-Action Log'!$V$15)+IF(AND(F$7>=1,F$7<=$F$3),'Variance-to-Action Log'!$W$15/$F$3,0)) -> 93.9 | G24: =IF(G$5<=$C$3,'Actual vs Budget'!G25,'Assumptions & Budget'!G79*IF('Assumptions & Budget'!$E$50="Revenue",G12/'Assumptions & Budget'!G67,IF('Assumptions & Budget'!$E$50="Orders",G9/'Assumptions & Budget'!G64,1))*(1+'Variance-to-Action Log'!$V$15)+IF(AND(G$7>=1,G$7<=$F$3),'Variance-to-Action Log'!$W$15/$F$3,0)) -> 93.5 | H24: =IF(H$5<=$C$3,'Actual vs Budget'!H25,'Assumptions & Budget'!H79*IF('Assumptions & Budget'!$E$50="Revenue",H12/'Assumptions & Budget'!H67,IF('Assumptions & Budget'!$E$50="Orders",H9/'Assumptions & Budget'!H64,1))*(1+'Variance-to-Action Log'!$V$15)+IF(AND(H$7>=1,H$7<=$F$3),'Variance-to-Action Log'!$W$15/$F$3,0)) -> 92.6 | I24: =IF(I$5<=$C$3,'Actual vs Budget'!I25,'Assumptions & Budget'!I79*IF('Assumptions & Budget'!$E$50="Revenue",I12/'Assumptions & Budget'!I67,IF('Assumptions & Budget'!$E$50="Orders",I9/'Assumptions & Budget'!I64,1))*(1+'Variance-to-Action Log'!$V$15)+IF(AND(I$7>=1,I$7<=$F$3),'Variance-to-Action Log'!$W$15/$F$3,0)) -> 93.844206 | J24: =IF(J$5<=$C$3,'Actual vs Budget'!J25,'Assumptions & Budget'!J79*IF('Assumptions & Budget'!$E$50="Revenue",J12/'Assumptions & Budget'!J67,IF('Assumptions & Budget'!$E$50="Orders",J9/'Assumptions & Budget'!J64,1))*(1+'Variance-to-Action Log'!$V$15)+IF(AND(J$7>=1,J$7<=$F$3),'Variance-to-Action Log'!$W$15/$F$3,0)) -> 93.844206 | ... N24: =IF(N$5<=$C$3,'Actual vs Budget'!N25,'Assumptions & Budget'!N79*IF('Assumptions & Budget'!$E$50="Revenue",N12/'Assumptions & Budget'!N67,IF('Assumptions & Budget'!$E$50="Orders",N9/'Assumptions & Budget'!N64,1))*(1+'Variance-to-Action Log'!$V$15)+IF(AND(N$7>=1,N$7<=$F$3),'Variance-to-Action Log'!$W$15/$F$3,0)) -> 93.844206 | O24: =SUM($C24:$N24) -> 1114.9652 | P24: ='Assumptions & Budget'!O79 -> 1117.7265 | Q24: =P24-O24 -> 2.7612784 | R24: =IF(P24=0,0,Q24/P24) -> 0.0024704418
A25: Marketing – performance marketing | B25: ₹ lakh | C25: =IF(C$5<=$C$3,'Actual vs Budget'!C26,'Assumptions & Budget'!C80*IF('Assumptions & Budget'!$E$51="Revenue",C12/'Assumptions & Budget'!C67,IF('Assumptions & Budget'!$E$51="Orders",C9/'Assumptions & Budget'!C64,1))*(1+'Variance-to-Action Log'!$V$16)+IF(AND(C$7>=1,C$7<=$F$3),'Variance-to-Action Log'!$W$16/$F$3,0)) -> 757.8 | D25: =IF(D$5<=$C$3,'Actual vs Budget'!D26,'Assumptions & Budget'!D80*IF('Assumptions & Budget'!$E$51="Revenue",D12/'Assumptions & Budget'!D67,IF('Assumptions & Budget'!$E$51="Orders",D9/'Assumptions & Budget'!D64,1))*(1+'Variance-to-Action Log'!$V$16)+IF(AND(D$7>=1,D$7<=$F$3),'Variance-to-Action Log'!$W$16/$F$3,0)) -> 745.1 | E25: =IF(E$5<=$C$3,'Actual vs Budget'!E26,'Assumptions & Budget'!E80*IF('Assumptions & Budget'!$E$51="Revenue",E12/'Assumptions & Budget'!E67,IF('Assumptions & Budget'!$E$51="Orders",E9/'Assumptions & Budget'!E64,1))*(1+'Variance-to-Action Log'!$V$16)+IF(AND(E$7>=1,E$7<=$F$3),'Variance-to-Action Log'!$W$16/$F$3,0)) -> 735.5 | F25: =IF(F$5<=$C$3,'Actual vs Budget'!F26,'Assumptions & Budget'!F80*IF('Assumptions & Budget'!$E$51="Revenue",F12/'Assumptions & Budget'!F67,IF('Assumptions & Budget'!$E$51="Orders",F9/'Assumptions & Budget'!F64,1))*(1+'Variance-to-Action Log'!$V$16)+IF(AND(F$7>=1,F$7<=$F$3),'Variance-to-Action Log'!$W$16/$F$3,0)) -> 718 | G25: =IF(G$5<=$C$3,'Actual vs Budget'!G26,'Assumptions & Budget'!G80*IF('Assumptions & Budget'!$E$51="Revenue",G12/'Assumptions & Budget'!G67,IF('Assumptions & Budget'!$E$51="Orders",G9/'Assumptions & Budget'!G64,1))*(1+'Variance-to-Action Log'!$V$16)+IF(AND(G$7>=1,G$7<=$F$3),'Variance-to-Action Log'!$W$16/$F$3,0)) -> 830.3 | H25: =IF(H$5<=$C$3,'Actual vs Budget'!H26,'Assumptions & Budget'!H80*IF('Assumptions & Budget'!$E$51="Revenue",H12/'Assumptions & Budget'!H67,IF('Assumptions & Budget'!$E$51="Orders",H9/'Assumptions & Budget'!H64,1))*(1+'Variance-to-Action Log'!$V$16)+IF(AND(H$7>=1,H$7<=$F$3),'Variance-to-Action Log'!$W$16/$F$3,0)) -> 948.7 | I25: =IF(I$5<=$C$3,'Actual vs Budget'!I26,'Assumptions & Budget'!I80*IF('Assumptions & Budget'!$E$51="Revenue",I12/'Assumptions & Budget'!I67,IF('Assumptions & Budget'!$E$51="Orders",I9/'Assumptions & Budget'!I64,1))*(1+'Variance-to-Action Log'!$V$16)+IF(AND(I$7>=1,I$7<=$F$3),'Variance-to-Action Log'!$W$16/$F$3,0)) -> 890.30277 | J25: =IF(J$5<=$C$3,'Actual vs Budget'!J26,'Assumptions & Budget'!J80*IF('Assumptions & Budget'!$E$51="Revenue",J12/'Assumptions & Budget'!J67,IF('Assumptions & Budget'!$E$51="Orders",J9/'Assumptions & Budget'!J64,1))*(1+'Variance-to-Action Log'!$V$16)+IF(AND(J$7>=1,J$7<=$F$3),'Variance-to-Action Log'!$W$16/$F$3,0)) -> 852.44115 | ... N25: =IF(N$5<=$C$3,'Actual vs Budget'!N26,'Assumptions & Budget'!N80*IF('Assumptions & Budget'!$E$51="Revenue",N12/'Assumptions & Budget'!N67,IF('Assumptions & Budget'!$E$51="Orders",N9/'Assumptions & Budget'!N64,1))*(1+'Variance-to-Action Log'!$V$16)+IF(AND(N$7>=1,N$7<=$F$3),'Variance-to-Action Log'!$W$16/$F$3,0)) -> 809.11497 | O25: =SUM($C25:$N25) -> 9749.1083 | P25: ='Assumptions & Budget'!O80 -> 9749.1083 | Q25: =P25-O25 -> 0 | R25: =IF(P25=0,0,Q25/P25) -> 0
A26: Marketing – brand & influencer | B26: ₹ lakh | C26: =IF(C$5<=$C$3,'Actual vs Budget'!C27,'Assumptions & Budget'!C81*IF('Assumptions & Budget'!$E$52="Revenue",C12/'Assumptions & Budget'!C67,IF('Assumptions & Budget'!$E$52="Orders",C9/'Assumptions & Budget'!C64,1))*(1+'Variance-to-Action Log'!$V$17)+IF(AND(C$7>=1,C$7<=$F$3),'Variance-to-Action Log'!$W$17/$F$3,0)) -> 360.1 | D26: =IF(D$5<=$C$3,'Actual vs Budget'!D27,'Assumptions & Budget'!D81*IF('Assumptions & Budget'!$E$52="Revenue",D12/'Assumptions & Budget'!D67,IF('Assumptions & Budget'!$E$52="Orders",D9/'Assumptions & Budget'!D64,1))*(1+'Variance-to-Action Log'!$V$17)+IF(AND(D$7>=1,D$7<=$F$3),'Variance-to-Action Log'!$W$17/$F$3,0)) -> 349.7 | E26: =IF(E$5<=$C$3,'Actual vs Budget'!E27,'Assumptions & Budget'!E81*IF('Assumptions & Budget'!$E$52="Revenue",E12/'Assumptions & Budget'!E67,IF('Assumptions & Budget'!$E$52="Orders",E9/'Assumptions & Budget'!E64,1))*(1+'Variance-to-Action Log'!$V$17)+IF(AND(E$7>=1,E$7<=$F$3),'Variance-to-Action Log'!$W$17/$F$3,0)) -> 401.3 | F26: =IF(F$5<=$C$3,'Actual vs Budget'!F27,'Assumptions & Budget'!F81*IF('Assumptions & Budget'!$E$52="Revenue",F12/'Assumptions & Budget'!F67,IF('Assumptions & Budget'!$E$52="Orders",F9/'Assumptions & Budget'!F64,1))*(1+'Variance-to-Action Log'!$V$17)+IF(AND(F$7>=1,F$7<=$F$3),'Variance-to-Action Log'!$W$17/$F$3,0)) -> 378 | G26: =IF(G$5<=$C$3,'Actual vs Budget'!G27,'Assumptions & Budget'!G81*IF('Assumptions & Budget'!$E$52="Revenue",G12/'Assumptions & Budget'!G67,IF('Assumptions & Budget'!$E$52="Orders",G9/'Assumptions & Budget'!G64,1))*(1+'Variance-to-Action Log'!$V$17)+IF(AND(G$7>=1,G$7<=$F$3),'Variance-to-Action Log'!$W$17/$F$3,0)) -> 405.6 | H26: =IF(H$5<=$C$3,'Actual vs Budget'!H27,'Assumptions & Budget'!H81*IF('Assumptions & Budget'!$E$52="Revenue",H12/'Assumptions & Budget'!H67,IF('Assumptions & Budget'!$E$52="Orders",H9/'Assumptions & Budget'!H64,1))*(1+'Variance-to-Action Log'!$V$17)+IF(AND(H$7>=1,H$7<=$F$3),'Variance-to-Action Log'!$W$17/$F$3,0)) -> 425.4 | I26: =IF(I$5<=$C$3,'Actual vs Budget'!I27,'Assumptions & Budget'!I81*IF('Assumptions & Budget'!$E$52="Revenue",I12/'Assumptions & Budget'!I67,IF('Assumptions & Budget'!$E$52="Orders",I9/'Assumptions & Budget'!I64,1))*(1+'Variance-to-Action Log'!$V$17)+IF(AND(I$7>=1,I$7<=$F$3),'Variance-to-Action Log'!$W$17/$F$3,0)) -> 483.01054 | J26: =IF(J$5<=$C$3,'Actual vs Budget'!J27,'Assumptions & Budget'!J81*IF('Assumptions & Budget'!$E$52="Revenue",J12/'Assumptions & Budget'!J67,IF('Assumptions & Budget'!$E$52="Orders",J9/'Assumptions & Budget'!J64,1))*(1+'Variance-to-Action Log'!$V$17)+IF(AND(J$7>=1,J$7<=$F$3),'Variance-to-Action Log'!$W$17/$F$3,0)) -> 464.27376 | ... N26: =IF(N$5<=$C$3,'Actual vs Budget'!N27,'Assumptions & Budget'!N81*IF('Assumptions & Budget'!$E$52="Revenue",N12/'Assumptions & Budget'!N67,IF('Assumptions & Budget'!$E$52="Orders",N9/'Assumptions & Budget'!N64,1))*(1+'Variance-to-Action Log'!$V$17)+IF(AND(N$7>=1,N$7<=$F$3),'Variance-to-Action Log'!$W$17/$F$3,0)) -> 400.4111 | O26: =SUM($C26:$N26) -> 4886.1041 | P26: ='Assumptions & Budget'!O81 -> 4534.469 | Q26: =P26-O26 -> -351.63514 | R26: =IF(P26=0,0,Q26/P26) -> -0.077547148
A27: Marketing – total | B27: ₹ lakh | C27: =C24+C25+C26 -> 1208.6 | D27: =D24+D25+D26 -> 1184 | E27: =E24+E25+E26 -> 1228.8 | F27: =F24+F25+F26 -> 1189.9 | G27: =G24+G25+G26 -> 1329.4 | H27: =H24+H25+H26 -> 1466.7 | I27: =I24+I25+I26 -> 1467.1575 | J27: =J24+J25+J26 -> 1410.5591 | ... O27: =O24+O25+O26 -> 15750.178 | P27: ='Assumptions & Budget'!O82 -> 15401.304 | Q27: =P27-O27 -> -348.87386 | R27: =IF(P27=0,0,Q27/P27) -> -0.022652229
A28: HR – personnel | B28: ₹ lakh | C28: =IF(C$5<=$C$3,'Actual vs Budget'!C29,'Assumptions & Budget'!C83*IF('Assumptions & Budget'!$E$53="Revenue",C12/'Assumptions & Budget'!C67,IF('Assumptions & Budget'!$E$53="Orders",C9/'Assumptions & Budget'!C64,1))*(1+'Variance-to-Action Log'!$V$18)+IF(AND(C$7>=1,C$7<=$F$3),'Variance-to-Action Log'!$W$18/$F$3,0)) -> 14 | D28: =IF(D$5<=$C$3,'Actual vs Budget'!D29,'Assumptions & Budget'!D83*IF('Assumptions & Budget'!$E$53="Revenue",D12/'Assumptions & Budget'!D67,IF('Assumptions & Budget'!$E$53="Orders",D9/'Assumptions & Budget'!D64,1))*(1+'Variance-to-Action Log'!$V$18)+IF(AND(D$7>=1,D$7<=$F$3),'Variance-to-Action Log'!$W$18/$F$3,0)) -> 13.9 | E28: =IF(E$5<=$C$3,'Actual vs Budget'!E29,'Assumptions & Budget'!E83*IF('Assumptions & Budget'!$E$53="Revenue",E12/'Assumptions & Budget'!E67,IF('Assumptions & Budget'!$E$53="Orders",E9/'Assumptions & Budget'!E64,1))*(1+'Variance-to-Action Log'!$V$18)+IF(AND(E$7>=1,E$7<=$F$3),'Variance-to-Action Log'!$W$18/$F$3,0)) -> 13.9 | F28: =IF(F$5<=$C$3,'Actual vs Budget'!F29,'Assumptions & Budget'!F83*IF('Assumptions & Budget'!$E$53="Revenue",F12/'Assumptions & Budget'!F67,IF('Assumptions & Budget'!$E$53="Orders",F9/'Assumptions & Budget'!F64,1))*(1+'Variance-to-Action Log'!$V$18)+IF(AND(F$7>=1,F$7<=$F$3),'Variance-to-Action Log'!$W$18/$F$3,0)) -> 13.9 | G28: =IF(G$5<=$C$3,'Actual vs Budget'!G29,'Assumptions & Budget'!G83*IF('Assumptions & Budget'!$E$53="Revenue",G12/'Assumptions & Budget'!G67,IF('Assumptions & Budget'!$E$53="Orders",G9/'Assumptions & Budget'!G64,1))*(1+'Variance-to-Action Log'!$V$18)+IF(AND(G$7>=1,G$7<=$F$3),'Variance-to-Action Log'!$W$18/$F$3,0)) -> 13.9 | H28: =IF(H$5<=$C$3,'Actual vs Budget'!H29,'Assumptions & Budget'!H83*IF('Assumptions & Budget'!$E$53="Revenue",H12/'Assumptions & Budget'!H67,IF('Assumptions & Budget'!$E$53="Orders",H9/'Assumptions & Budget'!H64,1))*(1+'Variance-to-Action Log'!$V$18)+IF(AND(H$7>=1,H$7<=$F$3),'Variance-to-Action Log'!$W$18/$F$3,0)) -> 14.9 | I28: =IF(I$5<=$C$3,'Actual vs Budget'!I29,'Assumptions & Budget'!I83*IF('Assumptions & Budget'!$E$53="Revenue",I12/'Assumptions & Budget'!I67,IF('Assumptions & Budget'!$E$53="Orders",I9/'Assumptions & Budget'!I64,1))*(1+'Variance-to-Action Log'!$V$18)+IF(AND(I$7>=1,I$7<=$F$3),'Variance-to-Action Log'!$W$18/$F$3,0)) -> 15.012 | J28: =IF(J$5<=$C$3,'Actual vs Budget'!J29,'Assumptions & Budget'!J83*IF('Assumptions & Budget'!$E$53="Revenue",J12/'Assumptions & Budget'!J67,IF('Assumptions & Budget'!$E$53="Orders",J9/'Assumptions & Budget'!J64,1))*(1+'Variance-to-Action Log'!$V$18)+IF(AND(J$7>=1,J$7<=$F$3),'Variance-to-Action Log'!$W$18/$F$3,0)) -> 15.012 | ... N28: =IF(N$5<=$C$3,'Actual vs Budget'!N29,'Assumptions & Budget'!N83*IF('Assumptions & Budget'!$E$53="Revenue",N12/'Assumptions & Budget'!N67,IF('Assumptions & Budget'!$E$53="Orders",N9/'Assumptions & Budget'!N64,1))*(1+'Variance-to-Action Log'!$V$18)+IF(AND(N$7>=1,N$7<=$F$3),'Variance-to-Action Log'!$W$18/$F$3,0)) -> 15.012 | O28: =SUM($C28:$N28) -> 174.572 | P28: ='Assumptions & Budget'!O83 -> 180.144 | Q28: =P28-O28 -> 5.572 | R28: =IF(P28=0,0,Q28/P28) -> 0.030930811
A29: HR – recruitment, training & other | B29: ₹ lakh | C29: =IF(C$5<=$C$3,'Actual vs Budget'!C30,'Assumptions & Budget'!C84*IF('Assumptions & Budget'!$E$54="Revenue",C12/'Assumptions & Budget'!C67,IF('Assumptions & Budget'!$E$54="Orders",C9/'Assumptions & Budget'!C64,1))*(1+'Variance-to-Action Log'!$V$19)+IF(AND(C$7>=1,C$7<=$F$3),'Variance-to-Action Log'!$W$19/$F$3,0)) -> 10.2 | D29: =IF(D$5<=$C$3,'Actual vs Budget'!D30,'Assumptions & Budget'!D84*IF('Assumptions & Budget'!$E$54="Revenue",D12/'Assumptions & Budget'!D67,IF('Assumptions & Budget'!$E$54="Orders",D9/'Assumptions & Budget'!D64,1))*(1+'Variance-to-Action Log'!$V$19)+IF(AND(D$7>=1,D$7<=$F$3),'Variance-to-Action Log'!$W$19/$F$3,0)) -> 9.2 | E29: =IF(E$5<=$C$3,'Actual vs Budget'!E30,'Assumptions & Budget'!E84*IF('Assumptions & Budget'!$E$54="Revenue",E12/'Assumptions & Budget'!E67,IF('Assumptions & Budget'!$E$54="Orders",E9/'Assumptions & Budget'!E64,1))*(1+'Variance-to-Action Log'!$V$19)+IF(AND(E$7>=1,E$7<=$F$3),'Variance-to-Action Log'!$W$19/$F$3,0)) -> 9.7 | F29: =IF(F$5<=$C$3,'Actual vs Budget'!F30,'Assumptions & Budget'!F84*IF('Assumptions & Budget'!$E$54="Revenue",F12/'Assumptions & Budget'!F67,IF('Assumptions & Budget'!$E$54="Orders",F9/'Assumptions & Budget'!F64,1))*(1+'Variance-to-Action Log'!$V$19)+IF(AND(F$7>=1,F$7<=$F$3),'Variance-to-Action Log'!$W$19/$F$3,0)) -> 10.7 | G29: =IF(G$5<=$C$3,'Actual vs Budget'!G30,'Assumptions & Budget'!G84*IF('Assumptions & Budget'!$E$54="Revenue",G12/'Assumptions & Budget'!G67,IF('Assumptions & Budget'!$E$54="Orders",G9/'Assumptions & Budget'!G64,1))*(1+'Variance-to-Action Log'!$V$19)+IF(AND(G$7>=1,G$7<=$F$3),'Variance-to-Action Log'!$W$19/$F$3,0)) -> 10 | H29: =IF(H$5<=$C$3,'Actual vs Budget'!H30,'Assumptions & Budget'!H84*IF('Assumptions & Budget'!$E$54="Revenue",H12/'Assumptions & Budget'!H67,IF('Assumptions & Budget'!$E$54="Orders",H9/'Assumptions & Budget'!H64,1))*(1+'Variance-to-Action Log'!$V$19)+IF(AND(H$7>=1,H$7<=$F$3),'Variance-to-Action Log'!$W$19/$F$3,0)) -> 10.2 | I29: =IF(I$5<=$C$3,'Actual vs Budget'!I30,'Assumptions & Budget'!I84*IF('Assumptions & Budget'!$E$54="Revenue",I12/'Assumptions & Budget'!I67,IF('Assumptions & Budget'!$E$54="Orders",I9/'Assumptions & Budget'!I64,1))*(1+'Variance-to-Action Log'!$V$19)+IF(AND(I$7>=1,I$7<=$F$3),'Variance-to-Action Log'!$W$19/$F$3,0)) -> 10.12375 | J29: =IF(J$5<=$C$3,'Actual vs Budget'!J30,'Assumptions & Budget'!J84*IF('Assumptions & Budget'!$E$54="Revenue",J12/'Assumptions & Budget'!J67,IF('Assumptions & Budget'!$E$54="Orders",J9/'Assumptions & Budget'!J64,1))*(1+'Variance-to-Action Log'!$V$19)+IF(AND(J$7>=1,J$7<=$F$3),'Variance-to-Action Log'!$W$19/$F$3,0)) -> 10.12375 | ... N29: =IF(N$5<=$C$3,'Actual vs Budget'!N30,'Assumptions & Budget'!N84*IF('Assumptions & Budget'!$E$54="Revenue",N12/'Assumptions & Budget'!N67,IF('Assumptions & Budget'!$E$54="Orders",N9/'Assumptions & Budget'!N64,1))*(1+'Variance-to-Action Log'!$V$19)+IF(AND(N$7>=1,N$7<=$F$3),'Variance-to-Action Log'!$W$19/$F$3,0)) -> 10.12375 | O29: =SUM($C29:$N29) -> 120.7425 | P29: ='Assumptions & Budget'!O84 -> 121.485 | Q29: =P29-O29 -> 0.7425 | R29: =IF(P29=0,0,Q29/P29) -> 0.0061118657
A30: HR – total | B30: ₹ lakh | C30: =C28+C29 -> 24.2 | D30: =D28+D29 -> 23.1 | E30: =E28+E29 -> 23.6 | F30: =F28+F29 -> 24.6 | G30: =G28+G29 -> 23.9 | H30: =H28+H29 -> 25.1 | I30: =I28+I29 -> 25.13575 | J30: =J28+J29 -> 25.13575 | ... O30: =O28+O29 -> 295.3145 | P30: ='Assumptions & Budget'!O85 -> 301.629 | Q30: =P30-O30 -> 6.3145 | R30: =IF(P30=0,0,Q30/P30) -> 0.020934658
A31: IT – personnel | B31: ₹ lakh | C31: =IF(C$5<=$C$3,'Actual vs Budget'!C32,'Assumptions & Budget'!C86*IF('Assumptions & Budget'!$E$55="Revenue",C12/'Assumptions & Budget'!C67,IF('Assumptions & Budget'!$E$55="Orders",C9/'Assumptions & Budget'!C64,1))*(1+'Variance-to-Action Log'!$V$20)+IF(AND(C$7>=1,C$7<=$F$3),'Variance-to-Action Log'!$W$20/$F$3,0)) -> 94 | D31: =IF(D$5<=$C$3,'Actual vs Budget'!D32,'Assumptions & Budget'!D86*IF('Assumptions & Budget'!$E$55="Revenue",D12/'Assumptions & Budget'!D67,IF('Assumptions & Budget'!$E$55="Orders",D9/'Assumptions & Budget'!D64,1))*(1+'Variance-to-Action Log'!$V$20)+IF(AND(D$7>=1,D$7<=$F$3),'Variance-to-Action Log'!$W$20/$F$3,0)) -> 94.3 | E31: =IF(E$5<=$C$3,'Actual vs Budget'!E32,'Assumptions & Budget'!E86*IF('Assumptions & Budget'!$E$55="Revenue",E12/'Assumptions & Budget'!E67,IF('Assumptions & Budget'!$E$55="Orders",E9/'Assumptions & Budget'!E64,1))*(1+'Variance-to-Action Log'!$V$20)+IF(AND(E$7>=1,E$7<=$F$3),'Variance-to-Action Log'!$W$20/$F$3,0)) -> 95.7 | F31: =IF(F$5<=$C$3,'Actual vs Budget'!F32,'Assumptions & Budget'!F86*IF('Assumptions & Budget'!$E$55="Revenue",F12/'Assumptions & Budget'!F67,IF('Assumptions & Budget'!$E$55="Orders",F9/'Assumptions & Budget'!F64,1))*(1+'Variance-to-Action Log'!$V$20)+IF(AND(F$7>=1,F$7<=$F$3),'Variance-to-Action Log'!$W$20/$F$3,0)) -> 98.9 | G31: =IF(G$5<=$C$3,'Actual vs Budget'!G32,'Assumptions & Budget'!G86*IF('Assumptions & Budget'!$E$55="Revenue",G12/'Assumptions & Budget'!G67,IF('Assumptions & Budget'!$E$55="Orders",G9/'Assumptions & Budget'!G64,1))*(1+'Variance-to-Action Log'!$V$20)+IF(AND(G$7>=1,G$7<=$F$3),'Variance-to-Action Log'!$W$20/$F$3,0)) -> 97.5 | H31: =IF(H$5<=$C$3,'Actual vs Budget'!H32,'Assumptions & Budget'!H86*IF('Assumptions & Budget'!$E$55="Revenue",H12/'Assumptions & Budget'!H67,IF('Assumptions & Budget'!$E$55="Orders",H9/'Assumptions & Budget'!H64,1))*(1+'Variance-to-Action Log'!$V$20)+IF(AND(H$7>=1,H$7<=$F$3),'Variance-to-Action Log'!$W$20/$F$3,0)) -> 99.5 | I31: =IF(I$5<=$C$3,'Actual vs Budget'!I32,'Assumptions & Budget'!I86*IF('Assumptions & Budget'!$E$55="Revenue",I12/'Assumptions & Budget'!I67,IF('Assumptions & Budget'!$E$55="Orders",I9/'Assumptions & Budget'!I64,1))*(1+'Variance-to-Action Log'!$V$20)+IF(AND(I$7>=1,I$7<=$F$3),'Variance-to-Action Log'!$W$20/$F$3,0)) -> 98.203355 | J31: =IF(J$5<=$C$3,'Actual vs Budget'!J32,'Assumptions & Budget'!J86*IF('Assumptions & Budget'!$E$55="Revenue",J12/'Assumptions & Budget'!J67,IF('Assumptions & Budget'!$E$55="Orders",J9/'Assumptions & Budget'!J64,1))*(1+'Variance-to-Action Log'!$V$20)+IF(AND(J$7>=1,J$7<=$F$3),'Variance-to-Action Log'!$W$20/$F$3,0)) -> 98.203355 | ... N31: =IF(N$5<=$C$3,'Actual vs Budget'!N32,'Assumptions & Budget'!N86*IF('Assumptions & Budget'!$E$55="Revenue",N12/'Assumptions & Budget'!N67,IF('Assumptions & Budget'!$E$55="Orders",N9/'Assumptions & Budget'!N64,1))*(1+'Variance-to-Action Log'!$V$20)+IF(AND(N$7>=1,N$7<=$F$3),'Variance-to-Action Log'!$W$20/$F$3,0)) -> 98.203355 | O31: =SUM($C31:$N31) -> 1169.1201 | P31: ='Assumptions & Budget'!O86 -> 1167.5288 | Q31: =P31-O31 -> -1.5913548 | R31: =IF(P31=0,0,Q31/P31) -> -0.0013630112
A32: IT – software, cloud & other | B32: ₹ lakh | C32: =IF(C$5<=$C$3,'Actual vs Budget'!C33,'Assumptions & Budget'!C87*IF('Assumptions & Budget'!$E$56="Revenue",C12/'Assumptions & Budget'!C67,IF('Assumptions & Budget'!$E$56="Orders",C9/'Assumptions & Budget'!C64,1))*(1+'Variance-to-Action Log'!$V$21)+IF(AND(C$7>=1,C$7<=$F$3),'Variance-to-Action Log'!$W$21/$F$3,0)) -> 52.2 | D32: =IF(D$5<=$C$3,'Actual vs Budget'!D33,'Assumptions & Budget'!D87*IF('Assumptions & Budget'!$E$56="Revenue",D12/'Assumptions & Budget'!D67,IF('Assumptions & Budget'!$E$56="Orders",D9/'Assumptions & Budget'!D64,1))*(1+'Variance-to-Action Log'!$V$21)+IF(AND(D$7>=1,D$7<=$F$3),'Variance-to-Action Log'!$W$21/$F$3,0)) -> 50.7 | E32: =IF(E$5<=$C$3,'Actual vs Budget'!E33,'Assumptions & Budget'!E87*IF('Assumptions & Budget'!$E$56="Revenue",E12/'Assumptions & Budget'!E67,IF('Assumptions & Budget'!$E$56="Orders",E9/'Assumptions & Budget'!E64,1))*(1+'Variance-to-Action Log'!$V$21)+IF(AND(E$7>=1,E$7<=$F$3),'Variance-to-Action Log'!$W$21/$F$3,0)) -> 138.4 | F32: =IF(F$5<=$C$3,'Actual vs Budget'!F33,'Assumptions & Budget'!F87*IF('Assumptions & Budget'!$E$56="Revenue",F12/'Assumptions & Budget'!F67,IF('Assumptions & Budget'!$E$56="Orders",F9/'Assumptions & Budget'!F64,1))*(1+'Variance-to-Action Log'!$V$21)+IF(AND(F$7>=1,F$7<=$F$3),'Variance-to-Action Log'!$W$21/$F$3,0)) -> 50.1 | G32: =IF(G$5<=$C$3,'Actual vs Budget'!G33,'Assumptions & Budget'!G87*IF('Assumptions & Budget'!$E$56="Revenue",G12/'Assumptions & Budget'!G67,IF('Assumptions & Budget'!$E$56="Orders",G9/'Assumptions & Budget'!G64,1))*(1+'Variance-to-Action Log'!$V$21)+IF(AND(G$7>=1,G$7<=$F$3),'Variance-to-Action Log'!$W$21/$F$3,0)) -> 52.2 | H32: =IF(H$5<=$C$3,'Actual vs Budget'!H33,'Assumptions & Budget'!H87*IF('Assumptions & Budget'!$E$56="Revenue",H12/'Assumptions & Budget'!H67,IF('Assumptions & Budget'!$E$56="Orders",H9/'Assumptions & Budget'!H64,1))*(1+'Variance-to-Action Log'!$V$21)+IF(AND(H$7>=1,H$7<=$F$3),'Variance-to-Action Log'!$W$21/$F$3,0)) -> 50.9 | I32: =IF(I$5<=$C$3,'Actual vs Budget'!I33,'Assumptions & Budget'!I87*IF('Assumptions & Budget'!$E$56="Revenue",I12/'Assumptions & Budget'!I67,IF('Assumptions & Budget'!$E$56="Orders",I9/'Assumptions & Budget'!I64,1))*(1+'Variance-to-Action Log'!$V$21)+IF(AND(I$7>=1,I$7<=$F$3),'Variance-to-Action Log'!$W$21/$F$3,0)) -> 52.210667 | J32: =IF(J$5<=$C$3,'Actual vs Budget'!J33,'Assumptions & Budget'!J87*IF('Assumptions & Budget'!$E$56="Revenue",J12/'Assumptions & Budget'!J67,IF('Assumptions & Budget'!$E$56="Orders",J9/'Assumptions & Budget'!J64,1))*(1+'Variance-to-Action Log'!$V$21)+IF(AND(J$7>=1,J$7<=$F$3),'Variance-to-Action Log'!$W$21/$F$3,0)) -> 52.210667 | ... N32: =IF(N$5<=$C$3,'Actual vs Budget'!N33,'Assumptions & Budget'!N87*IF('Assumptions & Budget'!$E$56="Revenue",N12/'Assumptions & Budget'!N67,IF('Assumptions & Budget'!$E$56="Orders",N9/'Assumptions & Budget'!N64,1))*(1+'Variance-to-Action Log'!$V$21)+IF(AND(N$7>=1,N$7<=$F$3),'Variance-to-Action Log'!$W$21/$F$3,0)) -> 52.210667 | O32: =SUM($C32:$N32) -> 707.764 | P32: ='Assumptions & Budget'!O87 -> 626.528 | Q32: =P32-O32 -> -81.236 | R32: =IF(P32=0,0,Q32/P32) -> -0.12966061
A33: IT – total | B33: ₹ lakh | C33: =C31+C32 -> 146.2 | D33: =D31+D32 -> 145 | E33: =E31+E32 -> 234.1 | F33: =F31+F32 -> 149 | G33: =G31+G32 -> 149.7 | H33: =H31+H32 -> 150.4 | I33: =I31+I32 -> 150.41402 | J33: =J31+J32 -> 150.41402 | ... O33: =O31+O32 -> 1876.8841 | P33: ='Assumptions & Budget'!O88 -> 1794.0568 | Q33: =P33-O33 -> -82.827355 | R33: =IF(P33=0,0,Q33/P33) -> -0.046167633
A34: Finance – personnel | B34: ₹ lakh | C34: =IF(C$5<=$C$3,'Actual vs Budget'!C35,'Assumptions & Budget'!C89*IF('Assumptions & Budget'!$E$57="Revenue",C12/'Assumptions & Budget'!C67,IF('Assumptions & Budget'!$E$57="Orders",C9/'Assumptions & Budget'!C64,1))*(1+'Variance-to-Action Log'!$V$22)+IF(AND(C$7>=1,C$7<=$F$3),'Variance-to-Action Log'!$W$22/$F$3,0)) -> 39.5 | D34: =IF(D$5<=$C$3,'Actual vs Budget'!D35,'Assumptions & Budget'!D89*IF('Assumptions & Budget'!$E$57="Revenue",D12/'Assumptions & Budget'!D67,IF('Assumptions & Budget'!$E$57="Orders",D9/'Assumptions & Budget'!D64,1))*(1+'Variance-to-Action Log'!$V$22)+IF(AND(D$7>=1,D$7<=$F$3),'Variance-to-Action Log'!$W$22/$F$3,0)) -> 39.1 | E34: =IF(E$5<=$C$3,'Actual vs Budget'!E35,'Assumptions & Budget'!E89*IF('Assumptions & Budget'!$E$57="Revenue",E12/'Assumptions & Budget'!E67,IF('Assumptions & Budget'!$E$57="Orders",E9/'Assumptions & Budget'!E64,1))*(1+'Variance-to-Action Log'!$V$22)+IF(AND(E$7>=1,E$7<=$F$3),'Variance-to-Action Log'!$W$22/$F$3,0)) -> 39 | F34: =IF(F$5<=$C$3,'Actual vs Budget'!F35,'Assumptions & Budget'!F89*IF('Assumptions & Budget'!$E$57="Revenue",F12/'Assumptions & Budget'!F67,IF('Assumptions & Budget'!$E$57="Orders",F9/'Assumptions & Budget'!F64,1))*(1+'Variance-to-Action Log'!$V$22)+IF(AND(F$7>=1,F$7<=$F$3),'Variance-to-Action Log'!$W$22/$F$3,0)) -> 39.1 | G34: =IF(G$5<=$C$3,'Actual vs Budget'!G35,'Assumptions & Budget'!G89*IF('Assumptions & Budget'!$E$57="Revenue",G12/'Assumptions & Budget'!G67,IF('Assumptions & Budget'!$E$57="Orders",G9/'Assumptions & Budget'!G64,1))*(1+'Variance-to-Action Log'!$V$22)+IF(AND(G$7>=1,G$7<=$F$3),'Variance-to-Action Log'!$W$22/$F$3,0)) -> 39.2 | H34: =IF(H$5<=$C$3,'Actual vs Budget'!H35,'Assumptions & Budget'!H89*IF('Assumptions & Budget'!$E$57="Revenue",H12/'Assumptions & Budget'!H67,IF('Assumptions & Budget'!$E$57="Orders",H9/'Assumptions & Budget'!H64,1))*(1+'Variance-to-Action Log'!$V$22)+IF(AND(H$7>=1,H$7<=$F$3),'Variance-to-Action Log'!$W$22/$F$3,0)) -> 39.2 | I34: =IF(I$5<=$C$3,'Actual vs Budget'!I35,'Assumptions & Budget'!I89*IF('Assumptions & Budget'!$E$57="Revenue",I12/'Assumptions & Budget'!I67,IF('Assumptions & Budget'!$E$57="Orders",I9/'Assumptions & Budget'!I64,1))*(1+'Variance-to-Action Log'!$V$22)+IF(AND(I$7>=1,I$7<=$F$3),'Variance-to-Action Log'!$W$22/$F$3,0)) -> 40.6224 | J34: =IF(J$5<=$C$3,'Actual vs Budget'!J35,'Assumptions & Budget'!J89*IF('Assumptions & Budget'!$E$57="Revenue",J12/'Assumptions & Budget'!J67,IF('Assumptions & Budget'!$E$57="Orders",J9/'Assumptions & Budget'!J64,1))*(1+'Variance-to-Action Log'!$V$22)+IF(AND(J$7>=1,J$7<=$F$3),'Variance-to-Action Log'!$W$22/$F$3,0)) -> 40.6224 | ... N34: =IF(N$5<=$C$3,'Actual vs Budget'!N35,'Assumptions & Budget'!N89*IF('Assumptions & Budget'!$E$57="Revenue",N12/'Assumptions & Budget'!N67,IF('Assumptions & Budget'!$E$57="Orders",N9/'Assumptions & Budget'!N64,1))*(1+'Variance-to-Action Log'!$V$22)+IF(AND(N$7>=1,N$7<=$F$3),'Variance-to-Action Log'!$W$22/$F$3,0)) -> 40.6224 | O34: =SUM($C34:$N34) -> 478.8344 | P34: ='Assumptions & Budget'!O89 -> 479.6064 | Q34: =P34-O34 -> 0.772 | R34: =IF(P34=0,0,Q34/P34) -> 0.0016096532
A35: Finance – professional fees, rent & admin | B35: ₹ lakh | C35: =IF(C$5<=$C$3,'Actual vs Budget'!C36,'Assumptions & Budget'!C90*IF('Assumptions & Budget'!$E$58="Revenue",C12/'Assumptions & Budget'!C67,IF('Assumptions & Budget'!$E$58="Orders",C9/'Assumptions & Budget'!C64,1))*(1+'Variance-to-Action Log'!$V$23)+IF(AND(C$7>=1,C$7<=$F$3),'Variance-to-Action Log'!$W$23/$F$3,0)) -> 59.6 | D35: =IF(D$5<=$C$3,'Actual vs Budget'!D36,'Assumptions & Budget'!D90*IF('Assumptions & Budget'!$E$58="Revenue",D12/'Assumptions & Budget'!D67,IF('Assumptions & Budget'!$E$58="Orders",D9/'Assumptions & Budget'!D64,1))*(1+'Variance-to-Action Log'!$V$23)+IF(AND(D$7>=1,D$7<=$F$3),'Variance-to-Action Log'!$W$23/$F$3,0)) -> 64 | E35: =IF(E$5<=$C$3,'Actual vs Budget'!E36,'Assumptions & Budget'!E90*IF('Assumptions & Budget'!$E$58="Revenue",E12/'Assumptions & Budget'!E67,IF('Assumptions & Budget'!$E$58="Orders",E9/'Assumptions & Budget'!E64,1))*(1+'Variance-to-Action Log'!$V$23)+IF(AND(E$7>=1,E$7<=$F$3),'Variance-to-Action Log'!$W$23/$F$3,0)) -> 62.2 | F35: =IF(F$5<=$C$3,'Actual vs Budget'!F36,'Assumptions & Budget'!F90*IF('Assumptions & Budget'!$E$58="Revenue",F12/'Assumptions & Budget'!F67,IF('Assumptions & Budget'!$E$58="Orders",F9/'Assumptions & Budget'!F64,1))*(1+'Variance-to-Action Log'!$V$23)+IF(AND(F$7>=1,F$7<=$F$3),'Variance-to-Action Log'!$W$23/$F$3,0)) -> 63.3 | G35: =IF(G$5<=$C$3,'Actual vs Budget'!G36,'Assumptions & Budget'!G90*IF('Assumptions & Budget'!$E$58="Revenue",G12/'Assumptions & Budget'!G67,IF('Assumptions & Budget'!$E$58="Orders",G9/'Assumptions & Budget'!G64,1))*(1+'Variance-to-Action Log'!$V$23)+IF(AND(G$7>=1,G$7<=$F$3),'Variance-to-Action Log'!$W$23/$F$3,0)) -> 64.2 | H35: =IF(H$5<=$C$3,'Actual vs Budget'!H36,'Assumptions & Budget'!H90*IF('Assumptions & Budget'!$E$58="Revenue",H12/'Assumptions & Budget'!H67,IF('Assumptions & Budget'!$E$58="Orders",H9/'Assumptions & Budget'!H64,1))*(1+'Variance-to-Action Log'!$V$23)+IF(AND(H$7>=1,H$7<=$F$3),'Variance-to-Action Log'!$W$23/$F$3,0)) -> 62.5 | I35: =IF(I$5<=$C$3,'Actual vs Budget'!I36,'Assumptions & Budget'!I90*IF('Assumptions & Budget'!$E$58="Revenue",I12/'Assumptions & Budget'!I67,IF('Assumptions & Budget'!$E$58="Orders",I9/'Assumptions & Budget'!I64,1))*(1+'Variance-to-Action Log'!$V$23)+IF(AND(I$7>=1,I$7<=$F$3),'Variance-to-Action Log'!$W$23/$F$3,0)) -> 62.071833 | J35: =IF(J$5<=$C$3,'Actual vs Budget'!J36,'Assumptions & Budget'!J90*IF('Assumptions & Budget'!$E$58="Revenue",J12/'Assumptions & Budget'!J67,IF('Assumptions & Budget'!$E$58="Orders",J9/'Assumptions & Budget'!J64,1))*(1+'Variance-to-Action Log'!$V$23)+IF(AND(J$7>=1,J$7<=$F$3),'Variance-to-Action Log'!$W$23/$F$3,0)) -> 62.071833 | ... N35: =IF(N$5<=$C$3,'Actual vs Budget'!N36,'Assumptions & Budget'!N90*IF('Assumptions & Budget'!$E$58="Revenue",N12/'Assumptions & Budget'!N67,IF('Assumptions & Budget'!$E$58="Orders",N9/'Assumptions & Budget'!N64,1))*(1+'Variance-to-Action Log'!$V$23)+IF(AND(N$7>=1,N$7<=$F$3),'Variance-to-Action Log'!$W$23/$F$3,0)) -> 62.071833 | O35: =SUM($C35:$N35) -> 748.231 | P35: ='Assumptions & Budget'!O90 -> 744.862 | Q35: =P35-O35 -> -3.369 | R35: =IF(P35=0,0,Q35/P35) -> -0.0045229855
A36: Finance – total | B36: ₹ lakh | C36: =C34+C35 -> 99.1 | D36: =D34+D35 -> 103.1 | E36: =E34+E35 -> 101.2 | F36: =F34+F35 -> 102.4 | G36: =G34+G35 -> 103.4 | H36: =H34+H35 -> 101.7 | I36: =I34+I35 -> 102.69423 | J36: =J34+J35 -> 102.69423 | ... O36: =O34+O35 -> 1227.0654 | P36: ='Assumptions & Budget'!O91 -> 1224.4684 | Q36: =P36-O36 -> -2.597 | R36: =IF(P36=0,0,Q36/P36) -> -0.0021209204
A37: Total operating cost & profitability (₹ lakh)
A38: Total operating cost | B38: ₹ lakh | C38: =C19+C23+C27+C30+C33+C36 -> 2066.7 | D38: =D19+D23+D27+D30+D33+D36 -> 2035.5 | E38: =E19+E23+E27+E30+E33+E36 -> 2188.7 | F38: =F19+F23+F27+F30+F33+F36 -> 2147.3 | G38: =G19+G23+G27+G30+G33+G36 -> 2235.1 | H38: =H19+H23+H27+H30+H33+H36 -> 2396.8 | I38: =I19+I23+I27+I30+I33+I36 -> 2478.7398 | J38: =J19+J23+J27+J30+J33+J36 -> 2401.0039 | ... O38: =O19+O23+O27+O30+O33+O36 -> 26927.274 | P38: ='Assumptions & Budget'!O93 -> 25929.972 | Q38: =P38-O38 -> -997.30218 | R38: =IF(P38=0,0,Q38/P38) -> -0.038461367
A39: EBITDA | B39: ₹ lakh | C39: =C14-C38 -> 390.68038 | D39: =D14-D38 -> 360.44397 | E39: =E14-E38 -> 235.43441 | F39: =F14-F38 -> 269.8588 | G39: =G14-G38 -> 324.40832 | H39: =H14-H38 -> 305.06387 | I39: =I14-I38 -> 739.14492 | J39: =J14-J38 -> 692.05368 | ... O39: =O14-O38 -> 5123.7988 | P39: ='Assumptions & Budget'!O94 -> 5357.8638 | Q39: =O39-P39 -> -234.06502 | R39: =IF(P39=0,0,Q39/P39) -> -0.043686258
A40: EBITDA margin % | B40: % | C40: =IF(C12=0,0,C39/C12) -> 0.10956685 | D40: =IF(D12=0,0,D39/D12) -> 0.10297093 | E40: =IF(E12=0,0,E39/E12) -> 0.066842345 | F40: =IF(F12=0,0,F39/F12) -> 0.079022564 | G40: =IF(G12=0,0,G39/G12) -> 0.090215959 | H40: =IF(H12=0,0,H39/H12) -> 0.079824884 | I40: =IF(I12=0,0,I39/I12) -> 0.16281984 | J40: =IF(J12=0,0,J39/J12) -> 0.15859883 | ... O40: =IF(O12=0,0,O39/O12) -> 0.1125173 | P40: ='Assumptions & Budget'!O95 -> 0.11815857 | Q40: =O40-P40 -> -0.0056412719
A41: Depreciation & amortisation | B41: ₹ lakh | C41: =IF(C$5<=$C$3,'Actual vs Budget'!C42,'Assumptions & Budget'!C96) -> 70.5 | D41: =IF(D$5<=$C$3,'Actual vs Budget'!D42,'Assumptions & Budget'!D96) -> 70.3 | E41: =IF(E$5<=$C$3,'Actual vs Budget'!E42,'Assumptions & Budget'!E96) -> 70.8 | F41: =IF(F$5<=$C$3,'Actual vs Budget'!F42,'Assumptions & Budget'!F96) -> 69.9 | G41: =IF(G$5<=$C$3,'Actual vs Budget'!G42,'Assumptions & Budget'!G96) -> 70.9 | H41: =IF(H$5<=$C$3,'Actual vs Budget'!H42,'Assumptions & Budget'!H96) -> 70.8 | I41: =IF(I$5<=$C$3,'Actual vs Budget'!I42,'Assumptions & Budget'!I96) -> 70.632 | J41: =IF(J$5<=$C$3,'Actual vs Budget'!J42,'Assumptions & Budget'!J96) -> 70.632 | ... N41: =IF(N$5<=$C$3,'Actual vs Budget'!N42,'Assumptions & Budget'!N96) -> 70.632 | O41: =SUM($C41:$N41) -> 846.992 | P41: ='Assumptions & Budget'!O96 -> 847.584 | Q41: =P41-O41 -> 0.592 | R41: =IF(P41=0,0,Q41/P41) -> 0.00069845585
A42: EBIT | B42: ₹ lakh | C42: =C39-C41 -> 320.18038 | D42: =D39-D41 -> 290.14397 | E42: =E39-E41 -> 164.63441 | F42: =F39-F41 -> 199.9588 | G42: =G39-G41 -> 253.50832 | H42: =H39-H41 -> 234.26387 | I42: =I39-I41 -> 668.51292 | J42: =J39-J41 -> 621.42168 | ... O42: =O39-O41 -> 4276.8068 | P42: ='Assumptions & Budget'!O97 -> 4510.2798 | Q42: =O42-P42 -> -233.47302 | R42: =IF(P42=0,0,Q42/P42) -> -0.051764642
A43: Operating metrics
A44: Marketing spend % of revenue | B44: % | C44: =IF(C12=0,0,(C25+C26)/C12) -> 0.3135166 | D44: =IF(D12=0,0,(D25+D26)/D12) -> 0.31276033 | E44: =IF(E12=0,0,(E25+E26)/E12) -> 0.32274967 | F44: =IF(F12=0,0,(F25+F26)/F12) -> 0.32094091 | G44: =IF(G12=0,0,(G25+G26)/G12) -> 0.34369619 | H44: =IF(H12=0,0,(H25+H26)/H12) -> 0.35955543 | I44: =IF(I12=0,0,(I25+I26)/I12) -> 0.3025153 | J44: =IF(J12=0,0,(J25+J26)/J12) -> 0.30175324 | ... O44: =IF(O12=0,0,(O25+O26)/O12) -> 0.32138549 | P44: ='Assumptions & Budget'!O107 -> 0.315 | Q44: =O44-P44 -> 0.0063854917

Sheet Summary
A1: Summary – FY27 Budget, YTD Performance and Outlook
A2: All figures link to the model sheets (₹ lakh unless stated).
A3: Actuals loaded through | C3: ='Assumptions & Budget'!$C$6 -> 46266
A5: 1. Year-to-date performance vs budget
A6: ₹ lakh | C6: YTD budget | D6: YTD actual | E6: Variance (fav +) | F6: Variance %
A7: Net revenue | C7: ='Actual vs Budget'!O63 -> 21227.704 | D7: ='Actual vs Budget'!O13 -> 21420.89 | E7: ='Actual vs Budget'!O119 -> 193.18544 | F7: ='Actual vs Budget'!P119 -> 0.0091006278
A8: Gross profit | C8: ='Actual vs Budget'!O65 -> 14647.116 | D8: ='Actual vs Budget'!O15 -> 14955.99 | E8: ='Actual vs Budget'!O121 -> 308.87377 | F8: ='Actual vs Budget'!P121 -> 0.021087685
A9: Total operating cost | C9: ='Actual vs Budget'!O86 -> 12348.056 | D9: ='Actual vs Budget'!O39 -> 13070.1 | E9: ='Actual vs Budget'!O142 -> -722.04383 | F9: ='Actual vs Budget'!P142 -> -0.058474291
A10: EBITDA | C10: ='Actual vs Budget'!O87 -> 2299.0598 | D10: ='Actual vs Budget'!O40 -> 1885.8897 | E10: ='Actual vs Budget'!O143 -> -413.17006 | F10: ='Actual vs Budget'!P143 -> -0.17971262
A11: EBITDA margin | C11: =IF(C7=0,0,C10/C7) -> 0.10830468 | D11: =IF(D7=0,0,D10/D7) -> 0.088039749 | E11: =D11-C11 -> -0.020264935
A12: Revenue variance: volume effect | E12: ='Actual vs Budget'!O173 -> 350.84983
A13: Revenue variance: price / mix effect | E13: ='Actual vs Budget'!O174 -> -157.66439
A15: 2. FY27 outlook – rolling forecast vs budget
A16: ₹ lakh | C16: FY27 Budget | D16: FY27 Rolling Fcst | E16: Variance (fav +) | F16: Variance %
A17: Net revenue | C17: ='Rolling Forecast'!P12 -> 45344.69 | D17: ='Rolling Forecast'!O12 -> 45537.875 | E17: ='Rolling Forecast'!Q12 -> 193.18544 | F17: ='Rolling Forecast'!R12 -> 0.0042603762
A18: Gross profit | C18: ='Rolling Forecast'!P14 -> 31287.836 | D18: ='Rolling Forecast'!O14 -> 32051.073 | E18: ='Rolling Forecast'!Q14 -> 763.23716 | F18: ='Rolling Forecast'!R14 -> 0.024394054
A19: EBITDA | C19: ='Rolling Forecast'!P39 -> 5357.8638 | D19: ='Rolling Forecast'!O39 -> 5123.7988 | E19: ='Rolling Forecast'!Q39 -> -234.06502 | F19: ='Rolling Forecast'!R39 -> -0.043686258
A20: EBITDA margin | C20: ='Rolling Forecast'!P40 -> 0.11815857 | D20: ='Rolling Forecast'!O40 -> 0.1125173 | E20: =D20-C20 -> -0.0056412719
A21: Net revenue (₹ crore) | C21: =C17/100 -> 453.4469 | D21: =D17/100 -> 455.37875
A23: 3. Variance-to-action log
A24: Material variances | C24: ='Variance-to-Action Log'!C27 -> 8
A25: Timing | C25: ='Variance-to-Action Log'!C28 -> 1
A26: One-off | C26: ='Variance-to-Action Log'!C29 -> 2
A27: Structural | C27: ='Variance-to-Action Log'!C30 -> 5
A28: Awaiting classification | C28: ='Variance-to-Action Log'!C31 -> 0
A29: Final action: Reforecast | C29: ='Variance-to-Action Log'!C32 -> 4
A30: Final action: Cut spend | C30: ='Variance-to-Action Log'!C33 -> 1
A31: Final action: Ignore | C31: ='Variance-to-Action Log'!C34 -> 3
A32: Analyst overrides in use | C32: ='Variance-to-Action Log'!C35 -> 1
